Workbook

Sheet README
A1: D7 INTEGRATED REVENUE MODEL, FY27–FY29
A2: Company | B2: Strata Sense Technologies is fictional; all data synthetic (MBA capstone). ₹ crore unless stated.
A3: How to use | B3: Pick a scenario in Assumptions!C4 (Base, Downside, Aggressive, CFO-capped). Flex any driver with the five sensitivity shift cells (Assumptions rows 60–64). Every sheet recalculates; the Cascade sheet shows what moved against the saved base run.
A4: Colour code | B4: Blue = input. Yellow fill = key assumption. Black = formula. Green = link to another sheet. No hard-coded plugs: every number in a calculation sheet is a formula or a labelled input.
A5: Flow | B5: Assumptions → Capacity (AE cohorts, ramp, attrition) → Bookings (capacity × win rate × deal size; pipeline required) → Channel (partner ARR, channel P&L) → ARR_bridge (quarterly) → PnL (revenue, gross margin incl. partner margin, S&M, EBITDA, CAC payback) → Investment (FY27 envelope; payback vs do-nothing) → Checks.
A6: Snapshot sheets | B6: Scenarios, Sensitivity and the 'Base (saved)' column of Cascade hold values produced by running this workbook with run_scenarios.py (script in the GitHub folder). They are labelled as saved runs; the live model is unaffected by them.
A7: Counting rule | B7: A partner-sourced deal worked by an AE is counted once, as partner ARR (Channel sheet). The AE gets 50% quota credit (compensation only). Direct bookings exclude partner-sourced deals.
A8: Q1 FY27 | B8: Q1 FY27 total new-logo ARR is the locked D4 hold-out forecast (₹8.71 cr, p50), because the quarter was already under way when the plan was set. Capacity drives bookings from Q2 FY27.
A9: Supersedes | B9: D2 capacity (₹46.5 cr need), D4 scenarios and D6 share denominators. D6 partner ARR is reproduced exactly in the Base scenario (Checks).
A10: Injects | B10: Inject 1 (₹15 cr envelope): Investment sheet. Inject 2 (HelixAsset free): win rate and churn assumptions (D5). Inject 3 (partner conflict): Channel existing-partner ARR. Inject 4 (Vajra re-tender): Inject4 sheet and ARR_bridge row 'Vajra re-tender'.

Sheet Assumptions
A1: Assumptions and scenario switch
A2: Scenario drivers by year; the Live columns (O–Q) feed the model. FY26 actual (column B) is the starting point for quarterly interpolation.
A4: SCENARIO (choose) | C4: Base | E4: Base = recommended plan inside the ₹15 cr envelope · Downside = same spend, weaker outcomes · Aggressive = ₹18 cr (extra ₹3 cr option) · CFO-capped = gated reserve never released, FY28–29 hiring frozen | T4: Base | U4: Downside | V4: Aggressive | W4: CFO-capped
A5: Scenario index | C5: =MATCH(C4,T4:W4,0) -> 1
C7: Base | F7: Downside | I7: Aggressive | L7: CFO-capped | O7: LIVE (selected)
A8: Driver | B8: FY26 actual | C8: FY27 | D8: FY28 | E8: FY29 | F8: FY27 | G8: FY28 | H8: FY29 | I8: FY27 | J8: FY28 | K8: FY29 | L8: FY27 | M8: FY28 | N8: FY29 | O8: FY27 | P8: FY28 | Q8: FY29 | R8: Source / reasoning
A9: Direct win rate on qualified deals | B9: 0.171 | C9: 0.195 | D9: 0.215 | E9: 0.225 | F9: 0.165 | G9: 0.175 | H9: 0.185 | I9: 0.21 | J9: 0.23 | K9: 0.245 | L9: 0.19 | M9: 0.205 | N9: 0.215 | O9: =CHOOSE($C$5,C9,F9,I9,L9) -> 0.195 | P9: =CHOOSE($C$5,D9,G9,J9,M9) -> 0.215 | Q9: =CHOOSE($C$5,E9,H9,K9,N9) -> 0.225 | R9: DR1 clean FY26 direct 17.1% (D1). D2 tiering mix +2.9 pts at full effect; D5 battlecards +0.6 pts beyond D2; Inject 2 holds Helix-incumbent win at 7%. Board goal 23% by FY28 not met in Base (defended in memo).
A10: Sales cycle, qualified to close (months) | B10: 8.1 | C10: 8 | D10: 7.6 | E10: 7.3 | F10: 8.4 | G10: 8.4 | H10: 8.2 | I10: 7.8 | J10: 7.2 | K10: 6.8 | L10: 8.1 | M10: 7.8 | N10: 7.5 | O10: =CHOOSE($C$5,C10,F10,I10,L10) -> 8 | P10: =CHOOSE($C$5,D10,G10,J10,M10) -> 7.6 | Q10: =CHOOSE($C$5,E10,H10,K10,N10) -> 7.3 | R10: Brief/DR1: 5.2 → 8.1 months. D4 stage-exit rules and D3 business-case discipline shorten it slowly; paid pilots (D3) add time on large deals.
A11: Average won deal at list price (₹ lakh) | B11: 71.4 | C11: 72 | D11: 74.5 | E11: 77 | F11: 70 | G11: 71 | H11: 72 | I11: 74 | J11: 78 | K11: 81 | L11: 72 | M11: 74 | N11: 76 | O11: =CHOOSE($C$5,C11,F11,I11,L11) -> 72 | P11: =CHOOSE($C$5,D11,G11,J11,M11) -> 74.5 | Q11: =CHOOSE($C$5,E11,H11,K11,N11) -> 77 | R11: DR1 FY26 won deals: ₹57.6 lakh at 19.3% discount = ₹71.4 lakh list. D2 strategic tier deals ₹71 lakh net; multi-plant expansion raises size.
A12: Average discount on won deals | B12: 0.193 | C12: 0.16 | D12: 0.15 | E12: 0.15 | F12: 0.18 | G12: 0.17 | H12: 0.17 | I12: 0.15 | J12: 0.14 | K12: 0.14 | L12: 0.16 | M12: 0.15 | N12: 0.15 | O12: =CHOOSE($C$5,C12,F12,I12,L12) -> 0.16 | P12: =CHOOSE($C$5,D12,G12,J12,M12) -> 0.15 | Q12: =CHOOSE($C$5,E12,H12,K12,N12) -> 0.15 | R12: DR1 FY26 19.3%. D3 negotiation plan and D5 discount limits: cap 15% (CFO approval above). Inject 2: no matching of free Helix offer.
A13: Qualified direct opportunities available (per year) | B13: 392 | C13: 380 | D13: 430 | E13: 470 | F13: 340 | G13: 370 | H13: 400 | I13: 400 | J13: 470 | K13: 540 | L13: 370 | M13: 400 | N13: 430 | O13: =CHOOSE($C$5,C13,F13,I13,L13) -> 380 | P13: =CHOOSE($C$5,D13,G13,J13,M13) -> 430 | Q13: =CHOOSE($C$5,E13,H13,K13,N13) -> 470 | R13: DR1 FY26: 392 qualified direct deals closed. D2: tiered accounts + ₹24 cr programme reallocation to strategic/scaled tiers; SDR capacity.
A14: AE annual attrition | B14: 0.29 | C14: 0.24 | D14: 0.22 | E14: 0.2 | F14: 0.29 | G14: 0.27 | H14: 0.25 | I14: 0.22 | J14: 0.2 | K14: 0.18 | L14: 0.26 | M14: 0.24 | N14: 0.22 | O14: =CHOOSE($C$5,C14,F14,I14,L14) -> 0.24 | P14: =CHOOSE($C$5,D14,G14,J14,M14) -> 0.22 | Q14: =CHOOSE($C$5,E14,H14,K14,N14) -> 0.2 | R14: DR3 FY26: 18 exits on ~63 AEs = 29%. Inject 1 AE retention pool (₹1.0 cr) targets 6–24-month tenure exits.
A15: Expansion ARR (% of opening ARR, annual) | B15: 0.081 | C15: 0.085 | D15: 0.095 | E15: 0.105 | F15: 0.07 | G15: 0.075 | H15: 0.08 | I15: 0.095 | J15: 0.11 | K15: 0.12 | L15: 0.08 | M15: 0.09 | N15: 0.095 | O15: =CHOOSE($C$5,C15,F15,I15,L15) -> 0.085 | P15: =CHOOSE($C$5,D15,G15,J15,M15) -> 0.095 | Q15: =CHOOSE($C$5,E15,H15,K15,N15) -> 0.105 | R15: DR3 FY26 ₹22 cr on ₹272 cr. D1: non-Helix expansion stall (₹9.9 cr at stake); Inject 1 top-30 expansion programme; D2 Lotus Motors-type plans.
A16: Contraction (% of opening ARR, annual) | B16: 0.033 | C16: 0.03 | D16: 0.025 | E16: 0.025 | F16: 0.035 | G16: 0.035 | H16: 0.03 | I16: 0.025 | J16: 0.022 | K16: 0.02 | L16: 0.03 | M16: 0.028 | N16: 0.026 | O16: =CHOOSE($C$5,C16,F16,I16,L16) -> 0.03 | P16: =CHOOSE($C$5,D16,G16,J16,M16) -> 0.025 | Q16: =CHOOSE($C$5,E16,H16,K16,N16) -> 0.025 | R16: DR3 FY26 ₹9 cr. Usage-led adoption programme (retention squad).
A17: Churn (% of opening ARR excl. Vajra, annual) | B17: 0.059 | C17: 0.05 | D17: 0.045 | E17: 0.04 | F17: 0.065 | G17: 0.06 | H17: 0.055 | I17: 0.045 | J17: 0.04 | K17: 0.035 | L17: 0.055 | M17: 0.05 | N17: 0.045 | O17: =CHOOSE($C$5,C17,F17,I17,L17) -> 0.05 | P17: =CHOOSE($C$5,D17,G17,J17,M17) -> 0.045 | Q17: =CHOOSE($C$5,E17,H17,K17,N17) -> 0.04 | R17: DR3 FY26 ₹16 cr (5.9%). Helix-incumbent churn is the driver (D1: Helix NRR 116% → 92%). Retention squads, Helix renewal protection; HelixAsset free until 31 Mar 2027 keeps FY27 elevated (Inject 2).
A18: Partners activated in the year (count) | B18: 0 | C18: 8 | D18: 9 | E18: 5 | F18: 8 | G18: 9 | H18: 5 | I18: 8 | J18: 11 | K18: 6 | L18: 8 | M18: 6 | N18: 4 | O18: =CHOOSE($C$5,C18,F18,I18,L18) -> 8 | P18: =CHOOSE($C$5,D18,G18,J18,M18) -> 9 | Q18: =CHOOSE($C$5,E18,H18,K18,N18) -> 5 | R18: D6: FY27 six prospects + P07, P10 reactivated; FY28 three held prospects + six new.
A19: Mature partner productivity (₹ cr sourced ARR / year) | B19: 0.49 | C19: 1.2 | D19: 1.2 | E19: 1.2 | F19: 0.6 | G19: 0.6 | H19: 0.6 | I19: 1.4 | J19: 1.4 | K19: 1.4 | L19: 1.2 | M19: 1.2 | N19: 1.2 | O19: =CHOOSE($C$5,C19,F19,I19,L19) -> 1.2 | P19: =CHOOSE($C$5,D19,G19,J19,M19) -> 1.2 | Q19: =CHOOSE($C$5,E19,H19,K19,N19) -> 1.2 | R19: D6: ~10 qualified deals × 34% SEA partner win rate × ₹37 lakh. FY26 actual ₹0.49 cr per active partner (India-heavy). Downside ≈ FY26 India partners.
A20: Vajra re-tender: probability of losing the account (Inject 4) | B20: 0 | C20: 0.2 | D20: 0 | E20: 0 | F20: 0.4 | G20: 0 | H20: 0 | I20: 0.15 | J20: 0 | K20: 0 | L20: 0.3 | M20: 0 | N20: 0 | O20: =CHOOSE($C$5,C20,F20,I20,L20) -> 0.2 | P20: =CHOOSE($C$5,D20,G20,J20,M20) -> 0 | Q20: =CHOOSE($C$5,E20,H20,K20,N20) -> 0 | R20: Inject 4 sheet: 45% without a plan (Helix-incumbent win/loss pattern, HelixAsset free); retention plan lowers it.
... A22: Vajra: price concession if retained | B22: 0 | C22: 0.08 | D22: 0 | E22: 0 | F22: 0.12 | G22: 0 | H22: 0 | I22: 0.06 | J22: 0 | K22: 0 | L22: 0.1 | M22: 0 | N22: 0 | O22: =CHOOSE($C$5,C22,F22,I22,L22) -> 0.08 | P22: =CHOOSE($C$5,D22,G22,J22,M22) -> 0 | Q22: =CHOOSE($C$5,E22,H22,K22,N22) -> 0 | R22: Inject 4: 3-year renewal with price lock; concession capped by D5 discount rules.
A24: NET NEW AE HIRES BY QUARTER (headcount added, on top of backfills)
A25: Scenario | C25: Q1 FY27 | D25: Q2 FY27 | E25: Q3 FY27 | F25: Q4 FY27 | G25: Q1 FY28 | H25: Q2 FY28 | I25: Q3 FY28 | J25: Q4 FY28 | K25: Q1 FY29 | L25: Q2 FY29 | M25: Q3 FY29 | N25: Q4 FY29 | R25: Note
A26: Base | C26: 0 | D26: 0 | E26: 6 | F26: 0 | G26: 4 | H26: 0 | I26: 4 | J26: 0 | K26: 4 | L26: 0 | M26: 2 | N26: 0 | R26: Inject 1: 6 AEs from Q3 FY27 (SEA-weighted). Aggressive adds 6 in Q4 FY27 = 12, the FY27 limit.
A27: Downside | C27: 0 | D27: 0 | E27: 6 | F27: 0 | G27: 4 | H27: 0 | I27: 4 | J27: 0 | K27: 4 | L27: 0 | M27: 2 | N27: 0
A28: Aggressive | C28: 0 | D28: 0 | E28: 6 | F28: 6 | G28: 5 | H28: 0 | I28: 5 | J28: 0 | K28: 4 | L28: 0 | M28: 4 | N28: 0
A29: CFO-capped | C29: 0 | D29: 0 | E29: 6 | F29: 0 | G29: 3 | H29: 0 | I29: 0 | J29: 0 | K29: 3 | L29: 0 | M29: 0 | N29: 0
A30: Live: net new AE hires | C30: =INDEX(C26:C29,$C$5) -> 0 | D30: =INDEX(D26:D29,$C$5) -> 0 | E30: =INDEX(E26:E29,$C$5) -> 6 | F30: =INDEX(F26:F29,$C$5) -> 0 | G30: =INDEX(G26:G29,$C$5) -> 4 | H30: =INDEX(H26:H29,$C$5) -> 0 | I30: =INDEX(I26:I29,$C$5) -> 4 | J30: =INDEX(J26:J29,$C$5) -> 0 | ... N30: =INDEX(N26:N29,$C$5) -> 0
A32: GLOBAL INPUTS
A33: Input | B33: Value | R33: Source / reasoning
A34: Qualified deals an AE carries at once (ramped AE) | B34: 5.4 | R34: Calibrated: FY26 392 direct qualified closes ÷ 48.5 ramped-AE years × 8.1-month cycle ÷ 12 (DR3 ae_quarterly, DR1)
A35: Ramp weight: AE tenure 0–6 months | B35: 0 | R35: D1 productivity by tenure: ₹0 / 0.29 / 0.59 / 0.89 cr per AE-year → weights 0 / 0.33 / 0.66 / 1.0
A36: Ramp weight: 6–12 months | B36: 0.33
A37: Ramp weight: 12–24 months | B37: 0.66
A38: Ramp weight: 24+ months | B38: 1
A39: Attrition multiplier: 0–6 months | B39: 0.8 | R39: DR3 exits concentrate at 6–24 months tenure (D1)
A40: Attrition multiplier: 6–12 months | B40: 1.4
A41: Attrition multiplier: 12–24 months | B41: 1.3
A42: Attrition multiplier: 24+ months | B42: 0.85
A43: AEs at 31 Mar 2026: 0–6 months | B43: 9 | R43: DR3 ae_roster (64 active)
A44: AEs at 31 Mar 2026: 6–12 months | B44: 8
A45: AEs at 31 Mar 2026: 12–24 months | B45: 9
A46: AEs at 31 Mar 2026: 24+ months | B46: 38
A47: Backfill hires in Q1 FY27 (for Q4 FY26 exits) | B47: 3.8 | R47: Holds headcount at 64 before net new hires (FY26 exits averaged 4.5 a quarter; FY27 attrition lower)
A48: Q1 FY27 total new-logo ARR (locked D4 forecast, p50) | B48: 8.71 | R48: D4_holdout_forecast_LOCKED.json (sha256 ba5b63ad…). Quarter under way when plan set.
A49: AE loaded cost FY26 (₹ cr / AE-year) | B49: 0.56 | R49: DR3: AE compensation ₹35.25 cr ÷ 62.9 AE-years
A50: Cost inflation per year | B50: 0.06 | R50: Assumption (salary inflation India)
A51: Recruiting cost per AE hire (₹ cr) | B51: 0.035 | R51: DR3 unit costs ₹3.5 lakh
A52: S&M excl. AE pay and partner commissions, FY26 (₹ cr) | B52: 60.33 | R52: DR3 sm_by_line FY26: ₹96.0 − 35.25 AE pay − 0.42 partner commissions
A53: Subscription revenue ÷ average ARR | B53: 1 | R53: DR3 FY26: ₹295.2 cr revenue on ₹295.2 cr average quarterly ARR
A54: Software cost of revenue (% of subscription revenue) | B54: 0.18 | R54: DR3 FY26 ₹53.1 cr ÷ ₹295.2 cr
A55: Hardware cost of revenue (% of hardware revenue) | B55: 0.75 | R55: DR3 FY26; unit costs: hardware ~25% gross margin
A56: R&D FY26 (₹ cr) | B56: 123.32 | R56: DR3
A57: R&D growth per year | B57: 0.06 | R57: Assumption: held near inflation; no new hardware (guardrail)
A58: G&A FY26 (₹ cr) | B58: 69.37 | R58: DR3
... A67: Partner ARR phasing: Q1 share of year | B67: 0.2 | R67: Recruits back-load each year (D6 ramp)
A68: Q2 share | B68: 0.23
A69: Q3 share | B69: 0.27
A70: Q4 share | B70: 0.3
A71: Blended year-1 partner margin FY27 | B71: 0.164 | R71: D6 tiers 10% / 18% / 22% × mix
A72: Blended year-1 partner margin FY28 | B72: 0.17 | R72: D6
A73: Blended year-1 partner margin FY29 | B73: 0.176 | R73: D6
A74: Blended renewal margin FY28 | B74: 0.065 | R74: D6
A75: Blended renewal margin FY29 | B75: 0.07 | R75: D6
A76: Channel fixed cost excl. MDF FY27 (₹ cr) | B76: 2.44 | R76: D6 Inputs (VP Channel, partner managers, enablement, PRM) = Inject 1 envelope line
A77: Channel fixed cost excl. MDF FY28 | B77: 3.46 | R77: D6
A78: Channel fixed cost excl. MDF FY29 | B78: 4 | R78: D6
A79: Partner MDF FY27 (inside existing ₹24 cr programme budget) | B79: 1.5 | R79: D6; reallocated, not incremental
A80: Partner MDF FY28 | B80: 2 | R80: D6
A81: Partner MDF FY29 | B81: 2.5 | R81: D6
A82: Direct effort share on partner deals FY27 | B82: 0.4 | R82: D6
... A94: Board growth path FY27 | B94: 0.15 | R94: Brief guardrail
A95: Board growth path FY28 | B95: 0.2
A96: Board growth path FY29 | B96: 0.22
A97: Board NRR goal FY29 | B97: 1.08 | R97: Brief objectives
A98: Gross margin floor | B98: 0.66 | R98: Guardrail
A99: CAC payback cap, every quarter (months) | B99: 30 | R99: Guardrail
A100: CAC payback cap by Q4 FY28 (months) | B100: 24 | R100: Guardrail
A101: S&M as % of ARR, FY29 cap | B101: 0.3 | R101: Guardrail (from 31%)
A102: Net new AEs in FY27, cap | B102: 12 | R102: Guardrail
A103: New channel roles, cap | B103: 6 | R103: Guardrail
A105: SENSITIVITY SHIFTS (leave at 0 for the plan; applied on top of the selected scenario)
A106: Win-rate shift (percentage points, direct and partner) | B106: 0 | R106: Cascade test: set to 3
A107: Sales-cycle shift (months) | B107: 0
A108: Discount shift (percentage points) | B108: 0 | R108: Also moves win rate by the response above
A109: Partner productivity shift (%) | B109: 0
A110: Churn shift (percentage points of annual churn) | B110: 0
A111: Share of planned improvement delivered (1 = plan; 0 = FY26 levels) | B111: 1 | R111: Applies to win, cycle, deal, discount, supply, attrition, retention rates and partner productivity

Sheet Scenarios
A1: Scenario comparison (saved runs)
A2: Values produced by run_scenarios.py: the live workbook was recalculated with each setting of Assumptions!C4. Change C4 to see any scenario live.
A4: Metric | B4: Base | C4: Downside | D4: Aggressive | E4: CFO-capped | F4: Reading
A5: ARR FY27 | B5: 350.94493 | C5: 333.83235 | D5: 360.09872 | E5: 346.60346
A6: ARR FY28 | B6: 422.67865 | C6: 368.78693 | D6: 454.96873 | E6: 407.52148
A7: ARR FY29 | B7: 525.52878 | C7: 419.05967 | D7: 598.03142 | E7: 491.60544 | F7: Board path FY29: ₹521.9 cr
A8: Growth FY27 | B8: 0.13208041 | C8: 0.076878564 | D8: 0.16160878 | E8: 0.11807568 | F8: Board path 15%; Base misses (defended in memo §4)
A9: Growth FY28 | B9: 0.20440167 | C9: 0.10470696 | D9: 0.26345556 | E9: 0.17575709
A10: Growth FY29 | B10: 0.24332937 | C10: 0.13631923 | D10: 0.31444511 | E10: 0.20633014
A11: New logo FY27 | B11: 43.716427 | C11: 35.486008 | D11: 48.231646 | E11: 42.378434
A12: New logo FY28 | B12: 65.046421 | C12: 43.151019 | D12: 79.229513 | E12: 58.769494
A13: New logo FY29 | B13: 86.948731 | C13: 54.322697 | D13: 113.23973 | E13: 75.477407
A14: NRR FY27 | B14: 0.99105967 | C14: 0.96240757 | D14: 1.0060228 | E14: 0.98137105
A15: NRR FY29 | B15: 1.0376205 | C15: 0.98901819 | D15: 1.0655495 | E15: 1.0211193
A16: Partner share FY29 | B16: 0.22668255 | C16: 0.20653908 | D16: 0.21573489 | E16: 0.23013191
A17: GM min year | B17: 0.67539296 | C17: 0.69121437 | D17: 0.66721811 | E17: 0.68000836
A18: CAC worst qtr | B18: 31.042604 | C18: 36.0498 | D18: 30.700981 | E18: 31.185478 | F18: Q1 FY27 is locked by the D4 forecast in every scenario
A19: CAC Q4 FY28 | B19: 21.211325 | C19: 30.920099 | D19: 18.255473 | E19: 22.485337
A20: CAC worst qtr from Q2 FY27 | B20: 29.439514 | C20: 36.0498 | D20: 27.170433 | E20: 29.62292 | F20: Tightest guardrail: Q3 FY27
A21: S&M/ARR FY29 | B21: 0.27015791 | C21: 0.33789343 | D21: 0.24978731 | E21: 0.27489641
A22: EBITDA FY27 | B22: -25.917193 | C22: -33.706576 | D22: -23.983317 | E22: -25.797624
A23: EBITDA FY28 | B23: 2.6009535 | C23: -32.428932 | D23: 16.829479 | E23: -2.9551076
A24: EBITDA FY29 | B24: 52.616092 | C24: -19.84217 | D24: 92.741045 | E24: 36.839843
A25: Investment FY27 | B25: 14.9508 | C25: 14.9508 | D25: 17.2512 | E25: 13.0308 | F25: Envelope ₹15 cr (₹18 cr Aggressive)
A26: Investment FY27-29 | B26: 61.853802 | C26: 61.853802 | D26: 77.716043 | E26: 48.897372
A27: Investment payback FY29 (months) | B27: 8.0187613 | C27: 35.554476 | D27: 6.6457321 | E27: 8.3755644
A28: Investment payback FY29 vs FY26-flat (months) | B28: 10.53838 | C28: never | D28: 7.876124 | E28: 12.281385 | F28: Stricter counterfactual: credits only gains beyond FY26 rates
A29: AE headcount end FY29 | B29: 83.434573 | C29: 82.280504 | D29: 93.409875 | E29: 75.472375
A30: Guardrails failed | B30: 1 | C30: 3 | D30: 1 | E30: 1 | F30: Base: only the Q1 FY27 payback (disclosed)
A31: Board-goal shortfalls | B31: 3 | C31: 5 | D31: 2 | E31: 5

Sheet Sensitivity
A1: Sensitivity of the Base plan and break-even points (saved runs)
A2: Each row flexes one driver with the Assumptions sensitivity shift cells and recalculates the whole model. Reproduce by typing the shift into Assumptions (rows marked SENSITIVITY SHIFTS).
A4: Driver and change | B4: FY29 ARR | C4: Δ vs Base | D4: FY29 growth | E4: FY27 ARR | F4: FY29 EBITDA | G4: Worst CAC payback from Q2 FY27 | H4: CAC payback Q4 FY28 | I4: Min GM | J4: Investment payback FY29 vs FY26-flat
A5: Base plan | B5: 525.52878 | C5: 0 | D5: 0.24332937 | E5: 350.94493 | F5: 52.616092 | G5: 29.439514 | H5: 21.211325 | I5: 0.67539296 | J5: 10.53838
A6: Win rate −3 pts | B6: 499.66428 | C6: -25.864506 | D6: 0.22370964 | E6: 345.59403 | F6: 33.120822 | G6: 32.215761 | H6: 23.202994 | I6: 0.68333446 | J6: 13.90258
A7: Win rate +3 pts | B7: 551.39329 | C7: 25.864506 | D7: 0.26165984 | E7: 356.29583 | F7: 72.111361 | G7: 27.15237 | H7: 19.551864 | I7: 0.6679416 | J7: 8.507648
A8: Sales cycle −1 months | B8: 526.08619 | C8: 0.55740297 | D8: 0.24306398 | E8: 351.09454 | F8: 53.080154 | G8: 29.43325 | H8: 21.198551 | I8: 0.67506136 | J8: 10.480897
A9: Sales cycle +1 months | B9: 517.38555 | C9: -8.1432378 | D9: 0.2436494 | E9: 348.00714 | F9: 45.671436 | G9: 31.05716 | H9: 21.46658 | I9: 0.67703466 | J9: 11.437681
A10: Discount −3 pts | B10: 528.81956 | C10: 3.2907719 | D10: 0.2458692 | E10: 351.5743 | F10: 55.139435 | G10: 29.147699 | H10: 20.975721 | I10: 0.67443654 | J10: 10.225465
A11: Discount +3 pts | B11: 522.07513 | C11: -3.4536564 | D11: 0.24065916 | E11: 350.27884 | F11: 49.966555 | G11: 29.755684 | H11: 21.464438 | I11: 0.67640732 | J11: 10.888756
A12: Partner productivity −30% | B12: 517.69859 | C12: -7.8301914 | D12: 0.23233251 | E12: 350.59903 | F12: 48.100258 | G12: 29.596076 | H12: 21.683508 | I12: 0.67825903 | J12: 11.314856
A13: Partner productivity +30% | B13: 533.35897 | C13: 7.8301914 | D13: 0.25419267 | E13: 351.29082 | F13: 57.131926 | G13: 29.284905 | H13: 20.762092 | I13: 0.67255748 | J13: 9.8691497
A14: Churn −2 pts | B14: 549.91886 | C14: 24.390079 | D14: 0.25867078 | E14: 357.29564 | F14: 68.767424 | G14: 29.301511 | H14: 20.919719 | I14: 0.6773366 | J14: 8.4996142
A15: Churn +2 pts | B15: 502.32063 | C15: -23.208156 | D15: 0.2284345 | E15: 344.68617 | F15: 37.130305 | G15: 29.578427 | H15: 21.504748 | I15: 0.67341574 | J15: 13.626088
A17: BREAK-EVEN: the change at which a payback test fails
A18: Test | B18: Win rate (pts vs plan) | C18: Churn (pts vs plan) | D18: Plan delivery (share of planned improvement)
A19: CAC payback > 30 months in any quarter from Q2 FY27 | B19: -0.711 | C19: 8.039 | D19: 0.777
A20: CAC payback Q4 FY28 > 24 months | B20: -4.102 | C20: never in range | D20: 0.59
A21: Investment payback vs FY26-flat > 30 months (FY29) | B21: -7.93 | C21: 6.07 | D21: 0.324
A23: Reading: the every-quarter payback test is the binding one. Q3 FY27 sits at 29.5 months, so a win rate half a point below plan breaks it; hence the Q2 FY27 trigger that holds the H2 reserve if win rate is off track. Sales-cycle gains add little because pipeline supply, not AE capacity, binds from Q3 FY27. Churn does not move CAC payback (it is measured on new and expansion ARR) but it drives NRR and FY29 ARR more than any other driver.

Sheet Cascade
A1: Cascade test: change the win rate by 3 points and every number that moves
A2: Set Assumptions!B106 to 3. 'Live' recalculates; 'Base (saved)' and '+3 pts (saved)' are values from run_scenarios.py for reference.
A4: Metric | B4: Where it shows | C4: Base (saved) | D4: +3 pts (saved) | E4: Live | F4: Live − Base | G4: Why it moves
A5: AE deal capacity FY27 (qualified deals) | B5: D2 capacity | C5: 380.3625 | D5: 380.3625 | E5: =Bookings!O9 -> 380.3625 | F5: =IF(ISNUMBER(C5),E5-C5,"") -> 0 | G5: Does not move: capacity is AEs × deals carried ÷ cycle
A6: Qualified deals worked FY27 | B6: D2 capacity | C6: 374.43467 | D6: 374.43467 | E6: =Bookings!O11 -> 374.43467 | F6: =IF(ISNUMBER(C6),E6-C6,"") -> 0 | G6: Does not move
A7: Deals won FY27 | B7: D2 / D4 | C7: 67.276735 | D7: 75.673443 | E7: =Bookings!O13 -> 67.276735 | F7: =IF(ISNUMBER(C7),E7-C7,"") -> 0 | G7: More of the same deals close
A8: Direct new-logo ARR FY27 (₹ cr) | B8: D4 forecast | C8: 40.020427 | D8: 45.04037 | E8: =Bookings!O14 -> 40.020427 | F8: =IF(ISNUMBER(C8),E8-C8,"") -> 0 | G8: Q2–Q4 move; Q1 is the locked forecast
A9: Direct new-logo ARR Q2 FY27 (₹ cr) | B9: D4 next-quarter forecast | C9: 10.115576 | D9: 11.773868 | E9: =Bookings!D14 -> 10.115576 | F9: =IF(ISNUMBER(C9),E9-C9,"") -> 0
A10: Pipeline required FY27 (₹ cr) | B10: D4 coverage | C10: 214.53832 | D10: 207.69674 | E10: =Bookings!O15 -> 214.53832 | F10: =IF(ISNUMBER(C10),E10-C10,"") -> 0 | G10: Required pipeline = bookings ÷ win rate
A11: Board path FY27: capacity surplus / (gap), deals | B11: D2 account plan capacity | C11: -32.115126 | D11: 27.752722 | E11: =Bookings!O24 -> -32.115126 | F11: =IF(ISNUMBER(C11),E11-C11,"") -> 0 | G11: Fewer deals needed at a higher win rate
A12: Board path FY27: extra ramped AEs needed | B12: D2 / Inject 1 hiring | C12: 3.9834155 | D12: 0 | E12: =Bookings!O25 -> 3.9834155 | F12: =IF(ISNUMBER(C12),E12-C12,"") -> 0
A13: Board path FY28: capacity surplus / (gap), deals | B13: D2 account plan capacity | C13: -17.236727 | D13: 84.922404 | E13: =Bookings!P24 -> -17.236727 | F13: =IF(ISNUMBER(C13),E13-C13,"") -> 0
A14: Partner-sourced ARR FY27 (₹ cr) | B14: D6 channel | C14: 3.696 | D14: 4.0221176 | E14: =Channel!O12 -> 3.696 | F14: =IF(ISNUMBER(C14),E14-C14,"") -> 0 | G14: Partner win rate 34% → 37% scales partner productivity
A15: Partner-sourced ARR FY29 (₹ cr) | B15: D6 channel | C15: 19.70976 | D15: 21.448856 | E15: =Channel!Q12 -> 19.70976 | F15: =IF(ISNUMBER(C15),E15-C15,"") -> 0
A16: Partner share of new logo FY29 | B16: D6 / board objective 5 | C16: 0.22668255 | D16: 0.21930467 | E16: =Channel!Q13 -> 0.22668255 | F16: =IF(ISNUMBER(C16),E16-C16,"") -> 0 | G16: Both numerator and denominator rise
A17: Channel saving vs direct FY29 (₹ cr) | B17: D6 channel P&L | C17: 11.708855 | D17: 13.315518 | E17: =Channel!Q22 -> 11.708855 | F17: =IF(ISNUMBER(C17),E17-C17,"") -> 0
A18: Partner pipeline required FY29 (₹ cr) | B18: D6 channel | C18: 57.969882 | D18: 57.969882 | E18: =Channel!Q25 -> 57.969882 | F18: =IF(ISNUMBER(C18),E18-C18,"") -> 0
A19: Total new-logo ARR FY29 (₹ cr) | B19: D7 bridge | C19: 86.948731 | D19: 97.803918 | E19: =ARR_bridge!Q17 -> 86.948731 | F19: =IF(ISNUMBER(C19),E19-C19,"") -> 0
A20: Closing ARR FY27 (₹ cr) | B20: D7 bridge | C20: 350.94493 | D20: 356.29583 | E20: =ARR_bridge!O12 -> 350.94493 | F20: =IF(ISNUMBER(C20),E20-C20,"") -> 0
A21: Closing ARR FY28 (₹ cr) | B21: D7 bridge | C21: 422.67865 | D21: 437.038 | E21: =ARR_bridge!P12 -> 422.67865 | F21: =IF(ISNUMBER(C21),E21-C21,"") -> 0
A22: Closing ARR FY29 (₹ cr) | B22: D7 bridge / D8 | C22: 525.52878 | D22: 551.39329 | E22: =ARR_bridge!Q12 -> 525.52878 | F22: =IF(ISNUMBER(C22),E22-C22,"") -> 0 | G22: Also compounds: more customers expand and renew
A23: Growth FY27 | B23: Growth guardrail | C23: 0.13208041 | D23: 0.14934137 | E23: =ARR_bridge!O18 -> 0.13208041 | F23: =IF(ISNUMBER(C23),E23-C23,"") -> 0
A24: Growth FY29 | B24: Growth guardrail | C24: 0.24332937 | D24: 0.26165984 | E24: =ARR_bridge!Q18 -> 0.24332937 | F24: =IF(ISNUMBER(C24),E24-C24,"") -> 0
A25: Closing ARR FY29 vs board path (₹ cr) | B25: D8 | C25: 3.6127833 | D25: 29.477289 | E25: =ARR_bridge!Q20 -> 3.6127833 | F25: =IF(ISNUMBER(C25),E25-C25,"") -> 0
A26: NRR FY29 | B26: Retention | C26: 1.0376205 | D26: 1.0378717 | E26: =ARR_bridge!Q21 -> 1.0376205 | F26: =IF(ISNUMBER(C26),E26-C26,"") -> 0 | G26: Does not move: win rate affects new logos only
A27: Revenue FY29 (₹ cr) | B27: P&L | C27: 619.39709 | D27: 653.42272 | E27: =PnL!Q8 -> 619.39709 | F27: =IF(ISNUMBER(C27),E27-C27,"") -> 0 | G27: Subscription and hardware both rise
A28: Gross margin after partner margin FY29 | B28: GM guardrail | C28: 0.67727112 | D28: 0.67183925 | E28: =PnL!Q15 -> 0.67727112 | F28: =IF(ISNUMBER(C28),E28-C28,"") -> 0 | G28: More hardware (25% margin) dilutes GM slightly
A29: EBITDA FY27 (₹ cr) | B29: P&L | C29: -25.917193 | D29: -22.407713 | E29: =PnL!O22 -> -25.917193 | F29: =IF(ISNUMBER(C29),E29-C29,"") -> 0
A30: EBITDA FY29 (₹ cr) | B30: P&L | C30: 52.616092 | D30: 72.111361 | E30: =PnL!Q22 -> 52.616092 | F30: =IF(ISNUMBER(C30),E30-C30,"") -> 0
A31: CAC payback, worst quarter (months) | B31: Payback guardrail | C31: 31.042604 | D31: 31.047369 | E31: =MAX(PnL!C24:N24) -> 31.042604 | F31: =IF(ISNUMBER(C31),E31-C31,"") -> 0 | G31: Q1 FY27 is locked, so the worst quarter barely moves
A32: CAC payback Q4 FY28 (months) | B32: Payback guardrail | C32: 21.211325 | D32: 19.551864 | E32: =PnL!J24 -> 21.211325 | F32: =IF(ISNUMBER(C32),E32-C32,"") -> 0
A33: S&M as % of ARR FY29 | B33: S&M guardrail | C33: 0.27015791 | D33: 0.25748547 | E33: =PnL!Q25 -> 0.27015791 | F33: =IF(ISNUMBER(C33),E33-C33,"") -> 0
A34: Investment payback vs do-nothing, FY29 (months) | B34: Inject 1 / D8 | C34: 8.0187613 | D34: 6.7972435 | E34: =Investment!L29 -> 8.0187613 | F34: =IF(ISNUMBER(C34),E34-C34,"") -> 0

Sheet Checks
A1: Checks and guardrails
A2: Every guardrail in the brief. A failed test is disclosed with its fix in the memo, not hidden.
A4: Check | B4: Value | C4: Result | D4: Threshold / note
A5: ARR bridge ties every quarter (sum of absolute differences) | B5: =SUMPRODUCT(ABS(ARR_bridge!C13:N13)) -> 0 | C5: =IF(B5<0.0001,"OK","ERROR") -> OK | D5: Opening + new + expansion − contraction − churn = closing
A6: No formula errors in model sheets | B6: =SUMPRODUCT(--ISERROR(Capacity!C5:Q40))+SUMPRODUCT(--ISERROR(Bookings!C5:Q30))+SUMPRODUCT(--ISERROR(ARR_bridge!C5:Q30))+SUMPRODUCT(--ISERROR(PnL!C5:Q30))+SUMPRODUCT(--ISERROR(Channel!O5:Q30)) -> 0 | C6: =IF(B6=0,"OK","ERROR") -> OK
A7: Total new logo = direct + partner (counted once) | B7: =ABS(SUM(ARR_bridge!O17:Q17)-SUM(Bookings!O14:Q14)-SUM(Channel!O12:Q12)) -> 0 | C7: =IF(B7<0.0001,"OK","ERROR") -> OK | D7: No double counting
A8: Investment within FY27 envelope | B8: =Investment!J20 -> 14.9508 | C8: =IF(B8<=Investment!J21+0.0001,"OK","OVER") -> OK | D8: ₹15 cr (₹18 cr Aggressive)
A9: Gross margin after partner margin ≥ 66%, lowest year | B9: =MIN(PnL!O15:Q15) -> 0.67539296 | C9: =IF(B9>=Assumptions!$B$98,"OK","BREACH") -> OK | D9: Every year
A10: CAC payback ≤ 30 months, worst quarter | B10: =MAX(PnL!C24:N24) -> 31.042604 | C10: =IF(B10<=Assumptions!$B$99,"OK","BREACH") -> BREACH | D10: Every quarter
A11: CAC payback ≤ 24 months by Q4 FY28 | B11: =PnL!J24 -> 21.211325 | C11: =IF(B11<=Assumptions!$B$100,"OK","BREACH") -> OK | D11: Q4 FY28
A12: S&M ≤ 30% of ARR by FY29 | B12: =PnL!Q25 -> 0.27015791 | C12: =IF(B12<=Assumptions!$B$101,"OK","BREACH") -> OK | D12: FY26 31%
A13: Net new AEs in FY27 ≤ 12 | B13: =Capacity!F35 -> 6 | C13: =IF(B13<=Assumptions!$B$102,"OK","OVER") -> OK | D13: 64 → 76 at most
A14: AE headcount end-FY27 ≤ 76 | B14: =Capacity!F30 -> 69.373108 | C14: =IF(B14<=76.0001,"OK","OVER") -> OK
A15: New channel roles FY27 ≤ 6 | B15: =3 -> 3 | C15: =IF(B15<=Assumptions!$B$103,"OK","OVER") -> OK | D15: VP Channel + 2 partner managers (D6)
A16: Pipeline arithmetic: deals worked ≤ AE capacity every quarter | B16: =SUMPRODUCT(--(Bookings!D11:N11>Bookings!D9:N9+0.0001)) -> 0 | C16: =IF(B16=0,"OK","ERROR") -> OK | D16: Required pipeline = bookings ÷ win rate (Bookings row 15)
A17: Pipeline arithmetic: deals worked ≤ pipeline supply every quarter | B17: =SUMPRODUCT(--(Bookings!D11:N11>Bookings!D10:N10+0.0001)) -> 0 | C17: =IF(B17=0,"OK","ERROR") -> OK
A18: Partner pipeline required ≤ partner capacity, every year | B18: =SUMPRODUCT(--(Channel!O25:Q25>Channel!O26:Q26+0.0001)) -> 0 | C18: =IF(B18=0,"OK","CHECK") -> OK
A19: Growth FY27 ≥ 15% | B19: =ARR_bridge!O18 -> 0.13208041 | C19: =IF(B19>=Assumptions!$B$94,"OK","SHORTFALL") -> SHORTFALL | D19: Or defended shortfall (memo §4)
A20: Growth FY28 ≥ 20% | B20: =ARR_bridge!P18 -> 0.20440167 | C20: =IF(B20>=Assumptions!$B$95,"OK","SHORTFALL") -> OK
A21: Growth FY29 ≥ 22% | B21: =ARR_bridge!Q18 -> 0.24332937 | C21: =IF(B21>=Assumptions!$B$96,"OK","SHORTFALL") -> OK
A22: FY29 NRR vs 108% goal | B22: =ARR_bridge!Q21 -> 1.0376205 | C22: =IF(B22>=Assumptions!$B$97,"OK","SHORTFALL") -> SHORTFALL
A23: Partner share of new logo FY29 ≥ 25% | B23: =Channel!Q13 -> 0.22668255 | C23: =IF(B23>=0.25,"OK","SHORTFALL") -> SHORTFALL | D23: Board objective 5
A24: D6 reconciliation: Base partner ARR FY27+FY28+FY29 = ₹33.27 cr | B24: =SUM(Channel!O12:Q12) -> 33.26736 | C24: =IF(Assumptions!$C$5<>1,"n/a",IF(ABS(B24-33.268)<0.01,"OK","DIFF")) -> OK | D24: Only tested in Base with shifts at 0
A25: Sensitivity shifts all zero (plan view) | B25: =ABS(Assumptions!B106)+ABS(Assumptions!B107)+ABS(Assumptions!B108)+ABS(Assumptions!B109)+ABS(Assumptions!B110)+ABS(1-Assumptions!B111) -> 0 | C25: =IF(B25=0,"OK","SHIFTED") -> OK | D25: Reminder when flexing
A27: Count of failed guardrails (ERROR / OVER / BREACH) | C27: =COUNTIF(C5:C25,"ERROR")+COUNTIF(C5:C25,"OVER")+COUNTIF(C5:C25,"BREACH") -> 1
A28: Count of shortfalls against board goals (disclosed and defended) | C28: =COUNTIF(C5:C25,"SHORTFALL") -> 3

Sheet Capacity
A1: AE capacity: hiring, ramp, attrition
A2: Cohorts by tenure band. Hires enter the 0–6 month band; half of each 6-month band and a quarter of the 12–24 band move up each quarter. Leavers are backfilled the next quarter.
A4: Line | B4: FY26 / start | C4: Q1 FY27 | D4: Q2 FY27 | E4: Q3 FY27 | F4: Q4 FY27 | G4: Q1 FY28 | H4: Q2 FY28 | I4: Q3 FY28 | J4: Q4 FY28 | K4: Q1 FY29 | L4: Q2 FY29 | M4: Q3 FY29 | N4: Q4 FY29 | O4: FY27 | P4: FY28 | Q4: FY29 | R4: Note / source
A5: Net new AE hires | C5: =Assumptions!C30 -> 0 | D5: =Assumptions!D30 -> 0 | E5: =Assumptions!E30 -> 6 | F5: =Assumptions!F30 -> 0 | G5: =Assumptions!G30 -> 4 | H5: =Assumptions!H30 -> 0 | I5: =Assumptions!I30 -> 4 | J5: =Assumptions!J30 -> 0 | ... N5: =Assumptions!N30 -> 0 | O5: =SUM(C5:F5) -> 6 | P5: =SUM(G5:J5) -> 8 | Q5: =SUM(K5:N5) -> 6
A6: Backfill hires (last quarter's leavers) | C6: =Assumptions!$B$47 -> 3.8 | D6: =C31 -> 3.9264 | E6: =D31 -> 4.0166793 | F6: =E31 -> 4.3295456 | G6: =F31 -> 4.4268916 | H6: =G31 -> 4.2528543 | I6: =H31 -> 4.3082561 | J6: =I31 -> 4.4819259 | K6: =J31 -> 4.518562 | ... N6: =M31 -> 4.3657887
A7: Quarterly attrition rate (base) | C7: =(Assumptions!$B$14+(Assumptions!$O$14-Assumptions!$B$14)*Assumptions!$B$111)/4 -> 0.06 | D7: =(Assumptions!$B$14+(Assumptions!$O$14-Assumptions!$B$14)*Assumptions!$B$111)/4 -> 0.06 | E7: =(Assumptions!$B$14+(Assumptions!$O$14-Assumptions!$B$14)*Assumptions!$B$111)/4 -> 0.06 | F7: =(Assumptions!$B$14+(Assumptions!$O$14-Assumptions!$B$14)*Assumptions!$B$111)/4 -> 0.06 | G7: =(Assumptions!$B$14+(Assumptions!$P$14-Assumptions!$B$14)*Assumptions!$B$111)/4 -> 0.055 | H7: =(Assumptions!$B$14+(Assumptions!$P$14-Assumptions!$B$14)*Assumptions!$B$111)/4 -> 0.055 | I7: =(Assumptions!$B$14+(Assumptions!$P$14-Assumptions!$B$14)*Assumptions!$B$111)/4 -> 0.055 | J7: =(Assumptions!$B$14+(Assumptions!$P$14-Assumptions!$B$14)*Assumptions!$B$111)/4 -> 0.055 | K7: =(Assumptions!$B$14+(Assumptions!$Q$14-Assumptions!$B$14)*Assumptions!$B$111)/4 -> 0.05 | L7: =(Assumptions!$B$14+(Assumptions!$Q$14-Assumptions!$B$14)*Assumptions!$B$111)/4 -> 0.05 | M7: =(Assumptions!$B$14+(Assumptions!$Q$14-Assumptions!$B$14)*Assumptions!$B$111)/4 -> 0.05 | N7: =(Assumptions!$B$14+(Assumptions!$Q$14-Assumptions!$B$14)*Assumptions!$B$111)/4 -> 0.05
A9: Band 0–6 months
A10: start | C10: =B13+C5+C6 -> 12.8 | D10: =C13+D5+D6 -> 10.0192 | E10: =D13+E5+E6 -> 14.785818 | F10: =E13+F5+F6 -> 11.367595 | G10: =F13+G5+G6 -> 13.837867 | H10: =G13+H5+H6 -> 10.867355 | I10: =H13+I5+I6 -> 13.502852 | J10: =I13+J5+J6 -> 10.936289 | ... N10: =M13+N5+N6 -> 9.8892077
A11: exits | C11: =C10*C7*Assumptions!$B$39 -> 0.6144 | D11: =D10*D7*Assumptions!$B$39 -> 0.4809216 | E11: =E10*E7*Assumptions!$B$39 -> 0.70971929 | F11: =F10*F7*Assumptions!$B$39 -> 0.54564457 | G11: =G10*G7*Assumptions!$B$39 -> 0.60886615 | H11: =H10*H7*Assumptions!$B$39 -> 0.47816361 | I11: =I10*I7*Assumptions!$B$39 -> 0.59412547 | J11: =J10*J7*Assumptions!$B$39 -> 0.48119672 | ... N11: =N10*N7*Assumptions!$B$39 -> 0.39556831
A12: moving up | C12: =(C10-C11)*0.5 -> 6.0928 | D12: =(D10-D11)*0.5 -> 4.7691392 | E12: =(E10-E11)*0.5 -> 7.0380496 | F12: =(F10-F11)*0.5 -> 5.4109753 | G12: =(G10-G11)*0.5 -> 6.6145004 | H12: =(H10-H11)*0.5 -> 5.1945956 | I12: =(I10-I11)*0.5 -> 6.4543631 | J12: =(J10-J11)*0.5 -> 5.2275461 | ... N12: =(N10-N11)*0.5 -> 4.7468197
A13: end | B13: =Assumptions!$B$43 -> 9 | C13: =C10-C11-C12 -> 6.0928 | D13: =D10-D11-D12 -> 4.7691392 | E13: =E10-E11-E12 -> 7.0380496 | F13: =F10-F11-F12 -> 5.4109753 | G13: =G10-G11-G12 -> 6.6145004 | H13: =H10-H11-H12 -> 5.1945956 | I13: =I10-I11-I12 -> 6.4543631 | J13: =J10-J11-J12 -> 5.2275461 | ... N13: =N10-N11-N12 -> 4.7468197
A14: Band 6–12 months
A15: start | C15: =B18 -> 8 | D15: =C18 -> 9.7568 | E15: =D18 -> 9.2377536 | F15: =E18 -> 11.268941 | G15: =F18 -> 10.57215 | H15: =G18 -> 11.493548 | I15: =H18 -> 10.498868 | J15: =I18 -> 11.299591 | ... N15: =M18 -> 10.423305
A16: exits | C16: =C15*C7*Assumptions!$B$40 -> 0.672 | D16: =D15*D7*Assumptions!$B$40 -> 0.8195712 | E16: =E15*E7*Assumptions!$B$40 -> 0.7759713 | F16: =F15*F7*Assumptions!$B$40 -> 0.94659102 | G16: =G15*G7*Assumptions!$B$40 -> 0.81405556 | H16: =H15*H7*Assumptions!$B$40 -> 0.88500317 | I16: =I15*I7*Assumptions!$B$40 -> 0.80841282 | J16: =J15*J7*Assumptions!$B$40 -> 0.87006847 | ... N16: =N15*N7*Assumptions!$B$40 -> 0.72963136
A17: moving up | C17: =(C15-C16)*0.5 -> 3.664 | D17: =(D15-D16)*0.5 -> 4.4686144 | E17: =(E15-E16)*0.5 -> 4.2308911 | F17: =(F15-F16)*0.5 -> 5.1611749 | G17: =(G15-G16)*0.5 -> 4.8790473 | H17: =(H15-H16)*0.5 -> 5.3042723 | I17: =(I15-I16)*0.5 -> 4.8452275 | J17: =(J15-J16)*0.5 -> 5.2147611 | ... N17: =(N15-N16)*0.5 -> 4.8468369
A18: end | B18: =Assumptions!$B$44 -> 8 | C18: =C15-C16-C17+C12 -> 9.7568 | D18: =D15-D16-D17+D12 -> 9.2377536 | E18: =E15-E16-E17+E12 -> 11.268941 | F18: =F15-F16-F17+F12 -> 10.57215 | G18: =G15-G16-G17+G12 -> 11.493548 | H18: =H15-H16-H17+H12 -> 10.498868 | I18: =I15-I16-I17+I12 -> 11.299591 | J18: =J15-J16-J17+J12 -> 10.442307 | ... N18: =N15-N16-N17+N12 -> 9.5936566
A19: Band 12–24 months
A20: start | C20: =B23 -> 9 | D20: =C23 -> 9.8875 | E20: =D23 -> 11.305821 | F20: =E23 -> 12.048866 | G20: =F23 -> 13.492966 | H20: =G23 -> 14.275211 | I20: =H23 -> 15.245173 | J20: =I23 -> 15.461585 | ... N20: =M23 -> 16.533726
A21: exits | C21: =C20*C7*Assumptions!$B$41 -> 0.702 | D21: =D20*D7*Assumptions!$B$41 -> 0.771225 | E21: =E20*E7*Assumptions!$B$41 -> 0.88185401 | F21: =F20*F7*Assumptions!$B$41 -> 0.93981156 | G21: =G20*G7*Assumptions!$B$41 -> 0.96474705 | H21: =H20*H7*Assumptions!$B$41 -> 1.0206776 | I21: =I20*I7*Assumptions!$B$41 -> 1.0900298 | J21: =J20*J7*Assumptions!$B$41 -> 1.1055033 | ... N21: =N20*N7*Assumptions!$B$41 -> 1.0746922
A22: moving up | C22: =(C20-C21)*0.25 -> 2.0745 | D22: =(D20-D21)*0.25 -> 2.2790687 | E22: =(E20-E21)*0.25 -> 2.6059917 | F22: =(F20-F21)*0.25 -> 2.7772636 | G22: =(G20-G21)*0.25 -> 3.1320547 | H22: =(H20-H21)*0.25 -> 3.3136334 | I22: =(I20-I21)*0.25 -> 3.5387857 | J22: =(J20-J21)*0.25 -> 3.5890203 | ... N22: =(N20-N21)*0.25 -> 3.8647584
A23: end | B23: =Assumptions!$B$45 -> 9 | C23: =C20-C21-C22+C17 -> 9.8875 | D23: =D20-D21-D22+D17 -> 11.305821 | E23: =E20-E21-E22+E17 -> 12.048866 | F23: =F20-F21-F22+F17 -> 13.492966 | G23: =G20-G21-G22+G17 -> 14.275211 | H23: =H20-H21-H22+H17 -> 15.245173 | I23: =I20-I21-I22+I17 -> 15.461585 | J23: =J20-J21-J22+J17 -> 15.981822 | ... N23: =N20-N21-N22+N17 -> 16.441112
A24: Band 24+ months
A25: start | C25: =B28 -> 38 | D25: =C28 -> 38.1365 | E25: =D28 -> 38.470607 | F25: =E28 -> 39.114598 | G25: =F28 -> 39.897017 | H25: =G28 -> 41.163886 | I25: =H28 -> 42.553108 | J25: =I28 -> 44.102536 | ... N25: =M28 -> 50.953761
A26: exits | C26: =C25*C7*Assumptions!$B$42 -> 1.938 | D26: =D25*D7*Assumptions!$B$42 -> 1.9449615 | E26: =E25*E7*Assumptions!$B$42 -> 1.962001 | F26: =F25*F7*Assumptions!$B$42 -> 1.9948445 | G26: =G25*G7*Assumptions!$B$42 -> 1.8651855 | H26: =H25*H7*Assumptions!$B$42 -> 1.9244117 | I26: =I25*I7*Assumptions!$B$42 -> 1.9893578 | J26: =J25*J7*Assumptions!$B$42 -> 2.0617936 | ... N26: =N25*N7*Assumptions!$B$42 -> 2.1655349
A27: moving up | C27: =(C25-C26)*0 -> 0 | D27: =(D25-D26)*0 -> 0 | E27: =(E25-E26)*0 -> 0 | F27: =(F25-F26)*0 -> 0 | G27: =(G25-G26)*0 -> 0 | H27: =(H25-H26)*0 -> 0 | I27: =(I25-I26)*0 -> 0 | J27: =(J25-J26)*0 -> 0 | ... N27: =(N25-N26)*0 -> 0
A28: end | B28: =Assumptions!$B$46 -> 38 | C28: =C25-C26-C27+C22 -> 38.1365 | D28: =D25-D26-D27+D22 -> 38.470607 | E28: =E25-E26-E27+E22 -> 39.114598 | F28: =F25-F26-F27+F22 -> 39.897017 | G28: =G25-G26-G27+G22 -> 41.163886 | H28: =H25-H26-H27+H22 -> 42.553108 | I28: =I25-I26-I27+I22 -> 44.102536 | J28: =J25-J26-J27+J22 -> 45.629763 | ... N28: =N25-N26-N27+N22 -> 52.652985
A30: AE headcount, end of quarter | B30: =SUM(B13,B18,B23,B28) -> 64 | C30: =C13+C18+C23+C28 -> 63.8736 | D30: =D13+D18+D23+D28 -> 63.783321 | E30: =E13+E18+E23+E28 -> 69.470454 | F30: =F13+F18+F23+F28 -> 69.373108 | G30: =G13+G18+G23+G28 -> 73.547146 | H30: =H13+H18+H23+H28 -> 73.491744 | I30: =I13+I18+I23+I28 -> 77.318074 | J30: =J13+J18+J23+J28 -> 77.281438 | ... N30: =N13+N18+N23+N28 -> 83.434573 | O30: =F30 -> 69.373108 | P30: =J30 -> 77.281438 | Q30: =N30 -> 83.434573 | R30: Guardrail: ≤ 76 at end-FY27 (64 + 12)
A31: Leavers in quarter | C31: =C11+C16+C21+C26 -> 3.9264 | D31: =D11+D16+D21+D26 -> 4.0166793 | E31: =E11+E16+E21+E26 -> 4.3295456 | F31: =F11+F16+F21+F26 -> 4.4268916 | G31: =G11+G16+G21+G26 -> 4.2528543 | H31: =H11+H16+H21+H26 -> 4.3082561 | I31: =I11+I16+I21+I26 -> 4.4819259 | J31: =J11+J16+J21+J26 -> 4.518562 | ... N31: =N11+N16+N21+N26 -> 4.3654267 | O31: =SUM(C31:F31) -> 16.699517 | P31: =SUM(G31:J31) -> 17.561598 | Q31: =SUM(K31:N31) -> 17.285857
A32: AE-years in quarter (for cost) | C32: =(C10-C11/2+C15-C16/2+C20-C21/2+C25-C26/2)/4 -> 16.4592 | D32: =(D10-D11/2+D15-D16/2+D20-D21/2+D25-D26/2)/4 -> 16.447915 | E32: =(E10-E11/2+E15-E16/2+E20-E21/2+E25-E26/2)/4 -> 17.908807 | F32: =(F10-F11/2+F15-F16/2+F20-F21/2+F25-F26/2)/4 -> 17.896639 | G32: =(G10-G11/2+G15-G16/2+G20-G21/2+G25-G26/2)/4 -> 18.918393 | H32: =(H10-H11/2+H15-H16/2+H20-H21/2+H25-H26/2)/4 -> 18.911468 | I32: =(I10-I11/2+I15-I16/2+I20-I21/2+I25-I26/2)/4 -> 19.889759 | J32: =(J10-J11/2+J15-J16/2+J20-J21/2+J25-J26/2)/4 -> 19.88518 | ... N32: =(N10-N11/2+N15-N16/2+N20-N21/2+N25-N26/2)/4 -> 21.404322 | O32: =SUM(C32:F32) -> 68.71256 | P32: =SUM(G32:J32) -> 77.6048 | Q32: =SUM(K32:N32) -> 84.639268
A33: Ramped-AE equivalents (quarter average) | C33: =(C10-C11/2)*Assumptions!$B$35+(C15-C16/2)*Assumptions!$B$36+(C20-C21/2)*Assumptions!$B$37+(C25-C26/2)*Assumptions!$B$38 -> 45.26846 | D33: =(D10-D11/2)*Assumptions!$B$35+(D15-D16/2)*Assumptions!$B$36+(D20-D21/2)*Assumptions!$B$37+(D25-D26/2)*Assumptions!$B$38 -> 46.51978 | E33: =(E10-E11/2)*Assumptions!$B$35+(E15-E16/2)*Assumptions!$B$36+(E20-E21/2)*Assumptions!$B$37+(E25-E26/2)*Assumptions!$B$38 -> 47.58086 | F33: =(F10-F11/2)*Assumptions!$B$35+(F15-F16/2)*Assumptions!$B$36+(F20-F21/2)*Assumptions!$B$37+(F25-F26/2)*Assumptions!$B$38 -> 49.321852 | G33: =(G10-G11/2)*Assumptions!$B$35+(G15-G16/2)*Assumptions!$B$36+(G20-G21/2)*Assumptions!$B$37+(G25-G26/2)*Assumptions!$B$38 -> 50.905906 | H33: =(H10-H11/2)*Assumptions!$B$35+(H15-H16/2)*Assumptions!$B$36+(H20-H21/2)*Assumptions!$B$37+(H25-H26/2)*Assumptions!$B$38 -> 52.933341 | I33: =(I10-I11/2)*Assumptions!$B$35+(I15-I16/2)*Assumptions!$B$36+(I20-I21/2)*Assumptions!$B$37+(I25-I26/2)*Assumptions!$B$38 -> 54.591771 | J33: =(J10-J11/2)*Assumptions!$B$35+(J15-J16/2)*Assumptions!$B$36+(J20-J21/2)*Assumptions!$B$37+(J25-J26/2)*Assumptions!$B$38 -> 56.496772 | ... N33: =(N10-N11/2)*Assumptions!$B$35+(N15-N16/2)*Assumptions!$B$36+(N20-N21/2)*Assumptions!$B$37+(N25-N26/2)*Assumptions!$B$38 -> 63.747906 | O33: =AVERAGE(C33:F33) -> 47.172738 | P33: =AVERAGE(G33:J33) -> 53.731948 | Q33: =AVERAGE(K33:N33) -> 61.082829 | R33: Weights 0 / 0.33 / 0.66 / 1.0 by tenure band (D1). FY26 actual: 48.5 ramped-AE years.
A34: Effective annual attrition | C34: =C31*4/(C30+C31) -> 0.23164602 | D34: =D31*4/(D30+D31) -> 0.23697223 | E34: =E31*4/(E30+E31) -> 0.23466372 | F34: =F31*4/(F30+F31) -> 0.23993993 | G34: =G31*4/(G30+G31) -> 0.21865575 | H34: =H31*4/(H30+H31) -> 0.22150417 | I34: =I31*4/(I30+I31) -> 0.21916508 | J34: =J31*4/(J30+J31) -> 0.22095658 | ... N34: =N31*4/(N30+N31) -> 0.19888049
A35: Cumulative net new AEs (from 64) | C35: =SUM($C$5:C5) -> 0 | D35: =SUM($C$5:D5) -> 0 | E35: =SUM($C$5:E5) -> 6 | F35: =SUM($C$5:F5) -> 6 | G35: =SUM($C$5:G5) -> 10 | H35: =SUM($C$5:H5) -> 10 | I35: =SUM($C$5:I5) -> 14 | J35: =SUM($C$5:J5) -> 14 | ... N35: =SUM($C$5:N5) -> 20

Sheet Bookings
A1: Direct new-logo bookings and pipeline required
A2: Capacity (ramped AEs × deals carried × 3 ÷ cycle) meets pipeline supply; bookings = deals worked × win rate × net deal size. Q1 FY27 = locked D4 forecast.
A4: Line | B4: FY26 / start | C4: Q1 FY27 | D4: Q2 FY27 | E4: Q3 FY27 | F4: Q4 FY27 | G4: Q1 FY28 | H4: Q2 FY28 | I4: Q3 FY28 | J4: Q4 FY28 | K4: Q1 FY29 | L4: Q2 FY29 | M4: Q3 FY29 | N4: Q4 FY29 | O4: FY27 | P4: FY28 | Q4: FY29 | R4: Note / source
A5: Win rate (incl. shifts) | C5: =MAX(0.01,(Assumptions!$B$9+((Assumptions!$B$9+(Assumptions!$O$9-Assumptions!$B$9)*Assumptions!$B$111)-Assumptions!$B$9)*1/4)+Assumptions!$B$106/100+Assumptions!$B$86*Assumptions!$B$108/100*100/100) -> 0.177 | D5: =MAX(0.01,(Assumptions!$B$9+((Assumptions!$B$9+(Assumptions!$O$9-Assumptions!$B$9)*Assumptions!$B$111)-Assumptions!$B$9)*2/4)+Assumptions!$B$106/100+Assumptions!$B$86*Assumptions!$B$108/100*100/100) -> 0.183 | E5: =MAX(0.01,(Assumptions!$B$9+((Assumptions!$B$9+(Assumptions!$O$9-Assumptions!$B$9)*Assumptions!$B$111)-Assumptions!$B$9)*3/4)+Assumptions!$B$106/100+Assumptions!$B$86*Assumptions!$B$108/100*100/100) -> 0.189 | F5: =MAX(0.01,(Assumptions!$B$9+((Assumptions!$B$9+(Assumptions!$O$9-Assumptions!$B$9)*Assumptions!$B$111)-Assumptions!$B$9)*4/4)+Assumptions!$B$106/100+Assumptions!$B$86*Assumptions!$B$108/100*100/100) -> 0.195 | G5: =MAX(0.01,((Assumptions!$B$9+(Assumptions!$O$9-Assumptions!$B$9)*Assumptions!$B$111)+((Assumptions!$B$9+(Assumptions!$P$9-Assumptions!$B$9)*Assumptions!$B$111)-(Assumptions!$B$9+(Assumptions!$O$9-Assumptions!$B$9)*Assumptions!$B$111))*1/4)+Assumptions!$B$106/100+Assumptions!$B$86*Assumptions!$B$108/100*100/100) -> 0.2 | H5: =MAX(0.01,((Assumptions!$B$9+(Assumptions!$O$9-Assumptions!$B$9)*Assumptions!$B$111)+((Assumptions!$B$9+(Assumptions!$P$9-Assumptions!$B$9)*Assumptions!$B$111)-(Assumptions!$B$9+(Assumptions!$O$9-Assumptions!$B$9)*Assumptions!$B$111))*2/4)+Assumptions!$B$106/100+Assumptions!$B$86*Assumptions!$B$108/100*100/100) -> 0.205 | I5: =MAX(0.01,((Assumptions!$B$9+(Assumptions!$O$9-Assumptions!$B$9)*Assumptions!$B$111)+((Assumptions!$B$9+(Assumptions!$P$9-Assumptions!$B$9)*Assumptions!$B$111)-(Assumptions!$B$9+(Assumptions!$O$9-Assumptions!$B$9)*Assumptions!$B$111))*3/4)+Assumptions!$B$106/100+Assumptions!$B$86*Assumptions!$B$108/100*100/100) -> 0.21 | J5: =MAX(0.01,((Assumptions!$B$9+(Assumptions!$O$9-Assumptions!$B$9)*Assumptions!$B$111)+((Assumptions!$B$9+(Assumptions!$P$9-Assumptions!$B$9)*Assumptions!$B$111)-(Assumptions!$B$9+(Assumptions!$O$9-Assumptions!$B$9)*Assumptions!$B$111))*4/4)+Assumptions!$B$106/100+Assumptions!$B$86*Assumptions!$B$108/100*100/100) -> 0.215 | K5: =MAX(0.01,((Assumptions!$B$9+(Assumptions!$P$9-Assumptions!$B$9)*Assumptions!$B$111)+((Assumptions!$B$9+(Assumptions!$Q$9-Assumptions!$B$9)*Assumptions!$B$111)-(Assumptions!$B$9+(Assumptions!$P$9-Assumptions!$B$9)*Assumptions!$B$111))*1/4)+Assumptions!$B$106/100+Assumptions!$B$86*Assumptions!$B$108/100*100/100) -> 0.2175 | L5: =MAX(0.01,((Assumptions!$B$9+(Assumptions!$P$9-Assumptions!$B$9)*Assumptions!$B$111)+((Assumptions!$B$9+(Assumptions!$Q$9-Assumptions!$B$9)*Assumptions!$B$111)-(Assumptions!$B$9+(Assumptions!$P$9-Assumptions!$B$9)*Assumptions!$B$111))*2/4)+Assumptions!$B$106/100+Assumptions!$B$86*Assumptions!$B$108/100*100/100) -> 0.22 | M5: =MAX(0.01,((Assumptions!$B$9+(Assumptions!$P$9-Assumptions!$B$9)*Assumptions!$B$111)+((Assumptions!$B$9+(Assumptions!$Q$9-Assumptions!$B$9)*Assumptions!$B$111)-(Assumptions!$B$9+(Assumptions!$P$9-Assumptions!$B$9)*Assumptions!$B$111))*3/4)+Assumptions!$B$106/100+Assumptions!$B$86*Assumptions!$B$108/100*100/100) -> 0.2225 | N5: =MAX(0.01,((Assumptions!$B$9+(Assumptions!$P$9-Assumptions!$B$9)*Assumptions!$B$111)+((Assumptions!$B$9+(Assumptions!$Q$9-Assumptions!$B$9)*Assumptions!$B$111)-(Assumptions!$B$9+(Assumptions!$P$9-Assumptions!$B$9)*Assumptions!$B$111))*4/4)+Assumptions!$B$106/100+Assumptions!$B$86*Assumptions!$B$108/100*100/100) -> 0.225 | O5: =AVERAGE(C5:F5) -> 0.186 | P5: =AVERAGE(G5:J5) -> 0.2075 | Q5: =AVERAGE(K5:N5) -> 0.22125 | R5: Linear path from FY26 actual to each year's scenario value
A6: Sales cycle (months) | C6: =MAX(3,(Assumptions!$B$10+((Assumptions!$B$10+(Assumptions!$O$10-Assumptions!$B$10)*Assumptions!$B$111)-Assumptions!$B$10)*1/4)+Assumptions!$B$107) -> 8.075 | D6: =MAX(3,(Assumptions!$B$10+((Assumptions!$B$10+(Assumptions!$O$10-Assumptions!$B$10)*Assumptions!$B$111)-Assumptions!$B$10)*2/4)+Assumptions!$B$107) -> 8.05 | E6: =MAX(3,(Assumptions!$B$10+((Assumptions!$B$10+(Assumptions!$O$10-Assumptions!$B$10)*Assumptions!$B$111)-Assumptions!$B$10)*3/4)+Assumptions!$B$107) -> 8.025 | F6: =MAX(3,(Assumptions!$B$10+((Assumptions!$B$10+(Assumptions!$O$10-Assumptions!$B$10)*Assumptions!$B$111)-Assumptions!$B$10)*4/4)+Assumptions!$B$107) -> 8 | G6: =MAX(3,((Assumptions!$B$10+(Assumptions!$O$10-Assumptions!$B$10)*Assumptions!$B$111)+((Assumptions!$B$10+(Assumptions!$P$10-Assumptions!$B$10)*Assumptions!$B$111)-(Assumptions!$B$10+(Assumptions!$O$10-Assumptions!$B$10)*Assumptions!$B$111))*1/4)+Assumptions!$B$107) -> 7.9 | H6: =MAX(3,((Assumptions!$B$10+(Assumptions!$O$10-Assumptions!$B$10)*Assumptions!$B$111)+((Assumptions!$B$10+(Assumptions!$P$10-Assumptions!$B$10)*Assumptions!$B$111)-(Assumptions!$B$10+(Assumptions!$O$10-Assumptions!$B$10)*Assumptions!$B$111))*2/4)+Assumptions!$B$107) -> 7.8 | I6: =MAX(3,((Assumptions!$B$10+(Assumptions!$O$10-Assumptions!$B$10)*Assumptions!$B$111)+((Assumptions!$B$10+(Assumptions!$P$10-Assumptions!$B$10)*Assumptions!$B$111)-(Assumptions!$B$10+(Assumptions!$O$10-Assumptions!$B$10)*Assumptions!$B$111))*3/4)+Assumptions!$B$107) -> 7.7 | J6: =MAX(3,((Assumptions!$B$10+(Assumptions!$O$10-Assumptions!$B$10)*Assumptions!$B$111)+((Assumptions!$B$10+(Assumptions!$P$10-Assumptions!$B$10)*Assumptions!$B$111)-(Assumptions!$B$10+(Assumptions!$O$10-Assumptions!$B$10)*Assumptions!$B$111))*4/4)+Assumptions!$B$107) -> 7.6 | K6: =MAX(3,((Assumptions!$B$10+(Assumptions!$P$10-Assumptions!$B$10)*Assumptions!$B$111)+((Assumptions!$B$10+(Assumptions!$Q$10-Assumptions!$B$10)*Assumptions!$B$111)-(Assumptions!$B$10+(Assumptions!$P$10-Assumptions!$B$10)*Assumptions!$B$111))*1/4)+Assumptions!$B$107) -> 7.525 | L6: =MAX(3,((Assumptions!$B$10+(Assumptions!$P$10-Assumptions!$B$10)*Assumptions!$B$111)+((Assumptions!$B$10+(Assumptions!$Q$10-Assumptions!$B$10)*Assumptions!$B$111)-(Assumptions!$B$10+(Assumptions!$P$10-Assumptions!$B$10)*Assumptions!$B$111))*2/4)+Assumptions!$B$107) -> 7.45 | M6: =MAX(3,((Assumptions!$B$10+(Assumptions!$P$10-Assumptions!$B$10)*Assumptions!$B$111)+((Assumptions!$B$10+(Assumptions!$Q$10-Assumptions!$B$10)*Assumptions!$B$111)-(Assumptions!$B$10+(Assumptions!$P$10-Assumptions!$B$10)*Assumptions!$B$111))*3/4)+Assumptions!$B$107) -> 7.375 | N6: =MAX(3,((Assumptions!$B$10+(Assumptions!$P$10-Assumptions!$B$10)*Assumptions!$B$111)+((Assumptions!$B$10+(Assumptions!$Q$10-Assumptions!$B$10)*Assumptions!$B$111)-(Assumptions!$B$10+(Assumptions!$P$10-Assumptions!$B$10)*Assumptions!$B$111))*4/4)+Assumptions!$B$107) -> 7.3 | O6: =AVERAGE(C6:F6) -> 8.0375 | P6: =AVERAGE(G6:J6) -> 7.75 | Q6: =AVERAGE(K6:N6) -> 7.4125
A7: Discount | C7: =(Assumptions!$B$12+((Assumptions!$B$12+(Assumptions!$O$12-Assumptions!$B$12)*Assumptions!$B$111)-Assumptions!$B$12)*1/4)+Assumptions!$B$108/100 -> 0.18475 | D7: =(Assumptions!$B$12+((Assumptions!$B$12+(Assumptions!$O$12-Assumptions!$B$12)*Assumptions!$B$111)-Assumptions!$B$12)*2/4)+Assumptions!$B$108/100 -> 0.1765 | E7: =(Assumptions!$B$12+((Assumptions!$B$12+(Assumptions!$O$12-Assumptions!$B$12)*Assumptions!$B$111)-Assumptions!$B$12)*3/4)+Assumptions!$B$108/100 -> 0.16825 | F7: =(Assumptions!$B$12+((Assumptions!$B$12+(Assumptions!$O$12-Assumptions!$B$12)*Assumptions!$B$111)-Assumptions!$B$12)*4/4)+Assumptions!$B$108/100 -> 0.16 | G7: =((Assumptions!$B$12+(Assumptions!$O$12-Assumptions!$B$12)*Assumptions!$B$111)+((Assumptions!$B$12+(Assumptions!$P$12-Assumptions!$B$12)*Assumptions!$B$111)-(Assumptions!$B$12+(Assumptions!$O$12-Assumptions!$B$12)*Assumptions!$B$111))*1/4)+Assumptions!$B$108/100 -> 0.1575 | H7: =((Assumptions!$B$12+(Assumptions!$O$12-Assumptions!$B$12)*Assumptions!$B$111)+((Assumptions!$B$12+(Assumptions!$P$12-Assumptions!$B$12)*Assumptions!$B$111)-(Assumptions!$B$12+(Assumptions!$O$12-Assumptions!$B$12)*Assumptions!$B$111))*2/4)+Assumptions!$B$108/100 -> 0.155 | I7: =((Assumptions!$B$12+(Assumptions!$O$12-Assumptions!$B$12)*Assumptions!$B$111)+((Assumptions!$B$12+(Assumptions!$P$12-Assumptions!$B$12)*Assumptions!$B$111)-(Assumptions!$B$12+(Assumptions!$O$12-Assumptions!$B$12)*Assumptions!$B$111))*3/4)+Assumptions!$B$108/100 -> 0.1525 | J7: =((Assumptions!$B$12+(Assumptions!$O$12-Assumptions!$B$12)*Assumptions!$B$111)+((Assumptions!$B$12+(Assumptions!$P$12-Assumptions!$B$12)*Assumptions!$B$111)-(Assumptions!$B$12+(Assumptions!$O$12-Assumptions!$B$12)*Assumptions!$B$111))*4/4)+Assumptions!$B$108/100 -> 0.15 | K7: =((Assumptions!$B$12+(Assumptions!$P$12-Assumptions!$B$12)*Assumptions!$B$111)+((Assumptions!$B$12+(Assumptions!$Q$12-Assumptions!$B$12)*Assumptions!$B$111)-(Assumptions!$B$12+(Assumptions!$P$12-Assumptions!$B$12)*Assumptions!$B$111))*1/4)+Assumptions!$B$108/100 -> 0.15 | L7: =((Assumptions!$B$12+(Assumptions!$P$12-Assumptions!$B$12)*Assumptions!$B$111)+((Assumptions!$B$12+(Assumptions!$Q$12-Assumptions!$B$12)*Assumptions!$B$111)-(Assumptions!$B$12+(Assumptions!$P$12-Assumptions!$B$12)*Assumptions!$B$111))*2/4)+Assumptions!$B$108/100 -> 0.15 | M7: =((Assumptions!$B$12+(Assumptions!$P$12-Assumptions!$B$12)*Assumptions!$B$111)+((Assumptions!$B$12+(Assumptions!$Q$12-Assumptions!$B$12)*Assumptions!$B$111)-(Assumptions!$B$12+(Assumptions!$P$12-Assumptions!$B$12)*Assumptions!$B$111))*3/4)+Assumptions!$B$108/100 -> 0.15 | N7: =((Assumptions!$B$12+(Assumptions!$P$12-Assumptions!$B$12)*Assumptions!$B$111)+((Assumptions!$B$12+(Assumptions!$Q$12-Assumptions!$B$12)*Assumptions!$B$111)-(Assumptions!$B$12+(Assumptions!$P$12-Assumptions!$B$12)*Assumptions!$B$111))*4/4)+Assumptions!$B$108/100 -> 0.15 | O7: =AVERAGE(C7:F7) -> 0.172375 | P7: =AVERAGE(G7:J7) -> 0.15375 | Q7: =AVERAGE(K7:N7) -> 0.15
A8: Net won deal (₹ cr) | C8: =(Assumptions!$B$11+((Assumptions!$B$11+(Assumptions!$O$11-Assumptions!$B$11)*Assumptions!$B$111)-Assumptions!$B$11)*1/4)*(1-C7)/100 -> 0.58331137 | D8: =(Assumptions!$B$11+((Assumptions!$B$11+(Assumptions!$O$11-Assumptions!$B$11)*Assumptions!$B$111)-Assumptions!$B$11)*2/4)*(1-D7)/100 -> 0.5904495 | E8: =(Assumptions!$B$11+((Assumptions!$B$11+(Assumptions!$O$11-Assumptions!$B$11)*Assumptions!$B$111)-Assumptions!$B$11)*3/4)*(1-E7)/100 -> 0.59761237 | F8: =(Assumptions!$B$11+((Assumptions!$B$11+(Assumptions!$O$11-Assumptions!$B$11)*Assumptions!$B$111)-Assumptions!$B$11)*4/4)*(1-F7)/100 -> 0.6048 | G8: =((Assumptions!$B$11+(Assumptions!$O$11-Assumptions!$B$11)*Assumptions!$B$111)+((Assumptions!$B$11+(Assumptions!$P$11-Assumptions!$B$11)*Assumptions!$B$111)-(Assumptions!$B$11+(Assumptions!$O$11-Assumptions!$B$11)*Assumptions!$B$111))*1/4)*(1-G7)/100 -> 0.61186562 | H8: =((Assumptions!$B$11+(Assumptions!$O$11-Assumptions!$B$11)*Assumptions!$B$111)+((Assumptions!$B$11+(Assumptions!$P$11-Assumptions!$B$11)*Assumptions!$B$111)-(Assumptions!$B$11+(Assumptions!$O$11-Assumptions!$B$11)*Assumptions!$B$111))*2/4)*(1-H7)/100 -> 0.6189625 | I8: =((Assumptions!$B$11+(Assumptions!$O$11-Assumptions!$B$11)*Assumptions!$B$111)+((Assumptions!$B$11+(Assumptions!$P$11-Assumptions!$B$11)*Assumptions!$B$111)-(Assumptions!$B$11+(Assumptions!$O$11-Assumptions!$B$11)*Assumptions!$B$111))*3/4)*(1-I7)/100 -> 0.62609063 | J8: =((Assumptions!$B$11+(Assumptions!$O$11-Assumptions!$B$11)*Assumptions!$B$111)+((Assumptions!$B$11+(Assumptions!$P$11-Assumptions!$B$11)*Assumptions!$B$111)-(Assumptions!$B$11+(Assumptions!$O$11-Assumptions!$B$11)*Assumptions!$B$111))*4/4)*(1-J7)/100 -> 0.63325 | K8: =((Assumptions!$B$11+(Assumptions!$P$11-Assumptions!$B$11)*Assumptions!$B$111)+((Assumptions!$B$11+(Assumptions!$Q$11-Assumptions!$B$11)*Assumptions!$B$111)-(Assumptions!$B$11+(Assumptions!$P$11-Assumptions!$B$11)*Assumptions!$B$111))*1/4)*(1-K7)/100 -> 0.6385625 | L8: =((Assumptions!$B$11+(Assumptions!$P$11-Assumptions!$B$11)*Assumptions!$B$111)+((Assumptions!$B$11+(Assumptions!$Q$11-Assumptions!$B$11)*Assumptions!$B$111)-(Assumptions!$B$11+(Assumptions!$P$11-Assumptions!$B$11)*Assumptions!$B$111))*2/4)*(1-L7)/100 -> 0.643875 | M8: =((Assumptions!$B$11+(Assumptions!$P$11-Assumptions!$B$11)*Assumptions!$B$111)+((Assumptions!$B$11+(Assumptions!$Q$11-Assumptions!$B$11)*Assumptions!$B$111)-(Assumptions!$B$11+(Assumptions!$P$11-Assumptions!$B$11)*Assumptions!$B$111))*3/4)*(1-M7)/100 -> 0.6491875 | N8: =((Assumptions!$B$11+(Assumptions!$P$11-Assumptions!$B$11)*Assumptions!$B$111)+((Assumptions!$B$11+(Assumptions!$Q$11-Assumptions!$B$11)*Assumptions!$B$111)-(Assumptions!$B$11+(Assumptions!$P$11-Assumptions!$B$11)*Assumptions!$B$111))*4/4)*(1-N7)/100 -> 0.6545 | O8: =AVERAGE(C8:F8) -> 0.59404331 | P8: =AVERAGE(G8:J8) -> 0.62254219 | Q8: =AVERAGE(K8:N8) -> 0.64653125
A9: AE deal capacity (qualified deals closed / quarter) | C9: =Capacity!C33*Assumptions!$B$34*3/C6 -> 90.81722 | D9: =Capacity!D33*Assumptions!$B$34*3/D6 -> 93.617445 | E9: =Capacity!E33*Assumptions!$B$34*3/E6 -> 96.051082 | F9: =Capacity!F33*Assumptions!$B$34*3/F6 -> 99.876751 | G9: =Capacity!G33*Assumptions!$B$34*3/G6 -> 104.38933 | H9: =Capacity!H33*Assumptions!$B$34*3/H6 -> 109.93848 | I9: =Capacity!I33*Assumptions!$B$34*3/I6 -> 114.85542 | J9: =Capacity!J33*Assumptions!$B$34*3/J6 -> 120.42733 | ... N9: =Capacity!N33*Assumptions!$B$34*3/N6 -> 141.46796 | O9: =SUM(C9:F9) -> 380.3625 | P9: =SUM(G9:J9) -> 449.61055 | Q9: =SUM(K9:N9) -> 534.25741
A10: Qualified pipeline supply (deals / quarter) | C10: =(Assumptions!$B$13+(Assumptions!$O$13-Assumptions!$B$13)*Assumptions!$B$111)/4 -> 95 | D10: =(Assumptions!$B$13+(Assumptions!$O$13-Assumptions!$B$13)*Assumptions!$B$111)/4 -> 95 | E10: =(Assumptions!$B$13+(Assumptions!$O$13-Assumptions!$B$13)*Assumptions!$B$111)/4 -> 95 | F10: =(Assumptions!$B$13+(Assumptions!$O$13-Assumptions!$B$13)*Assumptions!$B$111)/4 -> 95 | G10: =(Assumptions!$B$13+(Assumptions!$P$13-Assumptions!$B$13)*Assumptions!$B$111)/4 -> 107.5 | H10: =(Assumptions!$B$13+(Assumptions!$P$13-Assumptions!$B$13)*Assumptions!$B$111)/4 -> 107.5 | I10: =(Assumptions!$B$13+(Assumptions!$P$13-Assumptions!$B$13)*Assumptions!$B$111)/4 -> 107.5 | J10: =(Assumptions!$B$13+(Assumptions!$P$13-Assumptions!$B$13)*Assumptions!$B$111)/4 -> 107.5 | K10: =(Assumptions!$B$13+(Assumptions!$Q$13-Assumptions!$B$13)*Assumptions!$B$111)/4 -> 117.5 | L10: =(Assumptions!$B$13+(Assumptions!$Q$13-Assumptions!$B$13)*Assumptions!$B$111)/4 -> 117.5 | M10: =(Assumptions!$B$13+(Assumptions!$Q$13-Assumptions!$B$13)*Assumptions!$B$111)/4 -> 117.5 | N10: =(Assumptions!$B$13+(Assumptions!$Q$13-Assumptions!$B$13)*Assumptions!$B$111)/4 -> 117.5 | O10: =SUM(C10:F10) -> 380 | P10: =SUM(G10:J10) -> 430 | Q10: =SUM(K10:N10) -> 470
A11: Qualified deals worked to close | C11: =MIN(C9,C10) -> 90.81722 | D11: =MIN(D9,D10) -> 93.617445 | E11: =MIN(E9,E10) -> 95 | F11: =MIN(F9,F10) -> 95 | G11: =MIN(G9,G10) -> 104.38933 | H11: =MIN(H9,H10) -> 107.5 | I11: =MIN(I9,I10) -> 107.5 | J11: =MIN(J9,J10) -> 107.5 | ... N11: =MIN(N9,N10) -> 117.5 | O11: =SUM(C11:F11) -> 374.43467 | P11: =SUM(G11:J11) -> 426.88933 | Q11: =SUM(K11:N11) -> 470
A12: Binding constraint | C12: =IF(C9<C10,"AE capacity","Pipeline") -> AE capacity | D12: =IF(D9<D10,"AE capacity","Pipeline") -> AE capacity | E12: =IF(E9<E10,"AE capacity","Pipeline") -> Pipeline | F12: =IF(F9<F10,"AE capacity","Pipeline") -> Pipeline | G12: =IF(G9<G10,"AE capacity","Pipeline") -> AE capacity | H12: =IF(H9<H10,"AE capacity","Pipeline") -> Pipeline | I12: =IF(I9<I10,"AE capacity","Pipeline") -> Pipeline | J12: =IF(J9<J10,"AE capacity","Pipeline") -> Pipeline | ... N12: =IF(N9<N10,"AE capacity","Pipeline") -> Pipeline
A13: Deals won | C13: =C14/C8 -> 13.664743 | D13: =D11*D5 -> 17.131992 | E13: =E11*E5 -> 17.955 | F13: =F11*F5 -> 18.525 | G13: =G11*G5 -> 20.877865 | H13: =H11*H5 -> 22.0375 | I13: =I11*I5 -> 22.575 | J13: =J11*J5 -> 23.1125 | K13: =K11*K5 -> 25.55625 | ... N13: =N11*N5 -> 26.4375 | O13: =SUM(C13:F13) -> 67.276735 | P13: =SUM(G13:J13) -> 88.602865 | Q13: =SUM(K13:N13) -> 103.9875
A14: Direct new-logo ARR (₹ cr) | C14: =Assumptions!$B$48-Channel!C28 -> 7.9708 | D14: =D11*D5*D8 -> 10.115576 | E14: =E11*E5*E8 -> 10.73013 | F14: =F11*F5*F8 -> 11.20392 | G14: =G11*G5*G8 -> 12.774448 | H14: =H11*H5*H8 -> 13.640386 | I14: =I11*I5*I8 -> 14.133996 | J14: =J11*J5*J8 -> 14.635991 | K14: =K11*K5*K8 -> 16.319263 | ... N14: =N11*N5*N8 -> 17.303344 | O14: =SUM(C14:F14) -> 40.020427 | P14: =SUM(G14:J14) -> 55.184821 | Q14: =SUM(K14:N14) -> 67.238971 | R14: Q1 FY27: D4 locked p50 ₹8.71 cr total new-logo less partner ARR. Win-rate shifts do not move Q1 (already forecast).
A15: Pipeline required = direct ARR ÷ win rate (₹ cr) | C15: =C14/C5 -> 45.032768 | D15: =D14/D5 -> 55.276374 | E15: =E14/E5 -> 56.773176 | F15: =F14/F5 -> 57.456 | G15: =G14/G5 -> 63.87224 | H15: =H14/H5 -> 66.538469 | I15: =I14/I5 -> 67.304742 | J15: =J14/J5 -> 68.074375 | ... N15: =N14/N5 -> 76.90375 | O15: =SUM(C15:F15) -> 214.53832 | P15: =SUM(G15:J15) -> 265.78983 | Q15: =SUM(K15:N15) -> 303.86969
A16: AE capacity used | C16: =C11/C9 -> 1 | D16: =D11/D9 -> 1 | E16: =E11/E9 -> 0.98905705 | F16: =F11/F9 -> 0.95117231 | G16: =G11/G9 -> 1 | H16: =H11/H9 -> 0.97781961 | I16: =I11/I9 -> 0.93595935 | J16: =J11/J9 -> 0.89265451 | ... N16: =N11/N9 -> 0.83057678
A19: BOARD GROWTH PATH: WHAT IT WOULD TAKE
A20: Total new-logo ARR needed for board path (₹ cr) | O20: =ARR_bridge!O19-(ARR_bridge!O5+ARR_bridge!O8-ARR_bridge!O9-ARR_bridge!O10-ARR_bridge!O11) -> 49.271501 | P20: =ARR_bridge!P19-(ARR_bridge!P5+ARR_bridge!P8-ARR_bridge!P9-ARR_bridge!P10-ARR_bridge!P11) -> 70.167766 | Q20: =ARR_bridge!Q19-(ARR_bridge!Q5+ARR_bridge!Q8-ARR_bridge!Q9-ARR_bridge!Q10-ARR_bridge!Q11) -> 83.335948
A21: Direct new-logo ARR needed (₹ cr) | O21: =O20-Channel!O28 -> 45.575501 | P21: =P20-Channel!P28 -> 60.306166 | Q21: =Q20-Channel!Q28 -> 63.626188
A22: Qualified deals needed at plan win rate and deal size | O22: =O21/(O5*O8) -> 412.47762 | P22: =P21/(P5*P8) -> 466.84728 | Q22: =Q21/(Q5*Q8) -> 444.79828
A23: AE deal capacity in the year | O23: =O9 -> 380.3625 | P23: =P9 -> 449.61055 | Q23: =Q9 -> 534.25741
A24: Capacity surplus / (gap), deals | O24: =O23-O22 -> -32.115126 | P24: =P23-P22 -> -17.236727 | Q24: =Q23-Q22 -> 89.459122 | R24: Negative = the board path needs more AE capacity or pipeline than the plan funds
A25: Extra ramped AEs needed to close the gap | O25: =MAX(0,-O24)/(Assumptions!$B$34*12/O6) -> 3.9834155 | P25: =MAX(0,-P24)/(Assumptions!$B$34*12/P6) -> 2.0614913 | Q25: =MAX(0,-Q24)/(Assumptions!$B$34*12/Q6) -> 0
A26: Or: win rate needed with plan capacity | O26: =O21/(MIN(O9,O10)*O8) -> 0.20189694 | P26: =P21/(MIN(P9,P10)*P8) -> 0.22528095 | Q26: =Q21/(MIN(Q9,Q10)*Q8) -> 0.20938643

Sheet Channel
A1: Channel: partner-sourced ARR and channel P&L
A2: Reproduces D6 in the Base scenario. Partner ARR is counted once (not in direct bookings). Win-rate shift scales partner win rate too.
A4: Line | C4: Q1 FY27 | D4: Q2 FY27 | E4: Q3 FY27 | F4: Q4 FY27 | G4: Q1 FY28 | H4: Q2 FY28 | I4: Q3 FY28 | J4: Q4 FY28 | K4: Q1 FY29 | L4: Q2 FY29 | M4: Q3 FY29 | N4: Q4 FY29 | O4: FY27 | P4: FY28 | Q4: FY29 | R4: Note / source
A5: Partners activated in year | O5: =Assumptions!$O$18 -> 8 | P5: =Assumptions!$P$18 -> 9 | Q5: =Assumptions!$Q$18 -> 5
A6: Active partners, end of year | O6: =6+SUM($O$5:O5) -> 14 | P6: =6+SUM($O$5:P5) -> 23 | Q6: =6+SUM($O$5:Q5) -> 28 | R6: 6 retained existing partners (D6 keep/fix) + activations
A7: Mature productivity, after shifts (₹ cr) | O7: =(Assumptions!$B$19+(Assumptions!$O$19-Assumptions!$B$19)*Assumptions!$B$111)*(1+Assumptions!$B$109)*((Assumptions!$B$65+Assumptions!$B$106/100)/Assumptions!$B$65) -> 1.2 | P7: =(Assumptions!$B$19+(Assumptions!$P$19-Assumptions!$B$19)*Assumptions!$B$111)*(1+Assumptions!$B$109)*((Assumptions!$B$65+Assumptions!$B$106/100)/Assumptions!$B$65) -> 1.2 | Q7: =(Assumptions!$B$19+(Assumptions!$Q$19-Assumptions!$B$19)*Assumptions!$B$111)*(1+Assumptions!$B$109)*((Assumptions!$B$65+Assumptions!$B$106/100)/Assumptions!$B$65) -> 1.2
A8: Existing partners' ARR | O8: =Assumptions!$B$60*(1+Assumptions!$B$61)^0*((Assumptions!$B$65+Assumptions!$B$106/100)/Assumptions!$B$65) -> 2.256 | P8: =Assumptions!$B$60*(1+Assumptions!$B$61)^1*((Assumptions!$B$65+Assumptions!$B$106/100)/Assumptions!$B$65) -> 2.4816 | Q8: =Assumptions!$B$60*(1+Assumptions!$B$61)^2*((Assumptions!$B$65+Assumptions!$B$106/100)/Assumptions!$B$65) -> 2.72976
A9: FY27 recruits' ARR | O9: =O5*O7*Assumptions!$B$62 -> 1.44 | P9: =O5*P7*Assumptions!$B$63 -> 5.76 | Q9: =O5*Q7*Assumptions!$B$64 -> 9.6
A10: FY28 recruits' ARR | O10: 0 | P10: =P5*P7*Assumptions!$B$62 -> 1.62 | Q10: =P5*Q7*Assumptions!$B$63 -> 6.48
A11: FY29 recruits' ARR | O11: 0 | P11: 0 | Q11: =Q5*Q7*Assumptions!$B$62 -> 0.9
A12: Partner-sourced new-logo ARR (₹ cr) | O12: =SUM(O8:O11) -> 3.696 | P12: =SUM(P8:P11) -> 9.8616 | Q12: =SUM(Q8:Q11) -> 19.70976 | R12: D6 Base: ₹3.70 / 9.86 / 19.71 cr
A13: Share of total new-logo ARR | O13: =O12/(O12+Bookings!O14) -> 0.084544879 | P13: =P12/(P12+Bookings!P14) -> 0.15160865 | Q13: =Q12/(Q12+Bookings!Q14) -> 0.22668255
A14: Year-1 partner margin | O14: =O12*Assumptions!$B$71 -> 0.606144 | P14: =P12*Assumptions!$B$72 -> 1.676472 | Q14: =Q12*Assumptions!$B$73 -> 3.4689178
A15: Renewal margin on earlier partner cohorts | O15: =0 -> 0 | P15: =O12*Assumptions!$B$74 -> 0.24024 | Q15: =(O12+P12)*Assumptions!$B$75 -> 0.949032
A16: Total partner margin (in gross margin) | O16: =O14+O15 -> 0.606144 | P16: =P14+P15 -> 1.916712 | Q16: =Q14+Q15 -> 4.4179498
A17: Channel fixed cost excl. MDF (incremental) | O17: =Assumptions!$B$76 -> 2.44 | P17: =Assumptions!$B$77 -> 3.46 | Q17: =Assumptions!$B$78 -> 4
A18: Partner MDF (inside existing programme budget) | O18: =Assumptions!$B$79 -> 1.5 | P18: =Assumptions!$B$80 -> 2 | Q18: =Assumptions!$B$81 -> 2.5
A19: Direct effort on partner deals (AE, SE, 50% credit) | O19: =O12*Assumptions!$B$82*Assumptions!$B$85 -> 2.424576 | P19: =P12*Assumptions!$B$83*Assumptions!$B$85 -> 5.6605584 | Q19: =Q12*Assumptions!$B$84*Assumptions!$B$85 -> 9.6972019
A20: Total channel cost | O20: =O16+O17+O18+O19 -> 6.97072 | P20: =P16+P17+P18+P19 -> 13.03727 | Q20: =Q16+Q17+Q18+Q19 -> 20.615152
A21: Direct S&M cost avoided | O21: =O12*Assumptions!$B$85 -> 6.06144 | P21: =P12*Assumptions!$B$85 -> 16.173024 | Q21: =Q12*Assumptions!$B$85 -> 32.324006
A22: Saving / (extra cost) vs selling direct | O22: =O21-O20 -> -0.90928 | P22: =P21-P20 -> 3.1357536 | Q22: =Q21-Q20 -> 11.708855
A23: Incremental lens, first year: gross profit − total cost | O23: =O12*PnL!O12-O20 -> -4.4304015 | P23: =P12*PnL!P12-P20 -> -6.3398472 | Q23: =Q12*PnL!Q12-Q20 -> -7.1257173
A24: Break-even sourced ARR per active partner (substitution, ₹ cr) | O24: =(O17+O18)/(O6*(Assumptions!$B$85*(1-Assumptions!$B$82)-Assumptions!$B$71)) -> 0.34320557 | P24: =(P17+P18)/(P6*(Assumptions!$B$85*(1-Assumptions!$B$83)-Assumptions!$B$72)) -> 0.26494565 | Q24: =(Q17+Q18)/(Q6*(Assumptions!$B$85*(1-Assumptions!$B$84)-Assumptions!$B$73)) -> 0.2388301 | R24: D6 panel answer (~₹0.24 cr in FY29)
A25: Partner pipeline required = partner ARR ÷ partner win rate (₹ cr) | O25: =O12/(Assumptions!$B$65+Assumptions!$B$106/100) -> 10.870588 | P25: =P12/(Assumptions!$B$65+Assumptions!$B$106/100) -> 29.004706 | Q25: =Q12/(Assumptions!$B$65+Assumptions!$B$106/100) -> 57.969882
A26: Partner pipeline capacity: mature-equivalent partners × 10 deals × deal (₹ cr) | O26: =O12/MAX(0.01,O7)*10*Assumptions!$B$66 -> 11.396 | P26: =P12/MAX(0.01,P7)*10*Assumptions!$B$66 -> 30.4066 | Q26: =Q12/MAX(0.01,Q7)*10*Assumptions!$B$66 -> 60.77176 | R26: Mature-equivalent partners × 10 qualified deals a year × average partner deal
A28: Quarterly partner-sourced ARR (₹ cr) | C28: =O12*Assumptions!$B$67 -> 0.7392 | D28: =O12*Assumptions!$B$68 -> 0.85008 | E28: =O12*Assumptions!$B$69 -> 0.99792 | F28: =O12*Assumptions!$B$70 -> 1.1088 | G28: =P12*Assumptions!$B$67 -> 1.97232 | H28: =P12*Assumptions!$B$68 -> 2.268168 | I28: =P12*Assumptions!$B$69 -> 2.662632 | J28: =P12*Assumptions!$B$70 -> 2.95848 | K28: =Q12*Assumptions!$B$67 -> 3.941952 | L28: =Q12*Assumptions!$B$68 -> 4.5332448 | M28: =Q12*Assumptions!$B$69 -> 5.3216352 | N28: =Q12*Assumptions!$B$70 -> 5.912928 | O28: =SUM(C28:F28) -> 3.696 | P28: =SUM(G28:J28) -> 9.8616 | Q28: =SUM(K28:N28) -> 19.70976
A29: Quarterly partner margin (₹ cr) | C29: =O16*Assumptions!$B$67 -> 0.1212288 | D29: =O16*Assumptions!$B$68 -> 0.13941312 | E29: =O16*Assumptions!$B$69 -> 0.16365888 | F29: =O16*Assumptions!$B$70 -> 0.1818432 | G29: =P16*Assumptions!$B$67 -> 0.3833424 | H29: =P16*Assumptions!$B$68 -> 0.44084376 | I29: =P16*Assumptions!$B$69 -> 0.51751224 | J29: =P16*Assumptions!$B$70 -> 0.5750136 | K29: =Q16*Assumptions!$B$67 -> 0.88358995 | L29: =Q16*Assumptions!$B$68 -> 1.0161284 | M29: =Q16*Assumptions!$B$69 -> 1.1928464 | N29: =Q16*Assumptions!$B$70 -> 1.3253849
A30: Check: quarterly phasing sums to annual | O30: =ABS(SUM(C28:N28)-SUM(O12:Q12)) -> 0

Sheet ARR_bridge
A1: Quarterly ARR bridge, FY27–FY29
A2: Opening + new logo (direct + partner) + expansion − contraction − churn − Vajra re-tender = closing. Retention rates apply to opening ARR excluding Vajra until its Q4 FY27 renewal.
A4: Line | B4: FY26 / start | C4: Q1 FY27 | D4: Q2 FY27 | E4: Q3 FY27 | F4: Q4 FY27 | G4: Q1 FY28 | H4: Q2 FY28 | I4: Q3 FY28 | J4: Q4 FY28 | K4: Q1 FY29 | L4: Q2 FY29 | M4: Q3 FY29 | N4: Q4 FY29 | O4: FY27 | P4: FY28 | Q4: FY29 | R4: Note / source
A5: Opening ARR | C5: =B12 -> 310 | D5: =C12 -> 318.18412 | E5: =D12 -> 328.91827 | F5: =E12 -> 340.72617 | G5: =F12 -> 350.94493 | H5: =G12 -> 366.56906 | I5: =H12 -> 383.85224 | J5: =I12 -> 402.56813 | ... N5: =M12 -> 497.33912 | O5: =C5 -> 310 | P5: =G5 -> 350.94493 | Q5: =K5 -> 422.67865
A6: New logo: direct | C6: =Bookings!C14 -> 7.9708 | D6: =Bookings!D14 -> 10.115576 | E6: =Bookings!E14 -> 10.73013 | F6: =Bookings!F14 -> 11.20392 | G6: =Bookings!G14 -> 12.774448 | H6: =Bookings!H14 -> 13.640386 | I6: =Bookings!I14 -> 14.133996 | J6: =Bookings!J14 -> 14.635991 | ... N6: =Bookings!N14 -> 17.303344 | O6: =SUM(C6:F6) -> 40.020427 | P6: =SUM(G6:J6) -> 55.184821 | Q6: =SUM(K6:N6) -> 67.238971
A7: New logo: partner-sourced | C7: =Channel!C28 -> 0.7392 | D7: =Channel!D28 -> 0.85008 | E7: =Channel!E28 -> 0.99792 | F7: =Channel!F28 -> 1.1088 | G7: =Channel!G28 -> 1.97232 | H7: =Channel!H28 -> 2.268168 | I7: =Channel!I28 -> 2.662632 | J7: =Channel!J28 -> 2.95848 | ... N7: =Channel!N28 -> 5.912928 | O7: =SUM(C7:F7) -> 3.696 | P7: =SUM(G7:J7) -> 9.8616 | Q7: =SUM(K7:N7) -> 19.70976
A8: Expansion | C8: =C14*(Assumptions!$B$15+((Assumptions!$B$15+(Assumptions!$O$15-Assumptions!$B$15)*Assumptions!$B$111)-Assumptions!$B$15)*1/4)/4 -> 6.16025 | D8: =D14*(Assumptions!$B$15+((Assumptions!$B$15+(Assumptions!$O$15-Assumptions!$B$15)*Assumptions!$B$111)-Assumptions!$B$15)*2/4)/4 -> 6.4051956 | E8: =E14*(Assumptions!$B$15+((Assumptions!$B$15+(Assumptions!$O$15-Assumptions!$B$15)*Assumptions!$B$111)-Assumptions!$B$15)*3/4)/4 -> 6.7077836 | F8: =F14*(Assumptions!$B$15+((Assumptions!$B$15+(Assumptions!$O$15-Assumptions!$B$15)*Assumptions!$B$111)-Assumptions!$B$15)*4/4)/4 -> 7.0385562 | G8: =G14*((Assumptions!$B$15+(Assumptions!$O$15-Assumptions!$B$15)*Assumptions!$B$111)+((Assumptions!$B$15+(Assumptions!$P$15-Assumptions!$B$15)*Assumptions!$B$111)-(Assumptions!$B$15+(Assumptions!$O$15-Assumptions!$B$15)*Assumptions!$B$111))*1/4)/4 -> 7.6769203 | H8: =H14*((Assumptions!$B$15+(Assumptions!$O$15-Assumptions!$B$15)*Assumptions!$B$111)+((Assumptions!$B$15+(Assumptions!$P$15-Assumptions!$B$15)*Assumptions!$B$111)-(Assumptions!$B$15+(Assumptions!$O$15-Assumptions!$B$15)*Assumptions!$B$111))*2/4)/4 -> 8.2478038 | I8: =I14*((Assumptions!$B$15+(Assumptions!$O$15-Assumptions!$B$15)*Assumptions!$B$111)+((Assumptions!$B$15+(Assumptions!$P$15-Assumptions!$B$15)*Assumptions!$B$111)-(Assumptions!$B$15+(Assumptions!$O$15-Assumptions!$B$15)*Assumptions!$B$111))*3/4)/4 -> 8.8765831 | J8: =J14*((Assumptions!$B$15+(Assumptions!$O$15-Assumptions!$B$15)*Assumptions!$B$111)+((Assumptions!$B$15+(Assumptions!$P$15-Assumptions!$B$15)*Assumptions!$B$111)-(Assumptions!$B$15+(Assumptions!$O$15-Assumptions!$B$15)*Assumptions!$B$111))*4/4)/4 -> 9.5609932 | K8: =K14*((Assumptions!$B$15+(Assumptions!$P$15-Assumptions!$B$15)*Assumptions!$B$111)+((Assumptions!$B$15+(Assumptions!$Q$15-Assumptions!$B$15)*Assumptions!$B$111)-(Assumptions!$B$15+(Assumptions!$P$15-Assumptions!$B$15)*Assumptions!$B$111))*1/4)/4 -> 10.302792 | L8: =L14*((Assumptions!$B$15+(Assumptions!$P$15-Assumptions!$B$15)*Assumptions!$B$111)+((Assumptions!$B$15+(Assumptions!$Q$15-Assumptions!$B$15)*Assumptions!$B$111)-(Assumptions!$B$15+(Assumptions!$P$15-Assumptions!$B$15)*Assumptions!$B$111))*2/4)/4 -> 11.149447 | M8: =M14*((Assumptions!$B$15+(Assumptions!$P$15-Assumptions!$B$15)*Assumptions!$B$111)+((Assumptions!$B$15+(Assumptions!$Q$15-Assumptions!$B$15)*Assumptions!$B$111)-(Assumptions!$B$15+(Assumptions!$P$15-Assumptions!$B$15)*Assumptions!$B$111))*3/4)/4 -> 12.063708 | N8: =N14*((Assumptions!$B$15+(Assumptions!$P$15-Assumptions!$B$15)*Assumptions!$B$111)+((Assumptions!$B$15+(Assumptions!$Q$15-Assumptions!$B$15)*Assumptions!$B$111)-(Assumptions!$B$15+(Assumptions!$P$15-Assumptions!$B$15)*Assumptions!$B$111))*4/4)/4 -> 13.055152 | O8: =SUM(C8:F8) -> 26.311785 | P8: =SUM(G8:J8) -> 34.3623 | Q8: =SUM(K8:N8) -> 46.571099
A9: Contraction | C9: =C14*(Assumptions!$B$16+((Assumptions!$B$16+(Assumptions!$O$16-Assumptions!$B$16)*Assumptions!$B$111)-Assumptions!$B$16)*1/4)/4 -> 2.4227812 | D9: =D14*(Assumptions!$B$16+((Assumptions!$B$16+(Assumptions!$O$16-Assumptions!$B$16)*Assumptions!$B$111)-Assumptions!$B$16)*2/4)/4 -> 2.4308875 | E9: =E14*(Assumptions!$B$16+((Assumptions!$B$16+(Assumptions!$O$16-Assumptions!$B$16)*Assumptions!$B$111)-Assumptions!$B$16)*3/4)/4 -> 2.4555279 | F9: =F14*(Assumptions!$B$16+((Assumptions!$B$16+(Assumptions!$O$16-Assumptions!$B$16)*Assumptions!$B$111)-Assumptions!$B$16)*4/4)/4 -> 2.4841963 | G9: =G14*((Assumptions!$B$16+(Assumptions!$O$16-Assumptions!$B$16)*Assumptions!$B$111)+((Assumptions!$B$16+(Assumptions!$P$16-Assumptions!$B$16)*Assumptions!$B$111)-(Assumptions!$B$16+(Assumptions!$O$16-Assumptions!$B$16)*Assumptions!$B$111))*1/4)/4 -> 2.5224167 | H9: =H14*((Assumptions!$B$16+(Assumptions!$O$16-Assumptions!$B$16)*Assumptions!$B$111)+((Assumptions!$B$16+(Assumptions!$P$16-Assumptions!$B$16)*Assumptions!$B$111)-(Assumptions!$B$16+(Assumptions!$O$16-Assumptions!$B$16)*Assumptions!$B$111))*2/4)/4 -> 2.5201623 | I9: =I14*((Assumptions!$B$16+(Assumptions!$O$16-Assumptions!$B$16)*Assumptions!$B$111)+((Assumptions!$B$16+(Assumptions!$P$16-Assumptions!$B$16)*Assumptions!$B$111)-(Assumptions!$B$16+(Assumptions!$O$16-Assumptions!$B$16)*Assumptions!$B$111))*3/4)/4 -> 2.5190304 | J9: =J14*((Assumptions!$B$16+(Assumptions!$O$16-Assumptions!$B$16)*Assumptions!$B$111)+((Assumptions!$B$16+(Assumptions!$P$16-Assumptions!$B$16)*Assumptions!$B$111)-(Assumptions!$B$16+(Assumptions!$O$16-Assumptions!$B$16)*Assumptions!$B$111))*4/4)/4 -> 2.5160508 | K9: =K14*((Assumptions!$B$16+(Assumptions!$P$16-Assumptions!$B$16)*Assumptions!$B$111)+((Assumptions!$B$16+(Assumptions!$Q$16-Assumptions!$B$16)*Assumptions!$B$111)-(Assumptions!$B$16+(Assumptions!$P$16-Assumptions!$B$16)*Assumptions!$B$111))*1/4)/4 -> 2.6417416 | L9: =L14*((Assumptions!$B$16+(Assumptions!$P$16-Assumptions!$B$16)*Assumptions!$B$111)+((Assumptions!$B$16+(Assumptions!$Q$16-Assumptions!$B$16)*Assumptions!$B$111)-(Assumptions!$B$16+(Assumptions!$P$16-Assumptions!$B$16)*Assumptions!$B$111))*2/4)/4 -> 2.7873617 | M9: =M14*((Assumptions!$B$16+(Assumptions!$P$16-Assumptions!$B$16)*Assumptions!$B$111)+((Assumptions!$B$16+(Assumptions!$Q$16-Assumptions!$B$16)*Assumptions!$B$111)-(Assumptions!$B$16+(Assumptions!$P$16-Assumptions!$B$16)*Assumptions!$B$111))*3/4)/4 -> 2.9423679 | N9: =N14*((Assumptions!$B$16+(Assumptions!$P$16-Assumptions!$B$16)*Assumptions!$B$111)+((Assumptions!$B$16+(Assumptions!$Q$16-Assumptions!$B$16)*Assumptions!$B$111)-(Assumptions!$B$16+(Assumptions!$P$16-Assumptions!$B$16)*Assumptions!$B$111))*4/4)/4 -> 3.1083695 | O9: =SUM(C9:F9) -> 9.793393 | P9: =SUM(G9:J9) -> 10.07766 | Q9: =SUM(K9:N9) -> 11.479841
A10: Churn | C10: =C14*MAX(0,(Assumptions!$B$17+((Assumptions!$B$17+(Assumptions!$O$17-Assumptions!$B$17)*Assumptions!$B$111)-Assumptions!$B$17)*1/4)+Assumptions!$B$110/100)/4 -> 4.2633437 | D10: =D14*MAX(0,(Assumptions!$B$17+((Assumptions!$B$17+(Assumptions!$O$17-Assumptions!$B$17)*Assumptions!$B$111)-Assumptions!$B$17)*2/4)+Assumptions!$B$110/100)/4 -> 4.2058212 | E10: =E14*MAX(0,(Assumptions!$B$17+((Assumptions!$B$17+(Assumptions!$O$17-Assumptions!$B$17)*Assumptions!$B$111)-Assumptions!$B$17)*3/4)+Assumptions!$B$110/100)/4 -> 4.1724011 | F10: =F14*MAX(0,(Assumptions!$B$17+((Assumptions!$B$17+(Assumptions!$O$17-Assumptions!$B$17)*Assumptions!$B$111)-Assumptions!$B$17)*4/4)+Assumptions!$B$110/100)/4 -> 4.1403272 | G10: =G14*MAX(0,((Assumptions!$B$17+(Assumptions!$O$17-Assumptions!$B$17)*Assumptions!$B$111)+((Assumptions!$B$17+(Assumptions!$P$17-Assumptions!$B$17)*Assumptions!$B$111)-(Assumptions!$B$17+(Assumptions!$O$17-Assumptions!$B$17)*Assumptions!$B$111))*1/4)+Assumptions!$B$110/100)/4 -> 4.2771413 | H10: =H14*MAX(0,((Assumptions!$B$17+(Assumptions!$O$17-Assumptions!$B$17)*Assumptions!$B$111)+((Assumptions!$B$17+(Assumptions!$P$17-Assumptions!$B$17)*Assumptions!$B$111)-(Assumptions!$B$17+(Assumptions!$O$17-Assumptions!$B$17)*Assumptions!$B$111))*2/4)+Assumptions!$B$110/100)/4 -> 4.3530075 | I10: =I14*MAX(0,((Assumptions!$B$17+(Assumptions!$O$17-Assumptions!$B$17)*Assumptions!$B$111)+((Assumptions!$B$17+(Assumptions!$P$17-Assumptions!$B$17)*Assumptions!$B$111)-(Assumptions!$B$17+(Assumptions!$O$17-Assumptions!$B$17)*Assumptions!$B$111))*3/4)+Assumptions!$B$110/100)/4 -> 4.4382916 | J10: =J14*MAX(0,((Assumptions!$B$17+(Assumptions!$O$17-Assumptions!$B$17)*Assumptions!$B$111)+((Assumptions!$B$17+(Assumptions!$P$17-Assumptions!$B$17)*Assumptions!$B$111)-(Assumptions!$B$17+(Assumptions!$O$17-Assumptions!$B$17)*Assumptions!$B$111))*4/4)+Assumptions!$B$110/100)/4 -> 4.5288915 | K10: =K14*MAX(0,((Assumptions!$B$17+(Assumptions!$P$17-Assumptions!$B$17)*Assumptions!$B$111)+((Assumptions!$B$17+(Assumptions!$Q$17-Assumptions!$B$17)*Assumptions!$B$111)-(Assumptions!$B$17+(Assumptions!$P$17-Assumptions!$B$17)*Assumptions!$B$111))*1/4)+Assumptions!$B$110/100)/4 -> 4.6230478 | L10: =L14*MAX(0,((Assumptions!$B$17+(Assumptions!$P$17-Assumptions!$B$17)*Assumptions!$B$111)+((Assumptions!$B$17+(Assumptions!$Q$17-Assumptions!$B$17)*Assumptions!$B$111)-(Assumptions!$B$17+(Assumptions!$P$17-Assumptions!$B$17)*Assumptions!$B$111))*2/4)+Assumptions!$B$110/100)/4 -> 4.7385149 | M10: =M14*MAX(0,((Assumptions!$B$17+(Assumptions!$P$17-Assumptions!$B$17)*Assumptions!$B$111)+((Assumptions!$B$17+(Assumptions!$Q$17-Assumptions!$B$17)*Assumptions!$B$111)-(Assumptions!$B$17+(Assumptions!$P$17-Assumptions!$B$17)*Assumptions!$B$111))*3/4)+Assumptions!$B$110/100)/4 -> 4.854907 | N10: =N14*MAX(0,((Assumptions!$B$17+(Assumptions!$P$17-Assumptions!$B$17)*Assumptions!$B$111)+((Assumptions!$B$17+(Assumptions!$Q$17-Assumptions!$B$17)*Assumptions!$B$111)-(Assumptions!$B$17+(Assumptions!$P$17-Assumptions!$B$17)*Assumptions!$B$111))*4/4)+Assumptions!$B$110/100)/4 -> 4.9733912 | O10: =SUM(C10:F10) -> 16.781893 | P10: =SUM(G10:J10) -> 17.597332 | Q10: =SUM(K10:N10) -> 19.189861
A11: Vajra re-tender (Inject 4): expected ARR lost | C11: =0 -> 0 | D11: =0 -> 0 | E11: =0 -> 0 | F11: =Inject4!$C$14 -> 2.508 | G11: =0 -> 0 | H11: =0 -> 0 | I11: =0 -> 0 | J11: =0 -> 0 | K11: =0 -> 0 | L11: =0 -> 0 | M11: =0 -> 0 | N11: =0 -> 0 | O11: =SUM(C11:F11) -> 2.508 | P11: =SUM(G11:J11) -> 0 | Q11: =SUM(K11:N11) -> 0
A12: Closing ARR | B12: 310 | C12: =C5+C6+C7+C8-C9-C10-C11 -> 318.18412 | D12: =D5+D6+D7+D8-D9-D10-D11 -> 328.91827 | E12: =E5+E6+E7+E8-E9-E10-E11 -> 340.72617 | F12: =F5+F6+F7+F8-F9-F10-F11 -> 350.94493 | G12: =G5+G6+G7+G8-G9-G10-G11 -> 366.56906 | H12: =H5+H6+H7+H8-H9-H10-H11 -> 383.85224 | I12: =I5+I6+I7+I8-I9-I10-I11 -> 402.56813 | J12: =J5+J6+J7+J8-J9-J10-J11 -> 422.67865 | ... N12: =N5+N6+N7+N8-N9-N10-N11 -> 525.52878 | O12: =F12 -> 350.94493 | P12: =J12 -> 422.67865 | Q12: =N12 -> 525.52878 | R12: FY26 closing ARR ₹310 cr (DR3)
A13: Check: bridge ties (should be 0) | C13: =ROUND(C12-(C5+C6+C7+C8-C9-C10-C11),6) -> 0 | D13: =ROUND(D12-(D5+D6+D7+D8-D9-D10-D11),6) -> 0 | E13: =ROUND(E12-(E5+E6+E7+E8-E9-E10-E11),6) -> 0 | F13: =ROUND(F12-(F5+F6+F7+F8-F9-F10-F11),6) -> 0 | G13: =ROUND(G12-(G5+G6+G7+G8-G9-G10-G11),6) -> 0 | H13: =ROUND(H12-(H5+H6+H7+H8-H9-H10-H11),6) -> 0 | I13: =ROUND(I12-(I5+I6+I7+I8-I9-I10-I11),6) -> 0 | J13: =ROUND(J12-(J5+J6+J7+J8-J9-J10-J11),6) -> 0 | ... N13: =ROUND(N12-(N5+N6+N7+N8-N9-N10-N11),6) -> 0 | O13: =SUM(C13:F13) -> 0 | P13: =SUM(G13:J13) -> 0 | Q13: =SUM(K13:N13) -> 0
A14: ARR base for retention rates (excl. Vajra in FY27) | C14: =C5-Assumptions!$B$87 -> 300.5 | D14: =D5-Assumptions!$B$87 -> 308.68412 | E14: =E5-Assumptions!$B$87 -> 319.41827 | F14: =F5-Assumptions!$B$87 -> 331.22617 | G14: =G5-0 -> 350.94493 | H14: =H5-0 -> 366.56906 | I14: =I5-0 -> 383.85224 | J14: =J5-0 -> 402.56813 | K14: =K5-0 -> 422.67865 | L14: =L5-0 -> 445.97787 | M14: =M5-0 -> 470.77886 | N14: =N5-0 -> 497.33912
A17: Total new-logo ARR | O17: =O6+O7 -> 43.716427 | P17: =P6+P7 -> 65.046421 | Q17: =Q6+Q7 -> 86.948731
A18: ARR growth | B18: =310/272-1 -> 0.13970588 | O18: =O12/O5-1 -> 0.13208041 | P18: =P12/P5-1 -> 0.20440167 | Q18: =Q12/Q5-1 -> 0.24332937 | R18: FY26: 14.0%. Board path 15% / 20% / 22%.
A19: Board-path closing ARR | O19: =B12*(1+Assumptions!$B$94) -> 356.5 | P19: =O19*(1+Assumptions!$B$95) -> 427.8 | Q19: =P19*(1+Assumptions!$B$96) -> 521.916
A20: Closing ARR vs board path | O20: =O12-O19 -> -5.5550743 | P20: =P12-P19 -> -5.1213454 | Q20: =Q12-Q19 -> 3.6127833
A21: Net revenue retention (opening-base approximation) | O21: =(O5+O8-O9-O10-O11)/O5 -> 0.99105967 | P21: =(P5+P8-P9-P10-P11)/P5 -> 1.0190552 | Q21: =(Q5+Q8-Q9-Q10-Q11)/Q5 -> 1.0376205 | R21: FY26 98.9% (D1). Board goal 108% by FY29.
A22: Gross revenue retention | O22: =(O5-O9-O10-O11)/O5 -> 0.90618295 | P22: =(P5-P9-P10-P11)/P5 -> 0.9211415 | Q22: =(Q5-Q9-Q10-Q11)/Q5 -> 0.92743967
A23: Do-nothing closing ARR | O23: =Do_nothing!C8 -> 342.44 | P23: =Do_nothing!D8 -> 368.82686 | Q23: =Do_nothing!E8 -> 388.85733
A24: Incremental ARR vs do-nothing | O24: =O12-O23 -> 8.5049257 | P24: =P12-P23 -> 53.851795 | Q24: =Q12-Q23 -> 136.67145

Sheet PnL
A1: Profit and loss, gross margin and CAC payback
A2: Partner margin is charged to gross margin for the 66% floor test (today it sits in S&M). CAC payback uses the board-pack definition (DR3).
A4: Line | B4: FY26 / start | C4: Q1 FY27 | D4: Q2 FY27 | E4: Q3 FY27 | F4: Q4 FY27 | G4: Q1 FY28 | H4: Q2 FY28 | I4: Q3 FY28 | J4: Q4 FY28 | K4: Q1 FY29 | L4: Q2 FY29 | M4: Q3 FY29 | N4: Q4 FY29 | O4: FY27 | P4: FY28 | Q4: FY29 | R4: Note / source
A5: Average ARR in quarter | C5: =(ARR_bridge!C5+ARR_bridge!C12)/2 -> 314.09206 | D5: =(ARR_bridge!D5+ARR_bridge!D12)/2 -> 323.5512 | E5: =(ARR_bridge!E5+ARR_bridge!E12)/2 -> 334.82222 | F5: =(ARR_bridge!F5+ARR_bridge!F12)/2 -> 345.83555 | G5: =(ARR_bridge!G5+ARR_bridge!G12)/2 -> 358.75699 | H5: =(ARR_bridge!H5+ARR_bridge!H12)/2 -> 375.21065 | I5: =(ARR_bridge!I5+ARR_bridge!I12)/2 -> 393.21019 | J5: =(ARR_bridge!J5+ARR_bridge!J12)/2 -> 412.62339 | ... N5: =(ARR_bridge!N5+ARR_bridge!N12)/2 -> 511.43395 | O5: =AVERAGE(C5:F5) -> 329.57526 | P5: =AVERAGE(G5:J5) -> 384.95031 | Q5: =AVERAGE(K5:N5) -> 472.04989
A6: Subscription revenue | C6: =C5*Assumptions!$B$53/4 -> 78.523016 | D6: =D5*Assumptions!$B$53/4 -> 80.887799 | E6: =E5*Assumptions!$B$53/4 -> 83.705555 | F6: =F5*Assumptions!$B$53/4 -> 86.458887 | G6: =G5*Assumptions!$B$53/4 -> 89.689248 | H6: =H5*Assumptions!$B$53/4 -> 93.802663 | I6: =I5*Assumptions!$B$53/4 -> 98.302547 | J6: =J5*Assumptions!$B$53/4 -> 103.15585 | ... N6: =N5*Assumptions!$B$53/4 -> 127.85849 | O6: =SUM(C6:F6) -> 329.57526 | P6: =SUM(G6:J6) -> 384.95031 | Q6: =SUM(K6:N6) -> 472.04989
A7: Hardware revenue | C7: =(ARR_bridge!C6+ARR_bridge!C7+ARR_bridge!C8)*(Assumptions!$B$21+(Assumptions!$O$21-Assumptions!$B$21)*1/4) -> 21.710565 | D7: =(ARR_bridge!D6+ARR_bridge!D7+ARR_bridge!D8)*(Assumptions!$B$21+(Assumptions!$O$21-Assumptions!$B$21)*2/4) -> 25.014027 | E7: =(ARR_bridge!E6+ARR_bridge!E7+ARR_bridge!E8)*(Assumptions!$B$21+(Assumptions!$O$21-Assumptions!$B$21)*3/4) -> 26.178884 | F7: =(ARR_bridge!F6+ARR_bridge!F7+ARR_bridge!F8)*(Assumptions!$B$21+(Assumptions!$O$21-Assumptions!$B$21)*4/4) -> 27.091787 | G7: =(ARR_bridge!G6+ARR_bridge!G7+ARR_bridge!G8)*(Assumptions!$O$21+(Assumptions!$P$21-Assumptions!$O$21)*1/4) -> 30.271979 | H7: =(ARR_bridge!H6+ARR_bridge!H7+ARR_bridge!H8)*(Assumptions!$O$21+(Assumptions!$P$21-Assumptions!$O$21)*2/4) -> 31.403265 | I7: =(ARR_bridge!I6+ARR_bridge!I7+ARR_bridge!I8)*(Assumptions!$O$21+(Assumptions!$P$21-Assumptions!$O$21)*3/4) -> 32.091514 | J7: =(ARR_bridge!J6+ARR_bridge!J7+ARR_bridge!J8)*(Assumptions!$O$21+(Assumptions!$P$21-Assumptions!$O$21)*4/4) -> 32.586557 | K7: =(ARR_bridge!K6+ARR_bridge!K7+ARR_bridge!K8)*(Assumptions!$P$21+(Assumptions!$Q$21-Assumptions!$P$21)*1/4) -> 35.530658 | L7: =(ARR_bridge!L6+ARR_bridge!L7+ARR_bridge!L8)*(Assumptions!$P$21+(Assumptions!$Q$21-Assumptions!$P$21)*2/4) -> 36.367718 | M7: =(ARR_bridge!M6+ARR_bridge!M7+ARR_bridge!M8)*(Assumptions!$P$21+(Assumptions!$Q$21-Assumptions!$P$21)*3/4) -> 37.363824 | N7: =(ARR_bridge!N6+ARR_bridge!N7+ARR_bridge!N8)*(Assumptions!$P$21+(Assumptions!$Q$21-Assumptions!$P$21)*4/4) -> 38.084995 | O7: =SUM(C7:F7) -> 99.995263 | P7: =SUM(G7:J7) -> 126.35331 | Q7: =SUM(K7:N7) -> 147.34719 | R7: Hardware attaches to new and expansion ARR (DR3 FY26 ratio); not in ARR
A8: Total revenue | B8: 388.52 | C8: =C6+C7 -> 100.23358 | D8: =D6+D7 -> 105.90183 | E8: =E6+E7 -> 109.88444 | F8: =F6+F7 -> 113.55067 | G8: =G6+G7 -> 119.96123 | H8: =H6+H7 -> 125.20593 | I8: =I6+I7 -> 130.39406 | J8: =J6+J7 -> 135.74241 | ... N8: =N6+N7 -> 165.94348 | O8: =SUM(C8:F8) -> 429.57052 | P8: =SUM(G8:J8) -> 511.30362 | Q8: =SUM(K8:N8) -> 619.39709
A9: Software cost of revenue | C9: =C6*Assumptions!$B$54 -> 14.134143 | D9: =D6*Assumptions!$B$54 -> 14.559804 | E9: =E6*Assumptions!$B$54 -> 15.067 | F9: =F6*Assumptions!$B$54 -> 15.5626 | G9: =G6*Assumptions!$B$54 -> 16.144065 | H9: =H6*Assumptions!$B$54 -> 16.884479 | I9: =I6*Assumptions!$B$54 -> 17.694458 | J9: =J6*Assumptions!$B$54 -> 18.568053 | ... N9: =N6*Assumptions!$B$54 -> 23.014528 | O9: =SUM(C9:F9) -> 59.323546 | P9: =SUM(G9:J9) -> 69.291055 | Q9: =SUM(K9:N9) -> 84.968981
A10: Hardware cost of revenue | C10: =C7*Assumptions!$B$55 -> 16.282924 | D10: =D7*Assumptions!$B$55 -> 18.76052 | E10: =E7*Assumptions!$B$55 -> 19.634163 | F10: =F7*Assumptions!$B$55 -> 20.31884 | G10: =G7*Assumptions!$B$55 -> 22.703984 | H10: =H7*Assumptions!$B$55 -> 23.552449 | I10: =I7*Assumptions!$B$55 -> 24.068635 | J10: =J7*Assumptions!$B$55 -> 24.439917 | ... N10: =N7*Assumptions!$B$55 -> 28.563746 | O10: =SUM(C10:F10) -> 74.996447 | P10: =SUM(G10:J10) -> 94.764986 | Q10: =SUM(K10:N10) -> 110.5104
A11: Gross profit before partner margin | C11: =C8-C9-C10 -> 69.816514 | D11: =D8-D9-D10 -> 72.581502 | E11: =E8-E9-E10 -> 75.183276 | F11: =F8-F9-F10 -> 77.669234 | G11: =G8-G9-G10 -> 81.113178 | H11: =H8-H9-H10 -> 84.769 | I11: =I8-I9-I10 -> 88.630967 | J11: =J8-J9-J10 -> 92.734435 | ... N11: =N8-N9-N10 -> 114.36521 | O11: =SUM(C11:F11) -> 295.25053 | P11: =SUM(G11:J11) -> 347.24758 | Q11: =SUM(K11:N11) -> 423.91771
A12: Gross margin before partner margin | C12: =C11/C8 -> 0.69653816 | D12: =D11/D8 -> 0.68536592 | E12: =E11/E8 -> 0.68420312 | F12: =F11/F8 -> 0.68400505 | G12: =G11/G8 -> 0.67616162 | H12: =H11/H8 -> 0.67703663 | I12: =I11/I8 -> 0.67971629 | J12: =J11/J8 -> 0.68316481 | ... Q12: =Q11/Q8 -> 0.68440378
A13: Partner margin | C13: =Channel!C29 -> 0.1212288 | D13: =Channel!D29 -> 0.13941312 | E13: =Channel!E29 -> 0.16365888 | F13: =Channel!F29 -> 0.1818432 | G13: =Channel!G29 -> 0.3833424 | H13: =Channel!H29 -> 0.44084376 | I13: =Channel!I29 -> 0.51751224 | J13: =Channel!J29 -> 0.5750136 | ... N13: =Channel!N29 -> 1.3253849 | O13: =SUM(C13:F13) -> 0.606144 | P13: =SUM(G13:J13) -> 1.916712 | Q13: =SUM(K13:N13) -> 4.4179498
A14: Gross profit after partner margin | C14: =C11-C13 -> 69.695285 | D14: =D11-D13 -> 72.442089 | E14: =E11-E13 -> 75.019617 | F14: =F11-F13 -> 77.487391 | G14: =G11-G13 -> 80.729836 | H14: =H11-H13 -> 84.328156 | I14: =I11-I13 -> 88.113455 | J14: =J11-J13 -> 92.159421 | ... N14: =N11-N13 -> 113.03982 | O14: =SUM(C14:F14) -> 294.64438 | P14: =SUM(G14:J14) -> 345.33087 | Q14: =SUM(K14:N14) -> 419.49976
A15: Gross margin after partner margin | B15: =(388.52-53.13-70.02)/388.52 -> 0.6830279 | C15: =C14/C8 -> 0.6953287 | D15: =D14/D8 -> 0.68404948 | E15: =E14/E8 -> 0.68271375 | F15: =F14/F8 -> 0.68240362 | G15: =G14/G8 -> 0.67296607 | H15: =H14/H8 -> 0.67351568 | I15: =I14/I8 -> 0.67574746 | J15: =J14/J8 -> 0.67892875 | ... Q15: =Q14/Q8 -> 0.67727112 | R15: Floor 66% every year incl. partner margin
A16: S&M: existing lines excl. AE pay (inflated) | C16: =Assumptions!$B$52/4*(1+Assumptions!$B$50)^1 -> 15.98745 | D16: =Assumptions!$B$52/4*(1+Assumptions!$B$50)^1 -> 15.98745 | E16: =Assumptions!$B$52/4*(1+Assumptions!$B$50)^1 -> 15.98745 | F16: =Assumptions!$B$52/4*(1+Assumptions!$B$50)^1 -> 15.98745 | G16: =Assumptions!$B$52/4*(1+Assumptions!$B$50)^2 -> 16.946697 | H16: =Assumptions!$B$52/4*(1+Assumptions!$B$50)^2 -> 16.946697 | I16: =Assumptions!$B$52/4*(1+Assumptions!$B$50)^2 -> 16.946697 | J16: =Assumptions!$B$52/4*(1+Assumptions!$B$50)^2 -> 16.946697 | K16: =Assumptions!$B$52/4*(1+Assumptions!$B$50)^3 -> 17.963499 | L16: =Assumptions!$B$52/4*(1+Assumptions!$B$50)^3 -> 17.963499 | M16: =Assumptions!$B$52/4*(1+Assumptions!$B$50)^3 -> 17.963499 | N16: =Assumptions!$B$52/4*(1+Assumptions!$B$50)^3 -> 17.963499 | O16: =SUM(C16:F16) -> 63.9498 | P16: =SUM(G16:J16) -> 67.786788 | Q16: =SUM(K16:N16) -> 71.853995
A17: S&M: AE pay (all AEs) | C17: =Capacity!C32*Assumptions!$B$49*(1+Assumptions!$B$50)^1 -> 9.7701811 | D17: =Capacity!D32*Assumptions!$B$49*(1+Assumptions!$B$50)^1 -> 9.7634824 | E17: =Capacity!E32*Assumptions!$B$49*(1+Assumptions!$B$50)^1 -> 10.630668 | F17: =Capacity!F32*Assumptions!$B$49*(1+Assumptions!$B$50)^1 -> 10.623445 | G17: =Capacity!G32*Assumptions!$B$49*(1+Assumptions!$B$50)^2 -> 11.903756 | H17: =Capacity!H32*Assumptions!$B$49*(1+Assumptions!$B$50)^2 -> 11.899398 | I17: =Capacity!I32*Assumptions!$B$49*(1+Assumptions!$B$50)^2 -> 12.514955 | J17: =Capacity!J32*Assumptions!$B$49*(1+Assumptions!$B$50)^2 -> 12.512073 | K17: =Capacity!K32*Assumptions!$B$49*(1+Assumptions!$B$50)^3 -> 13.951416 | L17: =Capacity!L32*Assumptions!$B$49*(1+Assumptions!$B$50)^3 -> 13.948342 | M17: =Capacity!M32*Assumptions!$B$49*(1+Assumptions!$B$50)^3 -> 14.275988 | N17: =Capacity!N32*Assumptions!$B$49*(1+Assumptions!$B$50)^3 -> 14.276018 | O17: =SUM(C17:F17) -> 40.787776 | P17: =SUM(G17:J17) -> 48.830182 | Q17: =SUM(K17:N17) -> 56.451764
A18: S&M: initiatives (excl. net new AE pay) | C18: =SUM(Investment!P5:P17)+Investment!$J$19/4 -> 0.99 | D18: =SUM(Investment!Q5:Q17)+Investment!$J$19/4 -> 2.85 | E18: =SUM(Investment!R5:R17)+Investment!$J$19/4 -> 4.26 | F18: =SUM(Investment!S5:S17)+Investment!$J$19/4 -> 4.26 | G18: =(Investment!K24)/4 -> 3.13 | H18: =(Investment!K24)/4 -> 3.13 | I18: =(Investment!K24)/4 -> 3.13 | J18: =(Investment!K24)/4 -> 3.13 | K18: =(Investment!L24)/4 -> 3.4175 | L18: =(Investment!L24)/4 -> 3.4175 | M18: =(Investment!L24)/4 -> 3.4175 | N18: =(Investment!L24)/4 -> 3.4175 | O18: =SUM(C18:F18) -> 12.36 | P18: =SUM(G18:J18) -> 12.52 | Q18: =SUM(K18:N18) -> 13.67
A19: Total S&M | B19: 96 | C19: =C16+C17+C18 -> 26.747631 | D19: =D16+D17+D18 -> 28.600932 | E19: =E16+E17+E18 -> 30.878118 | F19: =F16+F17+F18 -> 30.870895 | G19: =G16+G17+G18 -> 31.980453 | H19: =H16+H17+H18 -> 31.976095 | I19: =I16+I17+I18 -> 32.591652 | J19: =J16+J17+J18 -> 32.58877 | ... N19: =N16+N17+N18 -> 35.657017 | O19: =SUM(C19:F19) -> 117.09758 | P19: =SUM(G19:J19) -> 129.13697 | Q19: =SUM(K19:N19) -> 141.97576
A20: R&D (incl. sensor-agnostic readiness) | C20: =Assumptions!$B$56/4*(1+Assumptions!$B$57)^1+Investment!J23/4 -> 32.8298 | D20: =Assumptions!$B$56/4*(1+Assumptions!$B$57)^1+Investment!J23/4 -> 32.8298 | E20: =Assumptions!$B$56/4*(1+Assumptions!$B$57)^1+Investment!J23/4 -> 32.8298 | F20: =Assumptions!$B$56/4*(1+Assumptions!$B$57)^1+Investment!J23/4 -> 32.8298 | G20: =Assumptions!$B$56/4*(1+Assumptions!$B$57)^2+Investment!K23/4 -> 34.640588 | H20: =Assumptions!$B$56/4*(1+Assumptions!$B$57)^2+Investment!K23/4 -> 34.640588 | I20: =Assumptions!$B$56/4*(1+Assumptions!$B$57)^2+Investment!K23/4 -> 34.640588 | J20: =Assumptions!$B$56/4*(1+Assumptions!$B$57)^2+Investment!K23/4 -> 34.640588 | K20: =Assumptions!$B$56/4*(1+Assumptions!$B$57)^3+Investment!L23/4 -> 36.719023 | L20: =Assumptions!$B$56/4*(1+Assumptions!$B$57)^3+Investment!L23/4 -> 36.719023 | M20: =Assumptions!$B$56/4*(1+Assumptions!$B$57)^3+Investment!L23/4 -> 36.719023 | N20: =Assumptions!$B$56/4*(1+Assumptions!$B$57)^3+Investment!L23/4 -> 36.719023 | O20: =SUM(C20:F20) -> 131.3192 | P20: =SUM(G20:J20) -> 138.56235 | Q20: =SUM(K20:N20) -> 146.87609
A21: G&A | C21: =Assumptions!$B$58/4*(1+Assumptions!$B$59)^1 -> 18.0362 | D21: =Assumptions!$B$58/4*(1+Assumptions!$B$59)^1 -> 18.0362 | E21: =Assumptions!$B$58/4*(1+Assumptions!$B$59)^1 -> 18.0362 | F21: =Assumptions!$B$58/4*(1+Assumptions!$B$59)^1 -> 18.0362 | G21: =Assumptions!$B$58/4*(1+Assumptions!$B$59)^2 -> 18.757648 | H21: =Assumptions!$B$58/4*(1+Assumptions!$B$59)^2 -> 18.757648 | I21: =Assumptions!$B$58/4*(1+Assumptions!$B$59)^2 -> 18.757648 | J21: =Assumptions!$B$58/4*(1+Assumptions!$B$59)^2 -> 18.757648 | K21: =Assumptions!$B$58/4*(1+Assumptions!$B$59)^3 -> 19.507954 | L21: =Assumptions!$B$58/4*(1+Assumptions!$B$59)^3 -> 19.507954 | M21: =Assumptions!$B$58/4*(1+Assumptions!$B$59)^3 -> 19.507954 | N21: =Assumptions!$B$58/4*(1+Assumptions!$B$59)^3 -> 19.507954 | O21: =SUM(C21:F21) -> 72.1448 | P21: =SUM(G21:J21) -> 75.030592 | Q21: =SUM(K21:N21) -> 78.031816
A22: EBITDA | B22: -23.31 | C22: =C14-C19-C20-C21 -> -7.9183459 | D22: =D14-D19-D20-D21 -> -7.0248435 | E22: =E14-E19-E20-E21 -> -6.7245004 | F22: =F14-F19-F20-F21 -> -4.2495036 | G22: =G14-G19-G20-G21 -> -4.6488532 | H22: =H14-H19-H20-H21 -> -1.0461754 | I22: =I14-I19-I20-I21 -> 2.1235671 | J22: =J14-J19-J20-J21 -> 6.172415 | ... N22: =N14-N19-N20-N21 -> 21.15583 | O22: =SUM(C22:F22) -> -25.917193 | P22: =SUM(G22:J22) -> 2.6009535 | Q22: =SUM(K22:N22) -> 52.616092
A23: EBITDA margin | C23: =C22/C8 -> -0.078998932 | D23: =D22/D8 -> -0.066333545 | E23: =E22/E8 -> -0.061196111 | F23: =F22/F8 -> -0.037423851 | G23: =G22/G8 -> -0.038752965 | H23: =H22/H8 -> -0.0083556383 | I23: =I22/I8 -> 0.016285766 | J23: =J22/J8 -> 0.045471531 | ... Q23: =Q22/Q8 -> 0.08494727
A24: CAC payback, margin-adjusted (months) | B24: =96/((41+22)*0.683)*12 -> 26.772642 | C24: =C19/((ARR_bridge!C6+ARR_bridge!C7+ARR_bridge!C8)*C15)*12 -> 31.042604 | D24: =D19/((ARR_bridge!D6+ARR_bridge!D7+ARR_bridge!D8)*D15)*12 -> 28.883698 | E24: =E19/((ARR_bridge!E6+ARR_bridge!E7+ARR_bridge!E8)*E15)*12 -> 29.439514 | F24: =F19/((ARR_bridge!F6+ARR_bridge!F7+ARR_bridge!F8)*F15)*12 -> 28.053014 | G24: =G19/((ARR_bridge!G6+ARR_bridge!G7+ARR_bridge!G8)*G15)*12 -> 25.431129 | H24: =H19/((ARR_bridge!H6+ARR_bridge!H7+ARR_bridge!H8)*H15)*12 -> 23.584545 | I24: =I19/((ARR_bridge!I6+ARR_bridge!I7+ARR_bridge!I8)*I15)*12 -> 22.543586 | J24: =J19/((ARR_bridge!J6+ARR_bridge!J7+ARR_bridge!J8)*J15)*12 -> 21.211325 | ... Q24: =Q19/((ARR_bridge!Q6+ARR_bridge!Q7+ARR_bridge!Q8)*Q15)*12 -> 18.84027 | R24: S&M ÷ ((new + expansion ARR) × GM) × 12 (DR3 definition). Cap 30 every quarter, 24 by Q4 FY28.
A25: S&M as % of closing ARR (annualised) | B25: =96/310 -> 0.30967742 | C25: =C19*4/ARR_bridge!C12 -> 0.3362535 | D25: =D19*4/ARR_bridge!D12 -> 0.34781811 | E25: =E19*4/ARR_bridge!E12 -> 0.36249775 | F25: =F19*4/ARR_bridge!F12 -> 0.35186028 | G25: =G19*4/ARR_bridge!G12 -> 0.34897057 | H25: =H19*4/ARR_bridge!H12 -> 0.33321254 | I25: =I19*4/ARR_bridge!I12 -> 0.32383737 | J25: =J19*4/ARR_bridge!J12 -> 0.30840233 | ... N25: =N19*4/ARR_bridge!N12 -> 0.27139916 | O25: =O19/ARR_bridge!O12 -> 0.33366368 | P25: =P19/ARR_bridge!P12 -> 0.30552044 | Q25: =Q19/ARR_bridge!Q12 -> 0.27015791 | R25: FY26 31.0%; ≤ 30% by FY29

Sheet Investment
A1: Investment: FY27 envelope and run-rate cost of initiatives
A2: Costs in ₹ cr. Flags (1/0) say which scenarios include a line. Q2 lines start once the plan is approved (Q2 FY27); H2 lines start in Q3 FY27. AE hiring and channel lines link to the model.
A4: Initiative | B4: FY27 | C4: FY28 | D4: FY29 | E4: Base | F4: Down | G4: Aggr | H4: Capped | I4: Phasing FY27 | J4: Live FY27 | K4: Live FY28 | L4: Live FY29 | M4: Source / what it buys | P4: Q1 FY27 S&M | Q4: Q2 FY27 S&M | R4: Q3 FY27 S&M | S4: Q4 FY27 S&M
A5: Retention squad: 4 CSMs + adoption programme | B5: 1.52 | C5: 1.61 | D5: 1.71 | E5: 1 | F5: 1 | G5: 1 | H5: 1 | I5: Even | J5: =B5*INDEX(E5:H5,Assumptions!$C$5) -> 1.52 | K5: =C5*INDEX(E5:H5,Assumptions!$C$5) -> 1.61 | L5: =D5*INDEX(E5:H5,Assumptions!$C$5) -> 1.71 | M5: Inject 1; churn and contraction assumptions | N5: S&M | P5: =J5*0.25*IF(N5="S&M",1,0) -> 0.38 | Q5: =J5*0.25*IF(N5="S&M",1,0) -> 0.38 | R5: =J5*0.25*IF(N5="S&M",1,0) -> 0.38 | S5: =J5*0.25*IF(N5="S&M",1,0) -> 0.38
A6: Top-30 expansion programme (incentives + 1 solutions architect) | B6: 0.82 | C6: 0.87 | D6: 0.92 | E6: 1 | F6: 1 | G6: 1 | H6: 1 | I6: Q2 | J6: =B6*INDEX(E6:H6,Assumptions!$C$5) -> 0.82 | K6: =C6*INDEX(E6:H6,Assumptions!$C$5) -> 0.87 | L6: =D6*INDEX(E6:H6,Assumptions!$C$5) -> 0.92 | M6: Inject 1; expansion assumption | N6: S&M | P6: =J6*0*IF(N6="S&M",1,0) -> 0 | Q6: =J6*1/3*IF(N6="S&M",1,0) -> 0.27333333 | R6: =J6*1/3*IF(N6="S&M",1,0) -> 0.27333333 | S6: =J6*1/3*IF(N6="S&M",1,0) -> 0.27333333
A7: AE retention pool (tenured AEs) | B7: 1 | C7: 1.06 | D7: 1.12 | E7: 1 | F7: 1 | G7: 1 | H7: 1 | I7: Q2 | J7: =B7*INDEX(E7:H7,Assumptions!$C$5) -> 1 | K7: =C7*INDEX(E7:H7,Assumptions!$C$5) -> 1.06 | L7: =D7*INDEX(E7:H7,Assumptions!$C$5) -> 1.12 | M7: Inject 1; AE attrition assumption | N7: S&M | P7: =J7*0*IF(N7="S&M",1,0) -> 0 | Q7: =J7*1/3*IF(N7="S&M",1,0) -> 0.33333333 | R7: =J7*1/3*IF(N7="S&M",1,0) -> 0.33333333 | S7: =J7*1/3*IF(N7="S&M",1,0) -> 0.33333333
A8: Partner incentives and SPIFFs | B8: 0.4 | C8: 0.5 | D8: 0.6 | E8: 1 | F8: 1 | G8: 1 | H8: 1 | I8: Q2 | J8: =B8*INDEX(E8:H8,Assumptions!$C$5) -> 0.4 | K8: =C8*INDEX(E8:H8,Assumptions!$C$5) -> 0.5 | L8: =D8*INDEX(E8:H8,Assumptions!$C$5) -> 0.6 | M8: Inject 1 / D6 | N8: S&M | P8: =J8*0*IF(N8="S&M",1,0) -> 0 | Q8: =J8*1/3*IF(N8="S&M",1,0) -> 0.13333333 | R8: =J8*1/3*IF(N8="S&M",1,0) -> 0.13333333 | S8: =J8*1/3*IF(N8="S&M",1,0) -> 0.13333333
A9: Value-selling enablement (training, calculator, 1 value engineer) | B9: 0.92 | C9: 0.6 | D9: 0.64 | E9: 1 | F9: 1 | G9: 1 | H9: 1 | I9: Q2 | J9: =B9*INDEX(E9:H9,Assumptions!$C$5) -> 0.92 | K9: =C9*INDEX(E9:H9,Assumptions!$C$5) -> 0.6 | L9: =D9*INDEX(E9:H9,Assumptions!$C$5) -> 0.64 | M9: Inject 1 / D3; win rate and discount | N9: S&M | P9: =J9*0*IF(N9="S&M",1,0) -> 0 | Q9: =J9*1/3*IF(N9="S&M",1,0) -> 0.30666667 | R9: =J9*1/3*IF(N9="S&M",1,0) -> 0.30666667 | S9: =J9*1/3*IF(N9="S&M",1,0) -> 0.30666667
A10: Solutions engineers for paid pilots | B10: 0.64 | C10: 0.68 | D10: 0.72 | E10: 1 | F10: 1 | G10: 1 | H10: 1 | I10: Q2 | J10: =B10*INDEX(E10:H10,Assumptions!$C$5) -> 0.64 | K10: =C10*INDEX(E10:H10,Assumptions!$C$5) -> 0.68 | L10: =D10*INDEX(E10:H10,Assumptions!$C$5) -> 0.72 | M10: Inject 1; proof-of-value (D1 driver) | N10: S&M | P10: =J10*0*IF(N10="S&M",1,0) -> 0 | Q10: =J10*1/3*IF(N10="S&M",1,0) -> 0.21333333 | R10: =J10*1/3*IF(N10="S&M",1,0) -> 0.21333333 | S10: =J10*1/3*IF(N10="S&M",1,0) -> 0.21333333
A11: RevOps analysts (2) + forecasting tool | B11: 1 | C11: 0.85 | D11: 0.9 | E11: 1 | F11: 1 | G11: 1 | H11: 1 | I11: Q2 | J11: =B11*INDEX(E11:H11,Assumptions!$C$5) -> 1 | K11: =C11*INDEX(E11:H11,Assumptions!$C$5) -> 0.85 | L11: =D11*INDEX(E11:H11,Assumptions!$C$5) -> 0.9 | M11: Inject 1 / D4 | N11: S&M | P11: =J11*0*IF(N11="S&M",1,0) -> 0 | Q11: =J11*1/3*IF(N11="S&M",1,0) -> 0.33333333 | R11: =J11*1/3*IF(N11="S&M",1,0) -> 0.33333333 | S11: =J11*1/3*IF(N11="S&M",1,0) -> 0.33333333
A12: Sensor-agnostic tier: launch readiness (no earlier than Q4 FY27) | B12: 0.6 | C12: 0 | D12: 0 | E12: 1 | F12: 1 | G12: 1 | H12: 1 | I12: Even | J12: =B12*INDEX(E12:H12,Assumptions!$C$5) -> 0.6 | K12: =C12*INDEX(E12:H12,Assumptions!$C$5) -> 0 | L12: =D12*INDEX(E12:H12,Assumptions!$C$5) -> 0 | M12: Inject 1; guardrail; cannibalisation plan in D8 | N12: R&D | P12: =J12*0.25*IF(N12="S&M",1,0) -> 0 | Q12: =J12*0.25*IF(N12="S&M",1,0) -> 0 | R12: =J12*0.25*IF(N12="S&M",1,0) -> 0 | S12: =J12*0.25*IF(N12="S&M",1,0) -> 0
A13: Helix-incumbent renewal protection (exec sponsors, MES pack) | B13: 0.8 | C13: 0.85 | D13: 0.9 | E13: 1 | F13: 1 | G13: 1 | H13: 1 | I13: Q2 | J13: =B13*INDEX(E13:H13,Assumptions!$C$5) -> 0.8 | K13: =C13*INDEX(E13:H13,Assumptions!$C$5) -> 0.85 | L13: =D13*INDEX(E13:H13,Assumptions!$C$5) -> 0.9 | M13: Inject 1 / D5; churn | N13: S&M | P13: =J13*0*IF(N13="S&M",1,0) -> 0 | Q13: =J13*1/3*IF(N13="S&M",1,0) -> 0.26666667 | R13: =J13*1/3*IF(N13="S&M",1,0) -> 0.26666667 | S13: =J13*1/3*IF(N13="S&M",1,0) -> 0.26666667
A14: RESERVE: Vajra retention plan (Inject 4) | B14: 0.9 | C14: 0 | D14: 0 | E14: 1 | F14: 1 | G14: 1 | H14: 1 | I14: H2 | J14: =B14*INDEX(E14:H14,Assumptions!$C$5) -> 0.9 | K14: =C14*INDEX(E14:H14,Assumptions!$C$5) -> 0 | L14: =D14*INDEX(E14:H14,Assumptions!$C$5) -> 0 | M14: Inject 4 sheet; released at Q2 review (defensive, all scenarios) | N14: S&M | P14: =J14*0*IF(N14="S&M",1,0) -> 0 | Q14: =J14*0*IF(N14="S&M",1,0) -> 0 | R14: =J14*0.5*IF(N14="S&M",1,0) -> 0.45 | S14: =J14*0.5*IF(N14="S&M",1,0) -> 0.45
A15: RESERVE: second retention squad for Helix-incumbent renewals | B15: 1.6 | C15: 1.7 | D15: 1.8 | E15: 1 | F15: 1 | G15: 1 | H15: 0 | I15: H2 | J15: =B15*INDEX(E15:H15,Assumptions!$C$5) -> 1.6 | K15: =C15*INDEX(E15:H15,Assumptions!$C$5) -> 1.7 | L15: =D15*INDEX(E15:H15,Assumptions!$C$5) -> 1.8 | M15: Inject 1 option (payback 14.1 months); released only if Q2 triggers met | N15: S&M | P15: =J15*0*IF(N15="S&M",1,0) -> 0 | Q15: =J15*0*IF(N15="S&M",1,0) -> 0 | R15: =J15*0.5*IF(N15="S&M",1,0) -> 0.8 | S15: =J15*0.5*IF(N15="S&M",1,0) -> 0.8
A16: RESERVE: restore SE pilot capacity cut in Inject 1 | B16: 0.32 | C16: 0.34 | D16: 0.36 | E16: 1 | F16: 1 | G16: 1 | H16: 0 | I16: H2 | J16: =B16*INDEX(E16:H16,Assumptions!$C$5) -> 0.32 | K16: =C16*INDEX(E16:H16,Assumptions!$C$5) -> 0.34 | L16: =D16*INDEX(E16:H16,Assumptions!$C$5) -> 0.36 | M16: Inject 1 | N16: S&M | P16: =J16*0*IF(N16="S&M",1,0) -> 0 | Q16: =J16*0*IF(N16="S&M",1,0) -> 0 | R16: =J16*0.5*IF(N16="S&M",1,0) -> 0.16 | S16: =J16*0.5*IF(N16="S&M",1,0) -> 0.16
A17: AGGRESSIVE ONLY: extra ₹3 cr items (demand generation for SEA/Gulf) | B17: 1.2 | C17: 1.3 | D17: 1.4 | E17: 0 | F17: 0 | G17: 1 | H17: 0 | I17: H2 | J17: =B17*INDEX(E17:H17,Assumptions!$C$5) -> 0 | K17: =C17*INDEX(E17:H17,Assumptions!$C$5) -> 0 | L17: =D17*INDEX(E17:H17,Assumptions!$C$5) -> 0 | M17: Original ₹18 cr draft | N17: S&M | P17: =J17*0*IF(N17="S&M",1,0) -> 0 | Q17: =J17*0*IF(N17="S&M",1,0) -> 0 | R17: =J17*0.5*IF(N17="S&M",1,0) -> 0 | S17: =J17*0.5*IF(N17="S&M",1,0) -> 0
A18: Net new AEs: pay and recruiting (from Capacity) | I18: Model | J18: =(Capacity!C35*0.25+Capacity!D35*0.25+Capacity!E35*0.25+Capacity!F35*0.25)*Assumptions!$B$49*(1+Assumptions!$B$50)^1+SUM(Capacity!C5:F5)*Assumptions!$B$51 -> 1.9908 | K18: =(Capacity!G35*0.25+Capacity!H35*0.25+Capacity!I35*0.25+Capacity!J35*0.25)*Assumptions!$B$49*(1+Assumptions!$B$50)^2+SUM(Capacity!G5:J5)*Assumptions!$B$51 -> 7.830592 | L18: =(Capacity!K35*0.25+Capacity!L35*0.25+Capacity!M35*0.25+Capacity!N35*0.25)*Assumptions!$B$49*(1+Assumptions!$B$50)^3+SUM(Capacity!K5:N5)*Assumptions!$B$51 -> 12.88241 | M18: Cumulative net new AEs × loaded cost (inflated) + ₹3.5 lakh per hire | N18: S&M
A19: Channel foundation: VP Channel, partner managers, enablement, PRM (from Channel) | I19: Model | J19: =Channel!O17 -> 2.44 | K19: =Channel!P17 -> 3.46 | L19: =Channel!Q17 -> 4 | M19: D6; 3 channel roles in FY27 (cap 6) | N19: S&M
A20: Total incremental investment | J20: =SUM(J5:J19) -> 14.9508 | K20: =SUM(K5:K19) -> 20.350592 | L20: =SUM(L5:L19) -> 26.55241
A21: FY27 envelope for the selected scenario | J21: =IF(Assumptions!$C$5=3,Assumptions!$B$93,Assumptions!$B$92) -> 15
A22: Headroom / (over) in FY27 | J22: =J21-J20 -> 0.0492
A23: of which R&D (outside S&M) | J23: =SUMIF($N$5:$N$19,"R&D",J5:J19) -> 0.6 | K23: =SUMIF($N$5:$N$19,"R&D",K5:K19) -> 0 | L23: =SUMIF($N$5:$N$19,"R&D",L5:L19) -> 0
A24: of which S&M, excluding net new AE pay (already in S&M AE pay line) | J24: =J20-J23-J18 -> 12.36 | K24: =K20-K23-K18 -> 12.52 | L24: =L20-L23-L18 -> 13.67
A26: PAYBACK OF THE INVESTMENT AGAINST DOING NOTHING
A27: Cumulative incremental investment (₹ cr) | J27: =J20 -> 14.9508 | K27: =J27+K20 -> 35.301392 | L27: =K27+L20 -> 61.853802
A28: Incremental ARR vs do-nothing, end of year (₹ cr) | J28: =ARR_bridge!O24 -> 8.5049257 | K28: =ARR_bridge!P24 -> 53.851795 | L28: =ARR_bridge!Q24 -> 136.67145
A29: Investment payback (months) = cumulative investment ÷ (incremental ARR × gross margin) × 12 | J29: =IF(J28<=0,"never",J27/(J28*PnL!O15)*12) -> 30.754697 | K29: =IF(K28<=0,"never",K27/(K28*PnL!P15)*12) -> 11.647061 | L29: =IF(L28<=0,"never",L27/(L28*PnL!Q15)*12) -> 8.0187613 | M29: Stops paying back when incremental ARR ≤ 0, or payback > 30 months (see Sensitivity break-even)
A30: Incremental ARR vs conservative counterfactual (FY26 rates held) | J30: =ARR_bridge!O12-Do_nothing!C14 -> 3.3549257 | K30: =ARR_bridge!P12-Do_nothing!D14 -> 37.912145 | L30: =ARR_bridge!Q12-Do_nothing!E14 -> 103.9947
A31: Investment payback vs conservative counterfactual (months) | J31: =IF(J30<=0,"never",J27/(J30*PnL!O15)*12) -> 77.96489 | K31: =IF(K30<=0,"never",K27/(K30*PnL!P15)*12) -> 16.543911 | L31: =IF(L30<=0,"never",L27/(L30*PnL!Q15)*12) -> 10.53838

Sheet Do_nothing
A1: Counterfactual: do nothing
A2: 64 AEs, no investment, FY24–26 trends continue (win rate falling, Helix pressure on NRR). Used for investment payback and the CEO's question.
A4: Line | B4: FY26 | C4: FY27 | D4: FY28 | E4: FY29 | F4: Note
A5: New-logo ARR | B5: =Assumptions!$B$88 -> 41 | C5: =B5*(1+Assumptions!$B$89) -> 38.95 | D5: =C5*(1+Assumptions!$B$89) -> 37.0025 | E5: =D5*(1+Assumptions!$B$89) -> 35.152375
A6: NRR | B6: =Assumptions!$B$90 -> 0.989 | C6: =B6+Assumptions!$B$91 -> 0.979 | D6: =C6+Assumptions!$B$91 -> 0.969 | E6: =D6+Assumptions!$B$91 -> 0.959
A7: Opening ARR | C7: =B8 -> 310 | D7: =C8 -> 342.44 | E7: =D8 -> 368.82686
A8: Closing ARR | B8: 310 | C8: =C7*C6+C5 -> 342.44 | D8: =D7*D6+D5 -> 368.82686 | E8: =E7*E6+E5 -> 388.85733 | F8: Do-nothing still grows (~9–10% a year) because the base renews; it misses the board path by more each year.
A9: Growth | C9: =C8/C7-1 -> 0.10464516 | D9: =D8/D7-1 -> 0.077055426 | E9: =E8/E7-1 -> 0.054308609
A11: CONSERVATIVE COUNTERFACTUAL: FY26 rates held flat (no further decline)
A12: New-logo ARR | B12: =Assumptions!$B$88 -> 41 | C12: =B12 -> 41 | D12: =C12 -> 41 | E12: =D12 -> 41
A13: NRR | B13: =Assumptions!$B$90 -> 0.989 | C13: =B13 -> 0.989 | D13: =C13 -> 0.989 | E13: =D13 -> 0.989
A14: Closing ARR | B14: 310 | C14: =B14*C13+C12 -> 347.59 | D14: =C14*D13+D12 -> 384.76651 | E14: =D14*E13+E12 -> 421.53408 | F14: Stricter test: credits the plan only with gains beyond FY26 performance

Sheet Inject4
A1: Inject 4: Vajra Auto Components (₹9.5 cr ARR) asks for a competitive re-tender against Helix
A2: Week 8. Renewal due Q4 FY27. Top-five customer (DR2 CU-1095).
A4: ARR at stake (₹ cr) | C4: =Assumptions!$B$87 -> 9.5
A5: Share of FY26 closing ARR | C5: =C4/310 -> 0.030645161
A6: Probability of loss WITHOUT a retention plan | C6: 0.45 | F6: D5: Helix-incumbent re-tenders; HelixAsset free until 31 Mar 2027 (Inject 2); Helix bundle is the #1 churn driver (D1)
A7: Price concession if retained WITHOUT a plan | C7: 0.15 | F7: Reactive discounting at the D5 ceiling
A8: Probability of loss WITH the retention plan (selected scenario) | C8: =Assumptions!$O$20 -> 0.2
A9: Price concession WITH the plan (selected scenario) | C9: =Assumptions!$O$22 -> 0.08
A10: Cost of the retention plan, FY27 (₹ cr) | C10: =Investment!J14 -> 0.9
A12: Expected ARR lost WITHOUT plan (₹ cr) | C12: =C4*C6+C4*(1-C6)*C7 -> 5.05875
A13: Expected ARR lost WITH plan (₹ cr) | C13: =C4*C8+C4*(1-C8)*C9 -> 2.508
A14: Used in ARR bridge, Q4 FY27 (₹ cr) | C14: =C13 -> 2.508
A15: Expected ARR saved by the plan (₹ cr) | C15: =C12-C13 -> 2.55075
A16: Payback of the plan (months, margin-adjusted) | C16: =C10/(C15*PnL!O15)*12 -> 6.1729415
A18: Outcome | B18: Q4 FY27 ARR lost | C18: FY27 closing ARR | D18: FY27 NRR | E18: FY27 growth | F18: Reading
A19: Expected (plan, selected scenario) | B19: =C13 -> 2.508 | C19: =ARR_bridge!O12+ARR_bridge!O11-B19 -> 350.94493 | D19: =ARR_bridge!O21+(ARR_bridge!O11-B19)/ARR_bridge!O5 -> 0.99105967 | E19: =C19/ARR_bridge!O5-1 -> 0.13208041
A20: Retained at plan concession | B20: =C4*C9 -> 0.76 | C20: =ARR_bridge!O12+ARR_bridge!O11-B20 -> 352.69293 | D20: =ARR_bridge!O21+(ARR_bridge!O11-B20)/ARR_bridge!O5 -> 0.99669838 | E20: =C20/ARR_bridge!O5-1 -> 0.13771912
A21: Lost | B21: =C4 -> 9.5 | C21: =ARR_bridge!O12+ARR_bridge!O11-B21 -> 343.95293 | D21: =ARR_bridge!O21+(ARR_bridge!O11-B21)/ARR_bridge!O5 -> 0.96850484 | E21: =C21/ARR_bridge!O5-1 -> 0.10952557 | F21: Losing Vajra costs ~3 pts of FY27 NRR on its own
A22: Expected WITHOUT plan | B22: =C12 -> 5.05875 | C22: =ARR_bridge!O12+ARR_bridge!O11-B22 -> 348.39418 | D22: =ARR_bridge!O21+(ARR_bridge!O11-B22)/ARR_bridge!O5 -> 0.98283145 | E22: =C22/ARR_bridge!O5-1 -> 0.12385218
A24: Forecast effect: Q4 FY27 net new ARR, expected vs retained vs lost (₹ cr)
A25: Q4 FY27 net ARR added (model, expected) | C25: =ARR_bridge!F12-ARR_bridge!F5 -> 10.218753
A26: If lost | C26: =C25+C14-C4 -> 3.2267527
A27: If retained at plan concession | C27: =C25+C14-C4*C9 -> 11.966753
A29: RETENTION PLAN
A30: 1. Week 8–9: CEO and CRO meet Vajra's MD and CFO; agree re-tender scope and evaluation criteria before Helix sets them.
A31: 2. Business review from Vajra's own usage data: assets monitored, failures caught, downtime avoided (D3 value model applied to their plants).
A32: 3. Offer a 3-year renewal with price lock and a capped concession (8% base, within the D5 15% limit), plus expansion to the two plants not yet covered.
A33: 4. MES integration pack and named executive sponsor (Helix-incumbent renewal protection line); dedicated CSM from the retention squad.
A34: 5. Do not match 'free': HelixAsset is free only until 31 Mar 2027; show the three-year total cost and switching risk (D5 Helix battlecard).
A35: 6. Triggers: exec meeting held by week 10; business review delivered by end-Q2; if Vajra shortlists Helix on price alone, escalate to CEO with the 3-year offer; decision expected Jan 2027.

Sheet Traceability
A1: Traceability map: every major assumption and where it came from
A3: Assumption (model location) | B3: Value used (Base) | C3: Evidence and source | D3: Owner deliverable
A4: Opening ARR and FY26 bridge (ARR_bridge B12) | B4: ₹310 cr; +41 new, +22 exp, −9 con, −16 churn | C4: DR3 pl_quarterly; DR2 arr_movements | D4: D1
A5: Direct win rate FY26 (Assumptions) | B5: 17.1% | C5: DR1 cleaned (30 duplicates, 16 tests, 88 DQ-as-lost removed; D1 rules) | D5: D1
A6: Win-rate path | B6: 19.5% / 21.5% / 22.5% | C6: D2 tier mix (+2.9 pts at full effect); D5 battlecards (+0.6 pts beyond D2); Inject 2 holds Helix-incumbent win at 7% | D6: D2, D5
A7: Sales cycle | B7: 8.1 → 7.3 months | C7: DR1 stage history; D4 stage-exit rules; D3 business-case discipline | D7: D1, D3, D4
A8: Deal size and discount | B8: ₹71.4 → 77 lakh list; 19.3% → 15% | C8: DR1 FY26 won deals; D3 negotiation plan; D5 discount limits (cap 15%) | D8: D3, D5
A9: Win-rate response to discount | B9: 0.1 pt per pt | C9: D1 discount-creep test; D5 DISCOUNT-NO-EFFECT interview code (to validate in interviews) | D9: D1, D5
A10: Qualified pipeline supply | B10: 380 / 430 / 470 deals | C10: DR1 FY26 392; D2 tiering and ₹24 cr programme reallocation | D10: D2
A11: Deals an AE carries at once | B11: 5.4 | C11: DR3 ae_quarterly (48.5 ramped-AE years) × DR1 closes and cycle | D11: D1, D2
A12: Ramp weights by tenure | B12: 0 / 0.33 / 0.66 / 1.0 | C12: D1 productivity by tenure ₹0 / 0.29 / 0.59 / 0.89 cr (DR3); management's 6-month ramp rejected | D12: D1
A13: AE attrition | B13: 29% → 24% / 22% / 20% | C13: DR3 roster; Inject 1 AE retention pool | D13: D1, Inject 1
A14: Net new AE hires | B14: 6 (Q3 FY27), 8 (FY28), 6 (FY29) | C14: Inject 1 re-prioritisation; guardrail ≤ 12 in FY27 | D14: Inject 1, D2
... A29: Primary evidence | B29: 8 interviews (in progress) | C29: Interview kit and log; codes cited above are flagged until interviews are coded | D29: Kit
