Workbook

Sheet README
A1: D6 PARTNER ECONOMICS WORKBOOK
A2: Company | B2: Strata Sense is fictional; synthetic data (MBA capstone).
A3: Colour code | B3: Blue = input; yellow = key assumption; black = formula; green = link.
A4: Sheets | B4: Inputs · Partner_ramp (active partners and partner-sourced ARR) · Channel_PL · GM_floor · Breakeven · Inject3 · Partners_14 · Prospects_12 · Checks
A5: Sources | B5: DR6 partner file; D1 (partner win rates by region, FY26 partner-sourced ARR ₹2.6 cr); D2 (FY27 partner target); D4 base scenario (FY28–29 new-logo); DR3 (gross margin, S&M).
A6: No double counting | B6: A partner-sourced deal worked by an AE is counted once in bookings, as partner-sourced. The AE receives 50% quota credit (comp only, not bookings).

Sheet Inputs
A1: Inputs
A4: Input | B4: FY27 | C4: FY28 | D4: FY29 | E4: Source / note
A5: Total new-logo ARR in plan (₹ cr) | B5: 46.5 | C5: 62.1 | D5: 78 | E5: D2 (FY27); D4 base scenario (FY28–29)
A6: Target partner-sourced share of new-logo ARR | D6: 0.25 | E6: Board objective 5 (FY29)
A7: Productivity of a mature active partner (₹ cr sourced ARR / yr) | B7: 1.2 | C7: 1.2 | D7: 1.2 | E7: Assumption: ~10 qualified opps × 34% win (SEA partner deals, D1) × ₹37 lakh partner deal (FY26)
A8: Ramp: activation-year productivity (share of mature) | B8: 0.15 | C8: 0.15 | D8: 0.15 | E8: Assumption: activated mid-year on average, first deal after 6–9 months (half a year at 30%)
A9: Ramp: second-year productivity (share of mature) | B9: 0.6 | C9: 0.6 | D9: 0.6 | E9: Assumption; 100% from the third year
A10: Existing active partners' sourced ARR (₹ cr) | B10: 2.6 | C10: 2.6 | D10: 2.6 | E10: FY26 actual (D1, after re-tagging)
A11: Blended gross margin before partner margin | B11: 0.683 | C11: 0.683 | D11: 0.683 | E11: DR3 FY26
A12: Direct S&M cost per ₹1 of new-logo ARR | B12: 1.64 | C12: 1.64 | D12: 1.64 | E12: DR3: ~70% of ₹96 cr S&M ÷ ₹41 cr new-logo ARR (allocation assumption)
A13: Direct effort still needed on partner deals (share) | B13: 0.4 | C13: 0.35 | D13: 0.3 | E13: AE co-sell and SE support; falls as partners certify
A14: Mix: referral / resell / gold (share of partner ARR) | B14: 30/50/20 | C14: 25/50/25 | D14: 20/50/30 | E14: Design choice
A17: PROGRAMME ECONOMICS
A18: Role / tier | B18: Year-1 margin | C18: Renewal margin (yrs 2–3) | D18: Share FY27 | E18: Share FY28 | F18: Share FY29
A19: Referral (registered) | B19: 0.1 | C19: 0 | D19: 0.3 | E19: 0.25 | F19: 0.2
A20: Silver (resell / co-sell) | B20: 0.18 | C20: 0.08 | D20: 0.5 | E20: 0.5 | F20: 0.5
A21: Gold (resell + certified services) | B21: 0.22 | C21: 0.1 | D21: 0.2 | E21: 0.25 | F21: 0.3
A22: Blended year-1 margin FY27 / FY28 / FY29 | D22: =SUMPRODUCT($B$19:$B$21,D19:D21) -> 0.164 | E22: =SUMPRODUCT($B$19:$B$21,E19:E21) -> 0.17 | F22: =SUMPRODUCT($B$19:$B$21,F19:F21) -> 0.176
A23: Blended renewal margin FY27 / FY28 / FY29 | D23: =SUMPRODUCT($C$19:$C$21,D19:D21) -> 0.06 | E23: =SUMPRODUCT($C$19:$C$21,E19:E21) -> 0.065 | F23: =SUMPRODUCT($C$19:$C$21,F19:F21) -> 0.07
A25: CHANNEL TEAM AND PROGRAMME COSTS (₹ cr / yr)
A26: Item | B26: FY27 | C26: FY28 | D26: FY29 | E26: Note
A27: VP Channel | B27: 0.9 | C27: 0.9 | D27: 0.9 | E27: 1 role (vacant today)
A28: Partner managers (count) | B28: 2 | C28: 4 | D28: 5 | E28: FY27: 2 SEA; within 6 channel roles
A29: Cost per partner manager | B29: 0.42 | C29: 0.44 | D29: 0.46 | E29: HR benchmark ₹38–45 lakh (DR3), inflated
A30: Enablement and certification | B30: 0.4 | C30: 0.5 | D30: 0.5 | E30: Training, demo kits
A31: PRM / deal-registration tool | B31: 0.3 | C31: 0.3 | D31: 0.3
A32: Partner marketing (MDF) | B32: 1.5 | C32: 2 | D32: 2.5 | E32: FY27 from the ₹24 cr programme budget (D2)
A33: Channel fixed cost (₹ cr) | B33: =B27+B28*B29+B30+B31+B32 -> 3.94 | C33: =C27+C28*C29+C30+C31+C32 -> 5.46 | D33: =D27+D28*D29+D30+D31+D32 -> 6.5

Sheet Partner_ramp
A1: Active partners and partner-sourced ARR
A2: Cohort ramp: recruits contribute 15% of mature productivity in the year they are activated, 60% the next year, 100% after
A4: Line | B4: FY27 | C4: FY28 | D4: FY29 | E4: Note
A5: New partners activated in year (count) | B5: 8 | C5: 9 | D5: 5 | E5: FY27: 6 prospects (PR01, PR02, PR06, PR07, PR09, PR10) + P07, P10 reactivated; FY28: 3 held prospects + 6 new
A6: Existing partners retained (after keep/fix/exit and Inject 3) | B6: 6 | C6: 6 | D6: 6 | E6: P02, P09, P12, P13 + P05, P11 restricted (P07, P10 counted as FY27 activations)
A7: Existing partners' sourced ARR after Inject 3 (₹ cr) | B7: =Inputs!B10*(1-Inject3!B8) -> 2.2559339 | C7: =B7*1.1 -> 2.4815273 | D7: =C7*1.1 -> 2.72968
A8: ARR from FY27 recruits (₹ cr) | B8: =B5*Inputs!B7*Inputs!B8 -> 1.44 | C8: =B5*Inputs!C7*Inputs!C9 -> 5.76 | D8: =B5*Inputs!D7 -> 9.6
A9: ARR from FY28 recruits (₹ cr) | C9: =C5*Inputs!C7*Inputs!C8 -> 1.62 | D9: =C5*Inputs!D7*Inputs!D9 -> 6.48
A10: ARR from FY29 recruits (₹ cr) | D10: =D5*Inputs!D7*Inputs!D8 -> 0.9
A11: Partner-sourced new-logo ARR (₹ cr) | B11: =SUM(B7:B10) -> 3.6959339 | C11: =SUM(C7:C10) -> 9.8615273 | D11: =SUM(D7:D10) -> 19.70968
A12: Share of new-logo ARR | B12: =B11/Inputs!B5 -> 0.07948245 | C12: =C11/Inputs!C5 -> 0.15880076 | D12: =D11/Inputs!D5 -> 0.25268821
A13: Active partners (count) | B13: =B6+B5 -> 14 | C13: =B13+C5 -> 23 | D13: =C13+D5 -> 28
A14: Surplus / (gap) vs 25% in FY29 (₹ cr) | D14: =D11-Inputs!D6*Inputs!D5 -> 0.20968004
A15: Mature-equivalent partners needed for 25% in FY29 | D15: =Inputs!D6*Inputs!D5/Inputs!D7 -> 16.25
A16: FY29 share if mature productivity is ₹0.8 / 1.0 / 1.4 cr (recruit ARR scaled) | B16: =(D7+(D8+D9+D10)*0.8/Inputs!D7)/Inputs!D5 -> 0.1801241 | C16: =(D7+(D8+D9+D10)*1/Inputs!D7)/Inputs!D5 -> 0.21640615 | D16: =(D7+(D8+D9+D10)*1.4/Inputs!D7)/Inputs!D5 -> 0.28897026
A18: Reading: the ramp is the constraint. Partners recruited in FY29 contribute little that year, so 25% depends on 17 activations in FY27–28 reaching ~₹1.2 cr each. At ₹1.0 cr the share is ~21%.
A19: the ramp is the constraint. Partners recruited in FY29 contribute little that year, so the 25% goal depends on recruiting in FY27–28.

Sheet Channel_PL
A1: Channel profit and loss (₹ cr)
A2: Two lenses: incremental (channel ARR the direct team would not win) and substitution (channel replaces direct selling cost)
A4: Line | B4: FY27 | C4: FY28 | D4: FY29 | E4: Note
A5: Partner-sourced new-logo ARR | B5: =Partner_ramp!B11 -> 3.6959339 | C5: =Partner_ramp!C11 -> 9.8615273 | D5: =Partner_ramp!D11 -> 19.70968
A6: Year-1 partner margin | B6: =B5*Inputs!D22 -> 0.60613316 | C6: =C5*Inputs!E22 -> 1.6764596 | D6: =D5*Inputs!F22 -> 3.4689037
A7: Renewal margin on prior partner cohorts | B7: =0 -> 0 | C7: =B5*Inputs!E23 -> 0.2402357 | D7: =(B5+C5)*Inputs!F23 -> 0.94902229
A8: Channel fixed cost | B8: =Inputs!B33 -> 3.94 | C8: =Inputs!C33 -> 5.46 | D8: =Inputs!D33 -> 6.5
A9: Direct effort still used on partner deals | B9: =B5*Inputs!B13*Inputs!B12 -> 2.4245327 | C9: =C5*Inputs!C13*Inputs!C12 -> 5.6605167 | D9: =D5*Inputs!D13*Inputs!D12 -> 9.6971626
A10: Total channel cost | B10: =B6+B7+B8+B9 -> 6.9706658 | C10: =C6+C7+C8+C9 -> 13.037212 | D10: =D6+D7+D8+D9 -> 20.615089
A11: Incremental lens: first-year gross profit on partner ARR | B11: =B5*Inputs!B11 -> 2.5243229 | C11: =C5*Inputs!C11 -> 6.7354232 | D11: =D5*Inputs!D11 -> 13.461711
A12: Incremental lens: channel profit / (loss), first year | B12: =B11-B10 -> -4.4463429 | C12: =C11-C10 -> -6.3017889 | D12: =D11-D10 -> -7.1533771
A13: Substitution lens: direct S&M cost avoided | B13: =B5*Inputs!B12 -> 6.0613316 | C13: =C5*Inputs!C12 -> 16.172905 | D13: =D5*Inputs!D12 -> 32.323875
A14: Substitution lens: saving / (extra cost) vs direct | B14: =B13-B10 -> -0.90933419 | C14: =C13-C10 -> 3.1356928 | D14: =D13-D10 -> 11.708787
A16: Three-year value of one year's partner ARR (GP × 3 − yr-1 margin − 2 yrs renewal margin), FY29 cohort | D16: =D5*(3*Inputs!D11-Inputs!F22-2*Inputs!F23) -> 34.156876
A17: Reading: on a first-year basis the channel loses money until partner ARR scales; on the three-year value of each cohort it pays back comfortably.

Sheet GM_floor
A1: Blended gross margin with partner margin included
A2: Guardrail: ≥66% every year, after partner margin. Today partner margin is booked in S&M, outside gross margin.
A4: Line | B4: FY27 | C4: FY28 | D4: FY29 | E4: Note
A5: Total revenue (₹ cr, approx.) | B5: 433 | C5: 510 | D5: 610 | E5: Subscription ≈ average ARR (D4 base) + hardware; D7 replaces
A6: Gross margin before partner margin | B6: =Inputs!B11 -> 0.683 | C6: =Inputs!C11 -> 0.683 | D6: =Inputs!D11 -> 0.683
A7: Partner margin (₹ cr) | B7: =Channel_PL!B6+Channel_PL!B7 -> 0.60613316 | C7: =Channel_PL!C6+Channel_PL!C7 -> 1.9166953 | D7: =Channel_PL!D6+Channel_PL!D7 -> 4.417926
A8: Gross margin after partner margin | B8: =(B5*B6-B7)/B5 -> 0.68160015 | C8: =(C5*C6-C7)/C5 -> 0.67924177 | D8: =(D5*D6-D7)/D5 -> 0.6757575
A9: Headroom over 66% floor (pts) | B9: =(B8-0.66)*100 -> 2.1600154 | C9: =(C8-0.66)*100 -> 1.9241774 | D9: =(D8-0.66)*100 -> 1.5757498
A10: Partner margin that would breach the floor (₹ cr) | B10: =B5*(B6-0.66) -> 9.959 | C10: =C5*(C6-0.66) -> 11.73 | D10: =D5*(D6-0.66) -> 14.03

Sheet Breakeven
A1: At what partner productivity does the channel lose money?
A2: FY29, at the planned number of active partners. Three lenses; the substitution lens is the decision lens.
A4: Active partners FY29 | B4: =Partner_ramp!D13 -> 28
A5: Channel fixed cost FY29 (₹ cr) | B5: =Inputs!D33 -> 6.5
A7: 1. SUBSTITUTION (decision lens): partner deals replace direct selling
A8: Saving per ₹1 of partner ARR: direct S&M avoided × (1 − direct effort) − year-1 partner margin | B8: =Inputs!D12*(1-Inputs!D13)-Inputs!F22 -> 0.972
A9: Break-even sourced ARR per active partner (₹ cr / yr) | B9: =B5/(B4*B8) -> 0.2388301 | C9: Below this, the channel costs more than selling direct
A11: 2. INCREMENTAL, THREE-YEAR: partner ARR the direct team would not have won
A12: Contribution per ₹1: 3 yrs gross profit − yr-1 margin − 2 yrs renewal margin − direct effort | B12: =3*Inputs!D11-Inputs!F22-2*Inputs!F23-Inputs!D13*Inputs!D12 -> 1.241
A13: Break-even sourced ARR per active partner (₹ cr / yr) | B13: =B5/(B4*B12) -> 0.18706113
A15: 3. INCREMENTAL, FIRST YEAR ONLY (shown for completeness)
A16: Contribution per ₹1: yr-1 gross profit − yr-1 margin − direct effort | B16: =Inputs!D11-Inputs!F22-Inputs!D13*Inputs!D12 -> 0.015
A17: Break-even sourced ARR per active partner (₹ cr / yr) | B17: =IF(B16<=0,"never",B5/(B4*B16)) -> 15.47619 | C17: Near-zero contribution: no subscription business pays back in year one
A19: FY26 actual: sourced ARR per active partner (₹ cr) | B19: =(0.69+0.85+0+0.41)/4 -> 0.4875
A20: FY26 actual: sourced ARR per signed partner (₹ cr) | B20: =Inputs!D10/14 -> 0.18571429
A21: Planned mature productivity (₹ cr) | B21: =Inputs!D7 -> 1.2
A23: Answer for the panel: the channel loses money if active partners average less than the substitution break-even above (about a quarter of a crore a year). FY26's active partners averaged about ₹0.5 cr, but spread across all 14 signed partners the figure falls to about ₹0.19 cr, below break-even. The risk is not the good partners; it is carrying inactive ones. Hence the exits and the two-quarter activation rule.

Sheet Inject3
A1: Inject 3: two active partners (P05, P11) announce joint programmes with Helix
A2: Week 7
A4: Open partner-sourced pipeline, all partners (₹ cr) | B4: 14.83 | C4: DR1 open deals, partner-sourced (re-tagged)
A5: of which P05 + P11 (₹ cr) | B5: 7.85
A6: Share of open partner-sourced pipeline at risk | B6: =B5/B4 -> 0.52933243
A7: Haircut applied to P05/P11 pipeline (assumption) | B7: 0.5 | C7: Their deals in Helix-incumbent accounts likely switch to Helix
A8: Reduction to existing partners' FY27 sourced ARR | B8: =B6*B7*0.5 -> 0.13233311 | C8: P05+P11 were half of FY26 sourced ARR (₹1.26 of ₹2.61 cr); half of that at risk
A9: FY27 partner-sourced ARR before Inject 3 (D2) | B9: 4
A10: FY27 partner-sourced ARR after Inject 3 (this model) | B10: =Partner_ramp!B11 -> 3.6959339
A11: Gap handed to D7 (₹ cr) | B11: =B9-B10 -> 0.30406608 | C11: D2 direct capacity had ₹2.9 cr headroom; D7 reconciles
A13: Response
A14: P05 and P11 move to 'restricted': no deal registration in Helix-incumbent accounts; keep services and non-Helix accounts.
A15: Competing-product disclosure required at registration; conflict check by the channel manager within 48 hours.
A16: Exclusivity is not demanded (we could not enforce it); protection is earned by registered, non-conflicted deals.
A17: Accelerate non-Helix SEA recruits (PR01, PR02, PR06) to first-quarter onboarding; PR05, PR08, PR12 (Helix-affiliated) deprioritised.
A18: Review P05/P11 scorecards at the end of Q2 FY27: exit if registered-deal conversion < 15% or any Helix switch on a registered deal.

Sheet Partners_14
A1: ID | B1: Partner | C1: Status | D1: Sourced FY26 (₹ cr) | E1: Influenced FY26 | F1: Win rate FY24–26 | G1: Open pipeline (₹ cr) | H1: Helix-tied | I1: Decision | J1: Reason
A2: P01 | B2: Gulf Automation Services LLC | C2: Inactive | D2: 0 | E2: 0 | F2: 0.5 | G2: 0 | H2: No | I2: Exit | J2: Inactive since FY24; no pipeline; Gulf coverage moves to PR07/PR08 review
A3: P02 | B3: Deccan Industrial Systems Pvt Ltd | C3: Active | D3: 0.69 | E3: 0.37 | F3: 0.216 | G3: 4.24 | H3: No | I3: Keep: Gold | J3: 22% win rate, ₹4.2 cr open pipeline, non-Helix, 6 certified engineers
A4: P03 | B4: Coromandel Controls | C4: Inactive | D4: 0.22 | E4: 0 | F4: 0.5 | G4: 0.3 | H4: No | I4: Exit | J4: One deal in three years
A5: P04 | B5: Northern Drives & Automation | C5: Inactive | D5: 0 | E5: 0 | F5: 0 | G5: 0 | H5: No | I5: Exit | J5: No activity
A6: P05 | B6: Sahyadri Automation Pvt Ltd | C6: Active | D6: 0.85 | E6: 0 | F6: 0.213 | G6: 3.11 | H6: Yes | I6: Fix: restricted | J6: Solid (21% win) but Helix integrator; Inject 3 → no registration in Helix-incumbent accounts
A7: P06 | B7: Najd Engineering Co. | C7: Inactive | D7: 0 | E7: 0 | F7: 0 | G7: 0 | H7: No | I7: Exit | J7: No activity; Saudi coverage via PR07
A8: P07 | B8: Mekong Industrial Tech | C8: Signed, no deals | D8: 0 | E8: 0 | G8: 0 | H8: No | I8: Fix: 2-quarter activation | J8: Vietnam access; certify 2 engineers by Q2 or exit
A9: P08 | B9: Hosur Machine Builders | C9: Signed, no deals | D9: 0 | E9: 0 | G9: 0 | H9: No | I9: Fix: OEM pilot | J9: Machine-builder embed pilot alongside PR09/PR10
A10: P09 | B10: Vindhya Reliability Services | C10: Active | D10: 0 | E10: 0.54 | F10: 0.178 | G10: 7.11 | H10: No | I10: Keep: Gold (services) | J10: Reliability MSP; ₹7.1 cr open pipeline; strongest influence partner
A11: P10 | B11: Penang Plant Solutions Sdn Bhd | C11: Signed, no deals | D11: 0 | E11: 0 | G11: 0 | H11: No | I11: Fix: 2-quarter activation | J11: Malaysia access; joint pipeline plan by Q2 or exit
A12: P11 | B12: Konkan Process Automation Ltd | C12: Active | D12: 0.41 | E12: 0.91 | F12: 0.133 | G12: 6.31 | H12: Yes | I12: Fix: probation | J12: Most volume but 13% win rate; Helix gold partner (Inject 3); referral-only until scorecard met
A13: P12 | B13: Siam Reliability Co. | C13: Occasional | D13: 0.44 | E13: 0 | F13: 0.2 | G13: 0 | H13: No | I13: Keep: Silver, grow | J13: Thailand; SEA partner deals win 34%
A14: P13 | B14: Al Fajr Industrial Services | C14: Occasional | D14: 0 | E14: 0 | F14: 0.25 | G14: 0 | H14: No | I14: Keep: Silver | J14: Gulf access; occasional
A15: P14 | B15: Ganga Electricals | C15: Inactive | D15: 0 | E15: 0 | F15: 0 | G15: 0 | H15: No | I15: Exit | J15: No activity

Sheet Prospects_12
A1: Prospective partners: scored shortlist
A2: Weights in row 4 (blue). Scores 1–5. Conflict: Helix-affiliated = 1.
A3: ID | B3: Prospect | C3: Type | D3: Region | E3: Access (overlap, priority region) | F3: Capability (engineers) | G3: Vertical fit | H3: Conflict risk (5 = none) | I3: Commitment | J3: Weighted score | K3: Rank | L3: Decision
A4: Weights | E4: 0.3 | F4: 0.2 | G4: 0.15 | H4: 0.2 | I4: 0.15
A5: PR01 | B5: Java Integrasi Teknik | C5: System integrator | D5: SEA (Indonesia) | E5: 5 | F5: 5 | G5: 4 | H5: 5 | I5: 5 | J5: =SUMPRODUCT(E5:I5,$E$4:$I$4) -> 4.85 | K5: =RANK(J5,$J$5:$J$16) -> 1 | L5: =IF(K5<=6,"Recruit FY27",IF(H5=1,"Deprioritise (Helix-tied)","Hold for FY28")) -> Recruit FY27
A6: PR02 | B6: Chao Phraya Automation Co. | C6: System integrator | D6: SEA (Thailand) | E6: 5 | F6: 4 | G6: 4 | H6: 5 | I6: 5 | J6: =SUMPRODUCT(E6:I6,$E$4:$I$4) -> 4.65 | K6: =RANK(J6,$J$5:$J$16) -> 2 | L6: =IF(K6<=6,"Recruit FY27",IF(H6=1,"Deprioritise (Helix-tied)","Hold for FY28")) -> Recruit FY27
A7: PR03 | B7: Saigon Reliability JSC | C7: Managed-service provider | D7: SEA (Vietnam) | E7: 4 | F7: 3 | G7: 3 | H7: 5 | I7: 3 | J7: =SUMPRODUCT(E7:I7,$E$4:$I$4) -> 3.7 | K7: =RANK(J7,$J$5:$J$16) -> 7 | L7: =IF(K7<=6,"Recruit FY27",IF(H7=1,"Deprioritise (Helix-tied)","Hold for FY28")) -> Hold for FY28
A8: PR04 | B8: Luzon Plant Services Inc. | C8: Managed-service provider | D8: SEA (Philippines) | E8: 3 | F8: 2 | G8: 3 | H8: 5 | I8: 3 | J8: =SUMPRODUCT(E8:I8,$E$4:$I$4) -> 3.2 | K8: =RANK(J8,$J$5:$J$16) -> 9 | L8: =IF(K8<=6,"Recruit FY27",IF(H8=1,"Deprioritise (Helix-tied)","Hold for FY28")) -> Hold for FY28
A9: PR05 | B9: Malacca Automation Sdn Bhd | C9: Automation distributor | D9: SEA (Malaysia) | E9: 4 | F9: 3 | G9: 3 | H9: 1 | I9: 3 | J9: =SUMPRODUCT(E9:I9,$E$4:$I$4) -> 2.9 | K9: =RANK(J9,$J$5:$J$16) -> 11 | L9: =IF(K9<=6,"Recruit FY27",IF(H9=1,"Deprioritise (Helix-tied)","Hold for FY28")) -> Deprioritise (Helix-tied)
A10: PR06 | B10: Merlion Industrial Pte Ltd | C10: Value-added reseller | D10: SEA regional (Singapore HQ) | E10: 5 | F10: 4 | G10: 4 | H10: 5 | I10: 4 | J10: =SUMPRODUCT(E10:I10,$E$4:$I$4) -> 4.5 | K10: =RANK(J10,$J$5:$J$16) -> 3 | L10: =IF(K10<=6,"Recruit FY27",IF(H10=1,"Deprioritise (Helix-tied)","Hold for FY28")) -> Recruit FY27
A11: PR07 | B11: Arabian Asset Care Co. | C11: Managed-service provider | D11: Middle East (Saudi Arabia) | E11: 5 | F11: 4 | G11: 4 | H11: 5 | I11: 4 | J11: =SUMPRODUCT(E11:I11,$E$4:$I$4) -> 4.5 | K11: =RANK(J11,$J$5:$J$16) -> 3 | L11: =IF(K11<=6,"Recruit FY27",IF(H11=1,"Deprioritise (Helix-tied)","Hold for FY28")) -> Recruit FY27
A12: PR08 | B12: Emirates Crest Engineering LLC | C12: System integrator | D12: Middle East (UAE) | E12: 4 | F12: 3 | G12: 4 | H12: 1 | I12: 3 | J12: =SUMPRODUCT(E12:I12,$E$4:$I$4) -> 3.05 | K12: =RANK(J12,$J$5:$J$16) -> 10 | L12: =IF(K12<=6,"Recruit FY27",IF(H12=1,"Deprioritise (Helix-tied)","Hold for FY28")) -> Deprioritise (Helix-tied)
A13: PR09 | B13: Tapti Press Machines Ltd | C13: Machine builder (OEM embed) | D13: India (national) | E13: 5 | F13: 2 | G13: 5 | H13: 5 | I13: 5 | J13: =SUMPRODUCT(E13:I13,$E$4:$I$4) -> 4.4 | K13: =RANK(J13,$J$5:$J$16) -> 5 | L13: =IF(K13<=6,"Recruit FY27",IF(H13=1,"Deprioritise (Helix-tied)","Hold for FY28")) -> Recruit FY27
A14: PR10 | B14: Shivalik Compressors Ltd | C14: Machine builder (OEM embed) | D14: India (national) | E14: 5 | F14: 2 | G14: 4 | H14: 5 | I14: 3 | J14: =SUMPRODUCT(E14:I14,$E$4:$I$4) -> 3.95 | K14: =RANK(J14,$J$5:$J$16) -> 6 | L14: =IF(K14<=6,"Recruit FY27",IF(H14=1,"Deprioritise (Helix-tied)","Hold for FY28")) -> Recruit FY27
A15: PR11 | B15: Narmada Reliability Services | C15: Managed-service provider | D15: India-East | E15: 3 | F15: 2 | G15: 4 | H15: 5 | I15: 3 | J15: =SUMPRODUCT(E15:I15,$E$4:$I$4) -> 3.35 | K15: =RANK(J15,$J$5:$J$16) -> 8 | L15: =IF(K15<=6,"Recruit FY27",IF(H15=1,"Deprioritise (Helix-tied)","Hold for FY28")) -> Hold for FY28
A16: PR12 | B16: Nilgiri Drives Pvt Ltd | C16: Automation distributor | D16: India-South | E16: 3 | F16: 3 | G16: 3 | H16: 1 | I16: 1 | J16: =SUMPRODUCT(E16:I16,$E$4:$I$4) -> 2.3 | K16: =RANK(J16,$J$5:$J$16) -> 12 | L16: =IF(K16<=6,"Recruit FY27",IF(H16=1,"Deprioritise (Helix-tied)","Hold for FY28")) -> Deprioritise (Helix-tied)

Sheet Risk_sim
A1: How likely is the channel to lose money? Monte Carlo, 20,000 runs
A2: Values pasted from risk_sim.py (plan case) and risk_sim_down.py (FY26-like partners). Loss = partner ARR below substitution break-even.
A4: Case / year | B4: P10 partner ARR | C4: P50 | D4: P90 | E4: Break-even ARR | F4: P(channel loses money) | G4: P(share ≥ 25%) | H4: Median share
A5: Plan case: 70% activation, median ₹1.0 cr / partner
A6: FY27 | B6: 2.6583 | C6: 3.3933 | D6: 4.3727 | E6: 4.8049 | F6: 0.957 | G6: 0 | H6: 0.073
A7: FY28 | B7: 6.1655 | C7: 9.2439 | D7: 13.6932 | E7: 6.0938 | F7: 0.094 | G7: 0.0439 | H7: 0.1489
A8: FY29 | B8: 12.0544 | C8: 18.8415 | D8: 28.5067 | E8: 6.6872 | F8: 0.0039 | G8: 0.4582 | H8: 0.2416
A9: Downside: FY26-like partners, 45% activation, median ₹0.45 cr
A10: FY27 | B10: 1.9778 | C10: 2.4305 | D10: 2.9122 | E10: 4.8049 | F10: 1 | G10: 0 | H10: 0.0523
A11: FY28 | B11: 2.9656 | C11: 4.2016 | D11: 5.9861 | E11: 6.0938 | F11: 0.9106 | G11: 0 | H11: 0.0677
A12: FY29 | B12: 4.4333 | C12: 7.0413 | D12: 10.8971 | E12: 6.6872 | F12: 0.44 | G12: 0.0009 | H12: 0.0903
A14: Reading: FY27 loses money by design (~₹0.9 cr). With selected SEA/Gulf partners the loss risk falls to ~9% in FY28 and under 1% in FY29, but 25% in FY29 is a coin flip (46%). If recruits behave like FY26 India partners, the channel loses money in FY28 and has a 44% chance of doing so in FY29. The kill gate (Q2 FY28) stops that path.

Sheet Checks
A1: Check | B1: Value | C1: OK?
A2: FY29 partner share ≥ 25% | B2: =Partner_ramp!D12 -> 0.25268821 | C2: =IF(B2>=0.25,"OK","GAP") -> OK
A3: Blended GM after partner margin ≥ 66% (min of 3 years) | B3: =MIN(GM_floor!B8:D8) -> 0.6757575 | C3: =IF(B3>=0.66,"OK","BREACH") -> OK
A4: Channel roles in FY27 ≤ 6 (VP + partner managers) | B4: =1+Inputs!B28 -> 3 | C4: =IF(B4<=6,"OK","OVER") -> OK
A5: Tier shares sum to 100% each year | B5: =SUM(Inputs!D19:D21)+SUM(Inputs!E19:E21)+SUM(Inputs!F19:F21) -> 3 | C5: =IF(ABS(B5-3)<0.001,"OK","ERROR") -> OK
A6: Inject 3 gap handed to D7 is non-negative (model not more optimistic than D2) | B6: =Inject3!B11 -> 0.30406608 | C6: =IF(B6>=0,"OK","CHECK") -> OK
A7: FY27 channel fixed cost within Inject 1 allocation (₹2.84 cr incl. incentives, excl. MDF) | B7: =Inputs!B33-Inputs!B32 -> 2.44 | C7: =IF(B7<=2.84+0.001,"OK","OVER") -> OK
