Workbook

Sheet README
A1: D3 VALUE MODEL: RANGANATH PRECISION COMPONENTS (CHAKAN PLANT 2)
A2: Company | B2: Strata Sense and Ranganath are fictional; synthetic data (MBA capstone).
A3: Colour code | B3: Green fill = number supplied by the buyer in discovery (who said it is in the Source column). Blue text = input. Yellow fill = Strata assumption to validate in the pilot. Black = formula.
A4: Money | B4: ₹ crore unless marked lakh (1 crore = 100 lakh).
A5: Scenarios | B5: Conservative = what Kavita's 12-month payback rule is tested on (no penalties, no energy, shortest outages). Base and Upside shown for context.
A6: Options | B6: Good = press line (22 presses + ~140 hydraulic pumps/motors = 162 assets). Better = Good + 60 compressors + ~200 critical pumps, chillers and fans (422). Best = every non-spindle asset (670); the 480 CNC spindles stay with the Helix pilot.
A7: Sheets | B7: Inputs · Scope_Price · Value · Payback · TCO_3yr · Discount_Rules · Checks

Sheet Inputs
A1: Inputs
A2: Green = buyer-supplied (role-play, Week 3). Yellow = assumption. Column B-D = Conservative / Base / Upside where they differ.
A4: Input | B4: Conservative | C4: Base | D4: Upside | E4: Source
A5: Major press failures per year | B5: 3 | C5: 3 | D5: 3 | E5: Suresh (plant head): 3 in FY26
A6: Hours down per major press failure | B6: 36 | C6: 48 | D6: 60 | E6: Suresh: 36–60 hours each (Nov event 52 h)
A7: Press-line contribution lost per hour (₹ lakh) | B7: 5.5 | C7: 5.5 | D7: 5.5 | E7: Kavita (CFO): ₹5.5 lakh/h
A8: Machining-line contribution lost per hour (₹ lakh) | B8: 2.4 | C8: 2.4 | D8: 2.4 | E8: Kavita: ₹2.4 lakh/h
A9: OEM penalty per stoppage event (₹ lakh) | B9: 120 | C9: 120 | D9: 120 | E9: Kavita: ₹1.2 cr in Nov (₹8 lakh/h × ~15 h)
A10: OEM stoppage events per year | B10: 1 | C10: 1 | D10: 1 | E10: Suresh/Kavita: one in FY26
A11: Plant maintenance spend per year (₹ cr) | B11: 6.5 | C11: 6.5 | D11: 6.5 | E11: Suresh: ₹6.5 cr
A12: Share of maintenance that is reactive | B12: 0.55 | C12: 0.55 | D12: 0.55 | E12: Suresh: ~55%
A13: Plant spares inventory (₹ cr) | B13: 5.2 | C13: 5.2 | D13: 5.2 | E13: Kavita: ₹5.2 cr (group ₹38 cr)
A14: Group power bill (₹ cr/yr) | B14: 62 | C14: 62 | D14: 62 | E14: Kavita: ₹62 cr
A15: Compressor share of plant electricity | B15: 0.18 | C15: 0.18 | D15: 0.18 | E15: Kavita: ~18%
A16: Payback rule (months, conservative case) | B16: 12 | C16: 12 | D16: 12 | E16: Kavita: under 12 months
... A25: Plants in group (for plant power share) | B25: 9 | C25: 9 | D25: 9 | E25: Kavita: 9 plants; plant power = group ÷ 9 (assumption)
A27: Asset counts, Chakan P2 (Suresh)
A28: CNC spindles (in Helix pilot) | B28: 480 | E28: Suresh: ~1,150 total
A29: Hydraulic presses | B29: 22 | E29: Suresh: ~1,150 total
A30: Pumps/motors on press hydraulics | B30: 140 | E30: Suresh: ~1,150 total
A31: Compressors and blowers | B31: 60 | E31: Suresh: ~1,150 total
A32: Other pumps, fans, chillers, conveyors | B32: 448 | E32: Suresh: ~1,150 total
A33: Total rotating assets | B33: =SUM(B28:B32) -> 1150

Sheet Scope_Price
A1: Scope and price
A2: List prices from DR5; per-asset pricing; hardware can be bundled as a service to keep the contract opex
A4: Item | B4: Good: press line | C4: Better: + compressors & critical utilities | D4: Best: all non-spindle assets | E4: Source
A5: Critical utilities included in Better (count) | C5: 200 | E5: Assumption: most critical of the 448
A6: Monitored assets | B6: =Inputs!$B$29+Inputs!$B$30 -> 162 | C6: =B6+Inputs!$B$31+C5 -> 422 | D6: =B6+Inputs!$B$31+Inputs!$B$32 -> 670
A7: List subscription per asset (₹/yr) | B7: 12500 | C7: 12500 | D7: 12500 | E7: DR5 Strata list price
A8: Hardware per asset, one-off (₹) | B8: 11000 | C8: 11000 | D8: 11000 | E8: DR5: ₹9,000–14,000, avg ~₹11,000
A9: Assets per gateway / gateway cost (₹ lakh) | B9: 150 | C9: 1.2 | E9: DR5
A10: Implementation per plant (₹ lakh) | B10: 6 | E10: DR5
A11: Edge server for on-premise buffering (₹ lakh) | B11: 8 | E11: Assumption; required by RPC CISO rules (Kavita)
A13: Annual subscription = ARR (₹ cr) | B13: =B6*B7/10000000 -> 0.2025 | C13: =C6*C7/10000000 -> 0.5275 | D13: =D6*D7/10000000 -> 0.8375
A14: Hardware + gateways + implementation + edge, one-off (₹ cr) | B14: =(B6*B8+ROUNDUP(B6/$B$9,0)*$C$9*100000+$B$10*100000+$B$11*100000)/10000000 -> 0.3422 | C14: =(C6*C8+ROUNDUP(C6/$B$9,0)*$C$9*100000+$B$10*100000+$B$11*100000)/10000000 -> 0.6402 | D14: =(D6*D8+ROUNDUP(D6/$B$9,0)*$C$9*100000+$B$10*100000+$B$11*100000)/10000000 -> 0.937
A15: Year-1 cost, hardware paid upfront (₹ cr) | B15: =B13+B14 -> 0.5447 | C15: =C13+C14 -> 1.1677 | D15: =D13+D14 -> 1.7745
A16: Hardware-as-a-service: one-offs spread over 36 months at 10% (₹ cr/yr) | B16: =PMT(10%/12,36,-B14)*12 -> 0.13250198 | C16: =PMT(10%/12,36,-C14)*12 -> 0.24788944 | D16: =PMT(10%/12,36,-D14)*12 -> 0.36281225
A17: Annual fee with hardware as a service (₹ cr/yr) | B17: =B13+B16 -> 0.33500198 | C17: =C13+C16 -> 0.77538944 | D17: =D13+D16 -> 1.2003123
A18: Within CFO's own ₹1.5 cr limit? | B18: =IF(B17<=Inputs!$B$17,"Yes","No: committee") -> Yes | C18: =IF(C17<=Inputs!$B$17,"Yes","No: committee") -> Yes | D18: =IF(D17<=Inputs!$B$17,"Yes","No: committee") -> Yes
A20: Paid pilot (press line, 4 months), fee (₹ cr) | B20: 0.25 | E20: Covers hardware and install; credited in full to year 1 on conversion

Sheet Value
A1: Annual value by driver (₹ cr)
A2: Formulas use the Inputs sheet; each driver switches on only for the options that cover those assets
A4: Driver | B4: Good C | C4: Good B | D4: Good U | E4: Better C | F4: Better B | G4: Better U | H4: Best C | I4: Best B | J4: Best U
A5: Press downtime avoided | B5: =Inputs!$B$5*Inputs!$B$6*Inputs!$B$19*Inputs!$B$18*Inputs!$B$7/100 -> 1.17612 | C5: =Inputs!$C$5*Inputs!$C$6*Inputs!$C$19*Inputs!$C$18*Inputs!$C$7/100 -> 2.97 | D5: =Inputs!$D$5*Inputs!$D$6*Inputs!$D$19*Inputs!$D$18*Inputs!$D$7/100 -> 5.63805 | E5: =Inputs!$B$5*Inputs!$B$6*Inputs!$B$19*Inputs!$B$18*Inputs!$B$7/100 -> 1.17612 | F5: =Inputs!$C$5*Inputs!$C$6*Inputs!$C$19*Inputs!$C$18*Inputs!$C$7/100 -> 2.97 | G5: =Inputs!$D$5*Inputs!$D$6*Inputs!$D$19*Inputs!$D$18*Inputs!$D$7/100 -> 5.63805 | H5: =Inputs!$B$5*Inputs!$B$6*Inputs!$B$19*Inputs!$B$18*Inputs!$B$7/100 -> 1.17612 | I5: =Inputs!$C$5*Inputs!$C$6*Inputs!$C$19*Inputs!$C$18*Inputs!$C$7/100 -> 2.97 | J5: =Inputs!$D$5*Inputs!$D$6*Inputs!$D$19*Inputs!$D$18*Inputs!$D$7/100 -> 5.63805
A6: OEM penalties avoided | B6: =Inputs!$B$10*Inputs!$B$9*Inputs!$B$20*Inputs!$B$18/100 -> 0 | C6: =Inputs!$C$10*Inputs!$C$9*Inputs!$C$20*Inputs!$C$18/100 -> 0.3 | D6: =Inputs!$D$10*Inputs!$D$9*Inputs!$D$20*Inputs!$D$18/100 -> 0.53868 | E6: =Inputs!$B$10*Inputs!$B$9*Inputs!$B$20*Inputs!$B$18/100 -> 0 | F6: =Inputs!$C$10*Inputs!$C$9*Inputs!$C$20*Inputs!$C$18/100 -> 0.3 | G6: =Inputs!$D$10*Inputs!$D$9*Inputs!$D$20*Inputs!$D$18/100 -> 0.53868 | H6: =Inputs!$B$10*Inputs!$B$9*Inputs!$B$20*Inputs!$B$18/100 -> 0 | I6: =Inputs!$C$10*Inputs!$C$9*Inputs!$C$20*Inputs!$C$18/100 -> 0.3 | J6: =Inputs!$D$10*Inputs!$D$9*Inputs!$D$20*Inputs!$D$18/100 -> 0.53868
A7: Machining downtime avoided (utility failures) | B7: =0 -> 0 | C7: =0 -> 0 | D7: =0 -> 0 | E7: =Inputs!$B$21*Inputs!$B$8/100*1 -> 0 | F7: =Inputs!$C$21*Inputs!$C$8/100*1 -> 0.48 | G7: =Inputs!$D$21*Inputs!$D$8/100*1 -> 0.96 | H7: =Inputs!$B$21*Inputs!$B$8/100*1.3 -> 0 | I7: =Inputs!$C$21*Inputs!$C$8/100*1.3 -> 0.624 | J7: =Inputs!$D$21*Inputs!$D$8/100*1.3 -> 1.248
A8: Reactive maintenance saved | B8: =Inputs!$B$11*Inputs!$B$12*B14*Inputs!$B$22 -> 0.0715 | C8: =Inputs!$C$11*Inputs!$C$12*C14*Inputs!$C$22 -> 0.10725 | D8: =Inputs!$D$11*Inputs!$D$12*D14*Inputs!$D$22 -> 0.143 | E8: =Inputs!$B$11*Inputs!$B$12*E14*Inputs!$B$22 -> 0.1287 | F8: =Inputs!$C$11*Inputs!$C$12*F14*Inputs!$C$22 -> 0.19305 | G8: =Inputs!$D$11*Inputs!$D$12*G14*Inputs!$D$22 -> 0.2574 | H8: =Inputs!$B$11*Inputs!$B$12*H14*Inputs!$B$22 -> 0.1716 | I8: =Inputs!$C$11*Inputs!$C$12*I14*Inputs!$C$22 -> 0.2574 | J8: =Inputs!$D$11*Inputs!$D$12*J14*Inputs!$D$22 -> 0.3432
A9: Compressor energy saved | B9: =0 -> 0 | C9: =0 -> 0 | D9: =0 -> 0 | E9: =Inputs!$B$14/Inputs!$B$25*Inputs!$B$15*Inputs!$B$23 -> 0 | F9: =Inputs!$C$14/Inputs!$C$25*Inputs!$C$15*Inputs!$C$23 -> 0.0496 | G9: =Inputs!$D$14/Inputs!$D$25*Inputs!$D$15*Inputs!$D$23 -> 0.0868 | H9: =Inputs!$B$14/Inputs!$B$25*Inputs!$B$15*Inputs!$B$23 -> 0 | I9: =Inputs!$C$14/Inputs!$C$25*Inputs!$C$15*Inputs!$C$23 -> 0.0496 | J9: =Inputs!$D$14/Inputs!$D$25*Inputs!$D$15*Inputs!$D$23 -> 0.0868
A10: Total annual value | B10: =SUM(B5:B9) -> 1.24762 | C10: =SUM(C5:C9) -> 3.37725 | D10: =SUM(D5:D9) -> 6.31973 | E10: =SUM(E5:E9) -> 1.30482 | F10: =SUM(F5:F9) -> 3.99265 | G10: =SUM(G5:G9) -> 7.48093 | H10: =SUM(H5:H9) -> 1.34772 | I10: =SUM(I5:I9) -> 4.201 | J10: =SUM(J5:J9) -> 7.85473
A12: One-off cash from lower spares inventory | B12: =Inputs!$B$13*B15*Inputs!$B$24 -> 0.052 | C12: =Inputs!$C$13*C15*Inputs!$C$24 -> 0.0832 | D12: =Inputs!$D$13*D15*Inputs!$D$24 -> 0.104 | E12: =Inputs!$B$13*E15*Inputs!$B$24 -> 0.091 | F12: =Inputs!$C$13*F15*Inputs!$C$24 -> 0.1456 | G12: =Inputs!$D$13*G15*Inputs!$D$24 -> 0.182 | H12: =Inputs!$B$13*H15*Inputs!$B$24 -> 0.13 | I12: =Inputs!$C$13*I15*Inputs!$C$24 -> 0.208 | J12: =Inputs!$D$13*J15*Inputs!$D$24 -> 0.26
A14: Share of maintenance spend on monitored assets | B14: 0.25 | C14: 0.25 | D14: 0.25 | E14: 0.45 | F14: 0.45 | G14: 0.45 | H14: 0.6 | I14: 0.6 | J14: 0.6
A15: Share of spares for monitored assets | B15: 0.2 | C15: 0.2 | D15: 0.2 | E15: 0.35 | F15: 0.35 | G15: 0.35 | H15: 0.5 | I15: 0.5 | J15: 0.5
A17: Best adds 30% more machining-hours saved than Better (wider utility coverage): assumption.

Sheet Payback
A1: Payback and ROI
A2: Payback months = annual fee (hardware as a service) ÷ annual value × 12. Tested on Conservative.
A4: Measure | B4: Good C | C4: Good B | D4: Good U | E4: Better C | F4: Better B | G4: Better U | H4: Best C | I4: Best B | J4: Best U
A5: Annual value (₹ cr) | B5: =Value!B10 -> 1.24762 | C5: =Value!C10 -> 3.37725 | D5: =Value!D10 -> 6.31973 | E5: =Value!E10 -> 1.30482 | F5: =Value!F10 -> 3.99265 | G5: =Value!G10 -> 7.48093 | H5: =Value!H10 -> 1.34772 | I5: =Value!I10 -> 4.201 | J5: =Value!J10 -> 7.85473
A6: Annual fee incl. hardware as a service (₹ cr) | B6: =Scope_Price!B17 -> 0.33500198 | C6: =Scope_Price!B17 -> 0.33500198 | D6: =Scope_Price!B17 -> 0.33500198 | E6: =Scope_Price!C17 -> 0.77538944 | F6: =Scope_Price!C17 -> 0.77538944 | G6: =Scope_Price!C17 -> 0.77538944 | H6: =Scope_Price!D17 -> 1.2003123 | I6: =Scope_Price!D17 -> 1.2003123 | J6: =Scope_Price!D17 -> 1.2003123
A7: Net annual benefit (₹ cr) | B7: =B5-B6 -> 0.91261802 | C7: =C5-C6 -> 3.042248 | D7: =D5-D6 -> 5.984728 | E7: =E5-E6 -> 0.52943056 | F7: =F5-F6 -> 3.2172606 | G7: =G5-G6 -> 6.7055406 | H7: =H5-H6 -> 0.14740775 | I7: =I5-I6 -> 3.0006877 | J7: =J5-J6 -> 6.6544177
A8: Payback (months) | B8: =IF(B5>0,B6/B5*12,"n/a") -> 3.222154 | C8: =IF(C5>0,C6/C5*12,"n/a") -> 1.1903246 | D8: =IF(D5>0,D6/D5*12,"n/a") -> 0.63610688 | E8: =IF(E5>0,E6/E5*12,"n/a") -> 7.1310014 | F8: =IF(F5>0,F6/F5*12,"n/a") -> 2.3304505 | G8: =IF(G5>0,G6/G5*12,"n/a") -> 1.2437856 | H8: =IF(H5>0,H6/H5*12,"n/a") -> 10.687492 | I8: =IF(I5>0,I6/I5*12,"n/a") -> 3.4286472 | J8: =IF(J5>0,J6/J5*12,"n/a") -> 1.8337673
A9: Value ÷ fee (x) | B9: =IF(B6>0,B5/B6,0) -> 3.7242168 | C9: =IF(C6>0,C5/C6,0) -> 10.081284 | D9: =IF(D6>0,D5/D6,0) -> 18.864754 | E9: =IF(E6>0,E5/E6,0) -> 1.6827931 | F9: =IF(F6>0,F5/F6,0) -> 5.149219 | G9: =IF(G6>0,G5/G6,0) -> 9.6479648 | H9: =IF(H6>0,H5/H6,0) -> 1.1228078 | I9: =IF(I6>0,I5/I6,0) -> 3.4999226 | J9: =IF(J6>0,J5/J6,0) -> 6.5439055
A10: Meets CFO 12-month rule? (Conservative) | B10: =IF(B8<=Inputs!$B$16,"Yes","No") -> Yes | E10: =IF(E8<=Inputs!$B$16,"Yes","No") -> Yes | H10: =IF(H8<=Inputs!$B$16,"Yes","No") -> Yes

Sheet TCO_3yr
A1: Three-year total cost and value-adjusted comparison (Good scope: press line)
A2: DR5 list prices. Helix year 1 is free only with a 3-year MES renewal (Kavita).
A4: Item | B4: Strata Cortex | C4: HelixAsset | D4: TrueSense AI | E4: Source / note
A5: Assets in scope | B5: =Scope_Price!B6 -> 162 | C5: =Scope_Price!B6 -> 162 | D5: =Scope_Price!B6 -> 162
A6: Subscription per asset per year (₹) | B6: =Scope_Price!B7 -> 12500 | C6: 9500 | D6: 7800 | E6: DR5 list prices
A7: Years charged out of 3 | B7: 3 | C7: 2 | D7: 3 | E7: Helix: year 1 free with 3-year MES lock-in
A8: Sensor hardware per asset (₹) | B8: =Scope_Price!B8 -> 11000 | C8: 13000 | D8: 8000 | E8: DR5: presses are not wired to Helix PLCs and have no online sensors today (Suresh)
A9: Other one-offs (gateways, implementation, edge) (₹ cr) | B9: =Scope_Price!B14-Scope_Price!B6*Scope_Price!B8/10000000 -> 0.164 | C9: 0.08 | D9: 0.1 | E9: Rival integration/edge costs: assumption
A10: Three-year cost (₹ cr) | B10: =B5*B6*B7/10000000+B5*B8/10000000+B9 -> 0.9497 | C10: =C5*C6*C7/10000000+C5*C8/10000000+C9 -> 0.5984 | D10: =D5*D6*D7/10000000+D5*D8/10000000+D9 -> 0.60868
A11: Share of press failures caught early (base) | B11: =Inputs!$C$18 -> 0.5 | C11: 0.2 | D11: 0.3 | E11: Helix sees PLC tags only; TrueSense weaker on hydraulic/low-speed assets (DR5). Assumptions to prove head-to-head in the pilot.
A12: Three-year value, base (₹ cr) | B12: =3*(Value!$C$5*B11/$B$11+Value!$C$6*B11/$B$11+Value!$C$8) -> 10.13175 | C12: =3*(Value!$C$5*C11/$B$11+Value!$C$6*C11/$B$11+Value!$C$8) -> 4.24575 | D12: =3*(Value!$C$5*D11/$B$11+Value!$C$6*D11/$B$11+Value!$C$8) -> 6.20775
A13: Three-year net value (₹ cr) | B13: =B12-B10 -> 9.18205 | C13: =C12-C10 -> 3.64735 | D13: =D12-D10 -> 5.59907
A14: Strata cost premium vs rival (₹ cr, 3 years) | C14: =B10-C10 -> 0.3513 | D14: =B10-D10 -> 0.34102
A15: Strata net-value advantage vs rival (₹ cr, 3 years) | C15: =B13-C13 -> 5.5347 | D15: =B13-D13 -> 3.58298
A17: Reading: Strata costs more over three years; it only wins if it catches materially more press failures. The pilot must prove that, so the detection rate is the pilot's first success criterion. Not costed: the value of avoiding a 3-year MES lock-in.

Sheet Discount_Rules
A1: Discount rules: every point is traded for something
A2: List ₹12,500 per asset per year. FY26 average discount was 19% and bought no extra wins (D1).
A4: Give (discount off subscription) | B4: Max % | C4: Get (what RPC commits)
A5: Three-year term | B5: 0.08 | C5: Contracted 3-year subscription with annual payment
A6: Annual payment in advance | B6: 0.03 | C6: 12 months paid upfront
A7: Second-site commitment | B7: 0.05 | C7: Signed option to extend to a Chennai forging plant within 12 months of conversion
A8: Reference and case study | B8: 0.02 | C8: Named reference, site visit and a published case study after 6 months
A9: Maximum total discount | B9: =MIN(0.15,SUM(B5:B8)) -> 0.15 | C9: Hard cap 15% (brief target: average discount ≤ 14%)
A10: Floor price per asset (₹/yr) | B10: =Scope_Price!B7*(1-B9) -> 10625
A12: Never traded | C12: Hardware below cost · a free pilot without a signed conversion price · outcome-linked fees without a measured baseline · discounts for 'matching Helix year-1 free'
A14: Outcome-linked option (no discount) | C14: 15% of the annual subscription at risk, paid only if agreed avoided-downtime hours are met; measured from Suresh's paper press log as baseline.
A16: Negotiation test: Neha asks 30% off | B16: 0.3 | C16: =IF(B16>B9,"Above the 15% cap: counter with give-gets; walk away below floor","Within rules") -> Above the 15% cap: counter with give-gets; walk away below floor

Sheet Checks
A1: Checks
A4: Check | B4: Value | C4: OK?
A5: Asset total = ~1,150 (Suresh) | B5: =Inputs!$B$33 -> 1150 | C5: =IF(ABS(B5-1150)<=10,"OK","CHECK") -> OK
A6: Better year-1 fee within CFO limit | B6: =Scope_Price!C17 -> 0.77538944 | C6: =IF(B6<=Inputs!$B$17,"OK","COMMITTEE") -> OK
A7: Good payback, conservative (months) | B7: =Payback!B8 -> 3.222154 | C7: =IF(B7<=Inputs!$B$16,"OK","FAILS RULE") -> OK
A8: Better payback, conservative (months) | B8: =Payback!E8 -> 7.1310014 | C8: =IF(B8<=Inputs!$B$16,"OK","FAILS RULE") -> OK
A9: Max discount ≤ 15% | B9: =Discount_Rules!B9 -> 0.15 | C9: =IF(B9<=0.15,"OK","OVER") -> OK
A10: Nov OEM penalty reconciles (₹8 lakh × 15 h = ₹120 lakh) | B10: =Inputs!$B$9 -> 120 | C10: =IF(B10=8*15,"OK","CHECK") -> OK
